Workbook

Sheet DASHBOARD
A1: DASHBOARD GENERAL DE COMPRAS | I1: Pendientes generados en junta | L1: PENDIENTES GENERALES
I2: FALSE | L2: FALSE
A3: Pendientes sin OC | C3: # Proyectos sin OVT-INT | E3: #OC Pendientes de enviar | I3: FALSE | L3: FALSE
A4: =COUNTIF(A10:A1000,"<>") -> 0 | C4: =IFERROR(__xludf.DUMMYFUNCTION("Countunique(filter(G10:G1000,G10:G1000<>""""))"),1.0) -> 1 | I4: FALSE | L4: FALSE
I5: FALSE | L5: FALSE
A6: OC sin Pago | C6: OC sin factura | I6: FALSE | L6: FALSE
I7: FALSE | L7: FALSE
L8: FALSE
A9: Proyecto | B9: Código | C9: Descripción | D9: Cantidad | E9: Proveedor | G9: Proyecto | H9: Descripción | I9: OV-INT | J9: Status de Interempresa
B10: ALT 039 | C10: GALONES DE GEL CONDUCTOR | D10: 2 | E10: PRONAMAC | I10: N/A | J10: TRUE
B11: ALFA-FLEX | C11: Lámpara de examinación | D11: 2 | E11: RIMSA | I11: N/A | J11: TRUE
B12: 137579
B13: 866389 | C13: CENTRAL DE MONITOREO PARA MÚLTIPLES CAMAS (14 MONITORES) | D13: 1 | E13: PHILIPS | I13: N/A | J13: FALSE
B14: 866424 | C14: PIC iX Hardware | D14: 1 | E14: PHILIPS | I14: N/A | J14: FALSE
B15: 866126 | C15: 24" Widescreen LCD Display - touch | D15: 1 | E15: PHILIPS | I15: N/A | J15: FALSE
B16: 866126 | C16: 24" Widescreen LCD Display - touch | D16: 1 | E16: PHILIPS | I16: N/A | J16: FALSE
B17: 867392 | C17: Layer 2 Switch | D17: 1 | E17: PHILIPS | I17: N/A | J17: FALSE
B18: 866389 | C18: CENTRAL DE MONITOREO PARA MÚLTIPLES CAMAS (8 MONITORES) | D18: 1 | E18: PHILIPS | I18: N/A | J18: FALSE
B19: 866424 | C19: PIC iX Hardware | D19: 1 | E19: PHILIPS | I19: N/A | J19: FALSE
B20: 866126 | C20: 24" Widescreen LCD Display - touch | D20: 1 | E20: PHILIPS | I20: N/A | J20: FALSE
B21: 866126 | C21: 24" Widescreen LCD Display - touch | D21: 1 | E21: PHILIPS | I21: N/A | J21: FALSE
B22: 867392 | C22: Layer 2 Switch | D22: 1 | E22: PHILIPS | I22: N/A | J22: FALSE
B23: 21078ST | C23: Skin Temperature Probe, Reusable | D23: 44 | E23: HOSPIINNOVA | I23: N/A | J23: TRUE
B24: M1668A | C24: CBL 5 Lead ECG Trunk AAMI/IEC 2.7m | D24: 22 | E24: PHILIPS | I24: N/A | J24: TRUE
B25: WP010-MX | C25: Wall Mount with adjustable height | D25: 22 | E25: TPX | I25: MPC28349 | J25: FALSE
B26: 31050522 | C26: ELECTRODO DE MONITOREO ECG PACIENTE ADULTO MT200 CAJA CON 10 SOBRES CON 100 PIEZAS | D26: 66 | E26: HOSPIINNOVA | J26: FALSE
B27: 31424743 | C27: ELECTRODOS NEONATAL DE ECG | D27: 2200 | E27: HOSPIINNOVA | J27: FALSE
B28: 21078ST | C28: Skin Temperature Probe, Reusable | D28: 62 | E28: HOSPIINNOVA | I28: N/A | J28: TRUE
B29: M1668A | C29: CBL 5 Lead ECG Trunk AAMI/IEC 2.7m | D29: 31 | E29: PHILIPS | I29: N/A | J29: TRUE
B30: RP050 | C30: Rolling Stand--For Patient Monitor | D30: 31 | E30: TPX | I30: MPC28349 | J30: FALSE
B31: PL-MX | C31: BASE PARA MONITOR PHILIPS MX | D31: 31 | E31: TPX | J31: FALSE
B32: 31424743 | C32: ELECTRODOS NEONATAL | D32: 3100 | E32: HOSPIINNOVA | J32: FALSE
B33: 31050522 | C33: ELECTRODO DE MONITOREO ECG PACIENTE ADULTO MT200 CAJA CON 10 SOBRES CON 100 PIEZAS | D33: 93 | E33: HOSPIINNOVA | J33: FALSE
B34: 21078ST | C34: Skin Temperature Probe, Reusable | D34: 30 | E34: HOSPIINNOVA | I34: N/A | J34: TRUE
B35: M1668A | C35: CBL 5 Lead ECG Trunk AAMI/IEC 2.7m | D35: 15 | E35: PHILIPS | I35: N/A | J35: TRUE
B36: RP050 | C36: Rolling Stand--For Patient Monitor | D36: 15 | E36: TPX | I36: MPC28349 | J36: FALSE
B37: PL-MX | C37: BASE PARA MONITOR PHILIPS MX | D37: 15 | E37: TPX | J37: FALSE
B38: 31424743 | C38: ELECTRODOS NEONATAL | D38: 1500 | E38: HOSPIINNOVA | J38: FALSE
B39: 31050522 | C39: ELECTRODO DE MONITOREO ECG PACIENTE ADULTO MT200 CAJA CON 10 SOBRES CON 100 PIEZAS | D39: 45 | E39: HOSPIINNOVA | J39: FALSE
B40: 21078ST | C40: Skin Temperature Probe, Reusable | D40: 2 | E40: HOSPIINNOVA | I40: N/A | J40: TRUE
B41: M1668A | C41: CBL 5 Lead ECG Trunk AAMI/IEC 2.7m | D41: 1 | E41: PHILIPS | I41: N/A | J41: TRUE
B42: WP010-MX | C42: Wall Mount with adjustable height | D42: 1 | E42: TPX | I42: MPC28349 | J42: FALSE
B43: 31424743 | C43: ELECTRODOS NEONATAL | D43: 100 | E43: HOSPIINNOVA | J43: FALSE
B44: 31050522 | C44: ELECTRODO DE MONITOREO ECG PACIENTE ADULTO MT200 CAJA CON 10 SOBRES CON 100 PIEZAS | D44: 3 | E44: HOSPIINNOVA | J44: FALSE
B45: 21078ST | C45: Skin Temperature Probe, Reusable | D45: 2 | E45: HOSPIINNOVA | I45: N/A | J45: TRUE
B46: M1668A | C46: CBL 5 Lead ECG Trunk AAMI/IEC 2.7m | D46: 2 | E46: PHILIPS | I46: N/A | J46: TRUE
B47: WP010-MX | C47: Wall Mount with adjustable height | D47: 2 | E47: TPX | I47: MPC28349 | J47: FALSE
B48: 31424743 | C48: ELECTRODOS NEONATAL | D48: 200 | E48: HOSPIINNOVA | J48: FALSE
B49: 31050522 | C49: ELECTRODO DE MONITOREO ECG PACIENTE ADULTO MT200 CAJA CON 10 SOBRES CON 100 PIEZAS | D49: 6 | E49: HOSPIINNOVA | J49: FALSE
B50: 21078ST | C50: Skin Temperature Probe, Reusable | D50: 8 | E50: HOSPIINNOVA | I50: N/A | J50: TRUE
B51: M1668A | C51: CBL 5 Lead ECG Trunk AAMI/IEC 2.7m | D51: 8 | E51: PHILIPS | I51: N/A | J51: TRUE
B52: RP050 | C52: Rolling Stand--For Patient Monitor | D52: 8 | E52: TPX | I52: MPC28349 | J52: FALSE
B53: PL-MX | C53: BASE PARA MONITOR PHILIPS MX | D53: 8 | E53: TPX | J53: FALSE
B54: 31424743 | C54: ELECTRODOS NEONATAL | D54: 800 | E54: HOSPIINNOVA | J54: FALSE
B55: 31050522 | C55: ELECTRODO DE MONITOREO ECG PACIENTE ADULTO MT200 CAJA CON 10 SOBRES CON 100 PIEZAS | D55: 24 | E55: HOSPIINNOVA | J55: FALSE
B56: M2702A.1 | C56: Monitor materno fetal (Cardiotocógrafo) | D56: 1 | E56: PHILIPS | I56: MAN13294 | J56: FALSE
B57: 867246 | C57: Avalon US Transducer | D57: 2 | E57: PHILIPS | I57: MAN13294 | J57: FALSE
B58: 867248 | C58: Avalon TOCO | D58: 2 | E58: PHILIPS | I58: MAN13294 | J58: FALSE
B59: 989803143411 | C59: Remote Event Marker | D59: 1 | E59: PHILIPS | I59: MAN13294 | J59: FALSE
B60: CINFM | C60: Reusable Abdominal Belt- 60mm Wd 1.3M Lg | D60: 2 | E60: GUSTAVO EDUARDO AVILA WOO | I60: MAN13294 | J60: FALSE
B61: RP050-FM | C61: Carro de transporte TPX para Cardiotoco Avalon FM20/FM30 | D61: 1 | E61: TPX | I61: - | J61: FALSE
B62: M1910A | C62: Fetal monitoring recording paper | D62: 1 | E62: AKUSUL | I62: MAN13294 | J62: FALSE
B63: 866064.3 | C63: Monitor IntelliVue MX500 | D63: 1 | E63: PHILIPS | J63: FALSE
B64: 867036.4 | C64: Módulo IntelliVue MMX | D64: 1 | E64: PHILIPS | J64: FALSE
B65: M1029A | C65: Temperature Parameter Module | D65: 1 | E65: PHILIPS | J65: FALSE
B66: M1191BL | C66: Reusable Adult SpO2 Sensor | D66: 1 | E66: PHILIPS | J66: FALSE
B67: 989803205871 | C67: SPO2 Reus Ped-Adult Glove Sensor M1192A | D67: 1 | E67: PHILIPS | J67: FALSE
B68: M1941A | C68: CBL SpO2 Extension Cable 2m | D68: 1 | E68: PHILIPS | J68: FALSE
B69: M1668A | C69: CBL 5 Lead ECG Trunk AAMI/IEC 2.7m | D69: 1 | E69: PHILIPS | J69: FALSE
B70: M1644A | C70: CBL 5 Leadset Snap AAMI ICU | D70: 1 | E70: PHILIPS | J70: FALSE
B71: 989803209771 | C71: Adult NIBP Air Hose 3.0m | D71: 1 | E71: PHILIPS | J71: FALSE
B72: M2501A | C72: Mainstream Sensor | D72: 1 | E72: PHILIPS | J72: FALSE
B73: 989803206591 | C73: Airway Adapter-Reusable-Adult/Pediatric | D73: 1 | E73: PHILIPS | J73: FALSE
B74: M4552B | C74: Easy Care Cuff 1 Hose Infant (1) | D74: 1 | E74: PHILIPS | J74: FALSE
B75: M4553B | C75: Easy Care Cuff 1 Hose Pediatric (1) | D75: 1 | E75: PHILIPS | J75: FALSE
B76: M4555B | C76: Easy Care Cuff 1 Hose Adult (1) | D76: 1 | E76: PHILIPS | J76: FALSE
B77: 21078ST | C77: SENSOR DE TEMPERATURA | D77: 1 | E77: HOSPIINNOVA | J77: FALSE
B78: MX960 | C78: PLACA DE TRANSDUCTOR LOGICAL REUSABLE | D78: 1 | E78: ATSA | J78: FALSE
B79: MX261 | C79: SOPORTE P/ PLACA DE TRANSDUCTOR LOGICAL | D79: 1 | E79: ATSA | J79: FALSE
B80: MX262 | C80: BRACKET PARA DOS TRANSDUCTORES | D80: 1 | E80: ATSA | J80: FALSE
B81: BC-HP-MX1 | C81: CABLE TRONCAL MONITOR PHILIPS TECNOLOGIA LOGICAL | D81: 1 | E81: ATSA | J81: FALSE
B82: MX9604A | C82: KIT DE MONITOREO LOGICAL DESECHABLE | D82: 10 | E82: ATSA | J82: FALSE
B83: WP010-MX | C83: Brazo de soporte giratorio TPX | D83: 1 | E83: TPX | J83: FALSE
B84: 866062.2 | C84: Monitor IntelliVue MX450 | D84: 1 | E84: PHILIPS | J84: FALSE
B85: 867036.1 | C85: Módulo IntelliVue MMX | D85: 1 | E85: PHILIPS | J85: FALSE
B86: M1668A | C86: CBL 5 Lead ECG Trunk AAMI/IEC 2.7m | D86: 4 | E86: PHILIPS | J86: FALSE
B87: M1644A | C87: CBL 5 Leadset Snap AAMI ICU | D87: 4 | E87: PHILIPS | J87: FALSE
B88: M1669A | C88: CBL 3 Lead ECG Trunk AAMI/IEC 2.7m | D88: 2 | E88: PHILIPS | J88: FALSE
B89: M1673A | C89: CBL 3 Leadset Snap AAMI ICU | D89: 2 | E89: PHILIPS | J89: FALSE
B90: M4555B | C90: Easy Care Cuff 1 Hose Adult (1) | D90: 5 | E90: PHILIPS | J90: FALSE
B91: 989803209771 | C91: Adult NIBP Air Hose 3.0m | D91: 1 | E91: PHILIPS | J91: FALSE
B92: 989803205871 | C92: SPO2 Reus Ped-Adult Glove Sensor M1192A | D92: 2 | E92: PHILIPS | J92: FALSE
B93: 989803205881 | C93: SPO2 Reus Neo Hnd-Ft Wrap Sensor M1193A | D93: 2 | E93: PHILIPS | J93: FALSE
B94: M1941A | C94: CBL SpO2 Extension Cable 2m | D94: 1 | E94: PHILIPS | J94: FALSE
B95: M1191BL | C95: Reusable Adult SpO2 Sensor | D95: 2 | E95: PHILIPS | J95: FALSE
B96: M4552B | C96: Easy Care Cuff 1 Hose Infant (1) | D96: 5 | E96: PHILIPS | J96: FALSE
B97: M4553B | C97: Easy Care Cuff 1 Hose Pediatric (1) | D97: 6 | E97: PHILIPS | J97: FALSE
B98: 21078ST | C98: SENSOR DE TEMPERATURA | D98: 6 | E98: HOSPIINNOVA | J98: FALSE
B99: RP050 | C99: Carro de transporte TPX para monitor de S.V. Philips Efficia/Goldway | D99: 1 | E99: TPX | J99: FALSE
B100: 866062.2 | C100: Monitor IntelliVue MX450 | D100: 5 | E100: PHILIPS | J100: FALSE
...

Sheet CMR
A1: #Orden de compra | B1: Código | C1: Descripción | D1: Cantidad | E1: Referencia
A2: MAN01120 | B2: MA-1164-2 | C2: CART - TOP CONTROL PANEL FRU KIT ASSEMBLY | D2: 1 | E2: GARANTÍA | SD-UK01007876 / SD-UK01007881
A3: MAN01120 | B3: MA-1182-1 | C3: Haptic Linkage FRU Kit Assembly | D3: 2 | E3: GARANTÍA | SD-UK01007876 / SD-UK01007881
A4: MAN01120 | B4: EA-0816-A | C4: USB 2.0 left angle A to micro-B cable 762mm | D4: 1 | E4: GARANTÍA | SD-UK01007876 / SD-UK01007881
A5: MAN01120 | B5: MA-1173-1 | C5: Console Top Deck Electronics FRU Kit Assembly | D5: 1 | E5: GARANTÍA | SD-UK01007876 / SD-UK01007881
A6: MAN01115 | B6: 10400 | C6: Instrumento Gancho monopolar Versius | D6: 1 | E6: MATERIAL PARA ENTRENAMIENTO
A7: MAN01115 | B7: 10200 | C7: Pinzas de agarre bipolares Maryland Versius. | D7: 2 | E7: MATERIAL PARA ENTRENAMIENTO
A8: MAN01115 | B8: 10500 | C8: Curved Scissors | D8: 1 | E8: MATERIAL PARA ENTRENAMIENTO
A9: MAN01115 | B9: 10600 | C9: Tijeras curvas monopolares Versius. | D9: 2 | E9: MATERIAL PARA ENTRENAMIENTO
A10: MAN01115 | B10: 10300 | C10: Pinzas de agarre Grasper fenestradas Versius. | D10: 1 | E10: MATERIAL PARA ENTRENAMIENTO
A11: MAN01115 | B11: 10100 | C11: Instrumento Portaagujas Versius | D11: 1 | E11: MATERIAL PARA ENTRENAMIENTO
A12: MAN01115 | B12: 20901 | C12: Tapa aislante de cabeza de cubierta | D12: 1 | E12: MATERIAL PARA ENTRENAMIENTO
A13: MAN01115 | B13: 20101 | C13: Cubierta Versius para unidad de instrumento (Corta) | D13: 1 | E13: MATERIAL PARA ENTRENAMIENTO
A14: MAN01115 | B14: 20301 | C14: Cubierta Versius para unidad de instrumento (Larga) | D14: 1 | E14: MATERIAL PARA ENTRENAMIENTO
A15: MAN01115 | B15: 10002 | C15: Paquete de accesorios con forro aislante flexible | D15: 1 | E15: MATERIAL PARA ENTRENAMIENTO
A16: MAN01115 | B16: 20401 | C16: Cubierta Versius para unidad de visualización (Larga) | D16: 1 | E16: MATERIAL PARA ENTRENAMIENTO
A17: MAN01115 | B17: 20501 | C17: Cubierta Versius para cabeza de Cámara | D17: 1 | E17: MATERIAL PARA ENTRENAMIENTO
A18: MAN01114 | B18: MA-1162-1 | C18: Arm Backup Battery FRU Kit Assembly | D18: 3 | E18: GARANTÍA | MA-1162-1
A19: MAN01111 | B19: 10600-T | C19: 10600-T | D19: 6 | E19: STOCK / SERVICIO
A20: MAN01110 | B20: 10100 | C20: Instrumento Portaagujas Versius | D20: 21 | E20: STOCK
A21: MAN01110 | B21: 10200 | C21: Pinzas de agarre bipolares Maryland Versius. | D21: 20 | E21: STOCK
A22: MAN01110 | B22: 10300 | C22: Pinzas de agarre Grasper fenestradas Versius. | D22: 17 | E22: STOCK
A23: MAN01110 | B23: 10400 | C23: Instrumento Gancho monopolar Versius | D23: 33 | E23: STOCK
A24: MAN01110 | B24: 10600 | C24: Tijeras curvas monopolares Versius. | D24: 21 | E24: STOCK
A25: MAN01110 | B25: 20101 | C25: Cubierta Versius para unidad de instrumento (Corta) | D25: 75 | E25: STOCK
A26: MAN01110 | B26: 20201 | C26: Cubierta Versius para unidad de visualización (Corta) | D26: 25 | E26: STOCK
A27: MAN01110 | B27: 20501 | C27: Cubierta Versius para cabeza de Cámara | D27: 11 | E27: STOCK
A28: MAN01110 | B28: 20901 | C28: Tapa aislante de cabeza de cubierta | D28: 5 | E28: STOCK
A29: MAN01110 | B29: 10002 | C29: Paquete de accesorios con forro aislante flexible | D29: 15 | E29: STOCK
A30: MAN01004 | B30: V-SS-1000 | C30: VERSIUS Surgeon Console | D30: 2 | E30: IMSS Bienestar | N-62-2026
A31: MAN01004 | B31: V-SS-2000 | C31: VERSIUS Instrument Bedside Unit | D31: 6 | E31: IMSS Bienestar | N-62-2026
A32: MAN01004 | B32: V-SS-3000 | C32: VERSIUS Visualisation Bedside Unit | D32: 2 | E32: IMSS Bienestar | N-62-2026
A33: MAN01004 | B33: 90900 | C33: Versius Camera Head | D33: 4 | E33: IMSS Bienestar | N-62-2026
A34: MAN01004 | B34: 90907 | C34: Versius 30 Degree Endoscope | D34: 4 | E34: IMSS Bienestar | N-62-2026
A35: MAN01004 | B35: 90908 | C35: Versius 0 Degree Endoscope | D35: 4 | E35: IMSS Bienestar | N-62-2026
A36: MAN01004 | B36: 90903 | C36: Light Cable (3.5m) | D36: 8 | E36: IMSS Bienestar | N-62-2026
A37: MAN01004 | B37: 90904 | C37: Light Source | D37: 2 | E37: IMSS Bienestar | N-62-2026
A38: MAN01004 | B38: 90200/10 | C38: Auxiliary Screen Cable -Long | D38: 4 | E38: IMSS Bienestar | N-62-2026
A39: MAN01004 | B39: 90200/5 | C39: Auxiliary Screen Cable -Short | D39: 4 | E39: IMSS Bienestar | N-62-2026
A40: MAN01004 | B40: 90100/10 | C40: Video Feed Cable-Long | D40: 4 | E40: IMSS Bienestar | N-62-2026
A41: MAN01004 | B41: 90100/5 | C41: Video Feed Cable-Short | D41: 4 | E41: IMSS Bienestar | N-62-2026
A42: MAN01004 | B42: 90800/10 | C42: Bedside Unit Cable-Long | D42: 8 | E42: IMSS Bienestar | N-62-2026
A43: MAN01004 | B43: 90800/5 | C43: Bedside Unit Cable-Short | D43: 8 | E43: IMSS Bienestar | N-62-2026
A44: MAN01004 | B44: 90703 | C44: Console Power Cable | D44: 4 | E44: IMSS Bienestar | N-62-2026
A45: MAN01004 | B45: 80000 | C45: 3D Glasses | D45: 20 | E45: IMSS Bienestar | N-62-2026
A46: MAN01004 | B46: 90300 | C46: Bipolar Instrument Cable | D46: 10 | E46: IMSS Bienestar | N-62-2026
A47: MAN01004 | B47: 90400 | C47: Bipolar Bedside Unit Cable | D47: 6 | E47: IMSS Bienestar | N-62-2026
A48: MAN01004 | B48: 90500 | C48: Monopolar Instrument Cable | D48: 10 | E48: IMSS Bienestar | N-62-2026
A49: MAN01004 | B49: 90600 | C49: Monopolar Bedside unit Cable | D49: 6 | E49: IMSS Bienestar | N-62-2026
A50: MAN01004 | B50: 90920 | C50: Richard Wolf Light Source Power Cable | D50: 2 | E50: IMSS Bienestar | N-62-2026
A51: MAN01004 | B51: 90906 | C51: Adapter Project Side | D51: 2 | E51: IMSS Bienestar | N-62-2026
A52: MAN01004 | B52: 91000/5 | C52: Ethernet Cable 5m | D52: 2 | E52: IMSS Bienestar | N-62-2026
A53: MAN01004 | B53: VT-1010 | C53: Versius Trainer Kit Unit | D53: 2 | E53: IMSS Bienestar | N-62-2026
A54: MAN00988 | B54: BOM-00345 TK-0001 | C54: Field Programing Toolkit | D54: 1 | E54: IMSS Bienestar | N-62-2026 SERVICE TOOL KITS
A55: MAN00988 | B55: BOM-00247 TK-0002 | C55: Field Service Toolkit | D55: 1 | E55: IMSS Bienestar | N-62-2026 SERVICE TOOL KITS
A56: MAN00988 | B56: BOM-00375 TK-0003 | C56: SAS Toolkit consumables | D56: 1 | E56: IMSS Bienestar | N-62-2026 SERVICE TOOL KITS
A57: MAN00988 | B57: MA-0658 | C57: Versius Black box Assy | D57: 1 | E57: IMSS Bienestar | N-62-2026 SERVICE TOOL KITS
A58: MAN00988 | B58: TK0017 | C58: BSU Baseplate FRU Toolkit | D58: 1 | E58: IMSS Bienestar | N-62-2026 SERVICE TOOL KITS
A59: MAN00987 | B59: MA-1190 | C59: J8 and Interface FRU Kit Assembly | D59: 2 | E59: IMSS Bienestar | N-62-2026 STOCK MINIMO
A60: MAN00987 | B60: MA-1189 | C60: J67 FRU Kit Assembly | D60: 4 | E60: IMSS Bienestar | N-62-2026 STOCK MINIMO
A61: MAN00987 | B61: MA-1195 | C61: Cart Brake and Battery Controller PCB FRU KiT Assembly | D61: 2 | E61: IMSS Bienestar | N-62-2026 STOCK MINIMO
A62: MAN00987 | B62: MA-1162 | C62: Arm Backup Battery FRU Kit Assembly | D62: 14 | E62: IMSS Bienestar | N-62-2026 STOCK MINIMO
A63: MAN00987 | B63: MA-1179 | C63: Right Handgrip Lower FRU Kit Assembly | D63: 2 | E63: IMSS Bienestar | N-62-2026 STOCK MINIMO
... A74: MAN00986 | B74: 10400-NC | C74: Instrumento Gancho monopolar Versius - NO CLINICO | D74: 6 | E74: IMSS Bienestar | N-62-2026 NC
A75: MAN00984 | B75: 10100 | C75: Instrumento Portaagujas Versius | D75: 16 | E75: IMSS Bienestar | N-62-2026 MES 2
A76: MAN00984 | B76: 10200 | C76: Pinzas de agarre bipolares Maryland Versius. | D76: 8 | E76: IMSS Bienestar | N-62-2026 MES 2
A77: MAN00984 | B77: 10300 | C77: Pinzas de agarre Grasper fenestradas Versius. | D77: 12 | E77: IMSS Bienestar | N-62-2026 MES 2
A78: MAN00984 | B78: 10400 | C78: Instrumento Gancho monopolar Versius | D78: 11 | E78: IMSS Bienestar | N-62-2026 MES 2
A79: MAN00984 | B79: 10600 | C79: Tijeras curvas monopolares Versius. | D79: 13 | E79: IMSS Bienestar | N-62-2026 MES 2
A80: MAN00984 | B80: 20101 | C80: Cubierta Versius para unidad de instrumento (Corta) | D80: 111 | E80: IMSS Bienestar | N-62-2026 MES 2
A81: MAN00984 | B81: 20201 | C81: Cubierta Versius para unidad de visualización (Corta) | D81: 20 | E81: IMSS Bienestar | N-62-2026 MES 2
A82: MAN00984 | B82: 20501 | C82: Cubierta Versius para cabeza de Cámara | D82: 8 | E82: IMSS Bienestar | N-62-2026 MES 2
A83: MAN00984 | B83: 20901 | C83: Tapa aislante de cabeza de cubierta | D83: 4 | E83: IMSS Bienestar | N-62-2026 MES 2
A84: MAN00984 | B84: 10002 | C84: Paquete de accesorios con forro aislante flexible | D84: 12 | E84: IMSS Bienestar | N-62-2026 MES 2
A85: MAN00983 | B85: 10100 | C85: Instrumento Portaagujas Versius | D85: 14 | E85: IMSS Bienestar | N-62-2026 MES 1
A86: MAN00983 | B86: 10200 | C86: Pinzas de agarre bipolares Maryland Versius. | D86: 16 | E86: IMSS Bienestar | N-62-2026 MES 1
... A94: MAN00983 | B94: 10002 | C94: Paquete de accesorios con forro aislante flexible | D94: 9 | E94: IMSS Bienestar | N-62-2026 MES 1
A95: MAN00960 | B95: V-SS-1000 | C95: VERSIUS Surgeon Console | D95: 2 | E95: IMSS Bienestar | N-62-2026
A96: MAN00960 | B96: V-SS-2000 | C96: VERSIUS Instrument Bedside Unit | D96: 6 | E96: IMSS Bienestar | N-62-2026
A97: MAN00960 | B97: V-SS-3000 | C97: VERSIUS Visualisation Bedside Unit | D97: 2 | E97: IMSS Bienestar | N-62-2026
A98: MAN00960 | B98: 90900 | C98: Versius Camera Head | D98: 4 | E98: IMSS Bienestar | N-62-2026
A99: MAN00960 | B99: 90907 | C99: Versius 30 Degree Endoscope | D99: 4 | E99: IMSS Bienestar | N-62-2026
A100: MAN00960 | B100: 90908 | C100: Versius 0 Degree Endoscope | D100: 4 | E100: IMSS Bienestar | N-62-2026
A101: MAN00960 | B101: 90903 | C101: Light Cable (3.5m) | D101: 8 | E101: IMSS Bienestar | N-62-2026
A102: MAN00960 | B102: 90904 | C102: Light Source | D102: 2 | E102: IMSS Bienestar | N-62-2026
A103: MAN00960 | B103: 90200/10 | C103: Auxiliary Screen Cable -Long | D103: 4 | E103: IMSS Bienestar | N-62-2026
A104: MAN00960 | B104: 90200/5 | C104: Auxiliary Screen Cable -Short | D104: 4 | E104: IMSS Bienestar | N-62-2026
A105: MAN00960 | B105: 90100/10 | C105: Video Feed Cable-Long | D105: 4 | E105: IMSS Bienestar | N-62-2026
A106: MAN00960 | B106: 90100/5 | C106: Video Feed Cable-Short | D106: 4 | E106: IMSS Bienestar | N-62-2026
A107: MAN00960 | B107: 90800/10 | C107: Bedside Unit Cable-Long | D107: 8 | E107: IMSS Bienestar | N-62-2026
A108: MAN00960 | B108: 90800/5 | C108: Bedside Unit Cable-Short | D108: 8 | E108: IMSS Bienestar | N-62-2026
A109: MAN00960 | B109: 90703 | C109: Console Power Cable | D109: 4 | E109: IMSS Bienestar | N-62-2026
A110: MAN00960 | B110: 80000 | C110: 3D Glasses | D110: 20 | E110: IMSS Bienestar | N-62-2026
A111: MAN00960 | B111: 90300 | C111: Bipolar Instrument Cable | D111: 10 | E111: IMSS Bienestar | N-62-2026
A112: MAN00960 | B112: 90400 | C112: Bipolar Bedside Unit Cable | D112: 6 | E112: IMSS Bienestar | N-62-2026
A113: MAN00960 | B113: 90500 | C113: Monopolar Instrument Cable | D113: 10 | E113: IMSS Bienestar | N-62-2026
A114: MAN00960 | B114: 90600 | C114: Monopolar Bedside unit Cable | D114: 6 | E114: IMSS Bienestar | N-62-2026
A115: MAN00960 | B115: 90920 | C115: Richard Wolf Light Source Power Cable | D115: 2 | E115: IMSS Bienestar | N-62-2026
A116: MAN00960 | B116: 90906 | C116: Adapter Project Side | D116: 2 | E116: IMSS Bienestar | N-62-2026
A117: MAN00960 | B117: 91000/5 | C117: Ethernet Cable 5m | D117: 2 | E117: IMSS Bienestar | N-62-2026
...

Sheet B2B
A1: VENTAS
A2: Modelo | B2: Descripción | C2: Total | F2: DESCRIPCIÓN | G2: CÓDIGO | H2: PROVEEDOR | I2: STOCK | J2: PRESENTACIÓN
A3: 867246 | B3: Avalon US Transducer | C3: 2 | F3: Adult NIBP Air Hose 3.0m | G3: 989803209771 | H3: PHILIPS | I3: 32 | J3: pz
A4: 867248 | B4: Avalon TOCO MP Transducer | C4: 1 | F4: Airway Adapter-Reusable-Adult/Pediatric | G4: 989803206591 | H4: PHILIPS | I4: 17 | J4: pz
A5: 867249 | B5: Transductor Avalon TOCO+ | C5: 1 | F5: BATTERY 10.8V 6Ah LiIon | G5: M4605A | H5: PHILIPS | I5: 0 | J5: pz
A6: 989803136891 | B6: Recording Paper | C6: 4 | F6: CBL 10 Lead ECG Trunk AAMI/IEC 2m | G6: M1663A | H6: PHILIPS | I6: 25 | J6: pz
A7: 989803145061 | B7: CBL 5 Lead ECG Trunk AAMI/IEC 2.7m (M1668A) | C7: 106 | F7: CBL 3 Lead ECG Trunk AAMI/IEC 2.7m | G7: M1669A | H7: PHILIPS | I7: 415 | J7: pz
A8: 989803161991 | B8: Quick Connect SpO2 Probe MRI | C8: 1 | F8: CBL 5 Lead ECG Trunk AAMI/IEC 2.7m | G8: M1668A | H8: PHILIPS | I8: 21 | J8: pz
A9: 989803166581 | B9: Quick Connect SpO2 Grip Neo 20/box | C9: 1 | F9: CBL 5 Leadset Grabber AAMI ICU | G9: M1968A | H9: PHILIPS | I9: 33 | J9: pz
A10: 989803167551 | B10: Neonatal Soft Single-Patient NIBP Cuffs | C10: 6 | F10: CBL 5 Leadset Grabber Chest AAMI ICU | G10: M1976A | H10: PHILIPS | I10: 1 | J10: pz
A11: 989803169491 | B11: Battery MRI 14.8V 5.08 AH UL | C11: 1 | F11: CBL 5 Leadset Snap AAMI ICU | G11: M1644A | H11: PHILIPS | I11: 5 | J11: pz
A12: 989803170121 | B12: Avanced filter ECG cable | C12: 1 | F12: CBL Cardiac Output Cable | G12: M1642A | H12: PHILIPS | I12: 27 | J12: pz
A13: 989803182621 | B13: NiBP Cuff Single Lumen Pediatric | C13: 1 | F13: CBL SpO2 Extension Cable 2m | G13: M1941A | H13: PHILIPS | I13: 22 | J13: pz
A14: 989803182641 | B14: NiBP Cuff Single Lumen Adult | C14: 1 | F14: CBL Unshielded 3 Ld Miniclip AAMI 0.7m | G14: M1624A | H14: PHILIPS | I14: 9 | J14: pz
A15: 989803190381 | B15: Efficia 50mm Chem Therm Paper No Lines | C15: 15 | F15: Co-Set(TM) Injectate Temp Probe - 7'9 | G15: 23001A | H15: PHILIPS | I15: 0 | J15: pz
A16: 989803193731 | B16: Expression MR ECG Leads AAMI Standard Philips | C16: 4 | F16: Easy Care Cuff 1 Hose Adult (1) | G16: M4555B | H16: PHILIPS | I16: 48 | J16: pz
... A18: 989803203561 | B18: Sensor de temperatura Esofágico / Rectal, 12 FR Philips | C18: 11 | F18: Ice Bath Temperature Probe | G18: 23002A | H18: PHILIPS | I18: 0 | J18: pz
A19: 989803205901 | B19: Sensor SpO2 Reusable Adult Clip Sensor M1196A | C19: 20 | F19: IntelliVue Capnography Extension | G19: 867040 | H19: PHILIPS | I19: 5 | J19: pz
A20: 989803209771 | B20: Adult NIBP Air Hose 3.0m | C20: 30 | F20: Mainstream Sensor | G20: M2501A | H20: PHILIPS | I20: 78 | J20: pz
A21: 989803210521 | B21: BATERIA 3S3P LiIon 10.7V 7.1Ah | C21: 11 | F21: Neonatal NIBP Air Hose 3.0m | G21: 989803209751 | H21: PHILIPS | I21: 147 | J21: pz
A22: M1191B | B22: Reusable Adult SpO2 Sensor | C22: 12 | F22: Neonatal Soft Single-Patient Cuff Size#1 | G22: M1866S | H22: PHILIPS | I22: 796 | J22: pz
A23: M1191BL | B23: Reusable Adult SpO2 Sensor | C23: 18 | F23: Neonatal Soft Single-Patient Cuff Size#2 | G23: M1868S | H23: PHILIPS | I23: 1801 | J23: pz
A24: M1571A | B24: Comfort Care Cuff Infant | C24: 5 | F24: Neonatal Soft Single-Patient Cuff Size#3 | G24: M1870S | H24: PHILIPS | I24: 5556 | J24: pz
A25: M1573A | B25: Reusable NIBP Comfort Cuff/small adult | C25: 2 | F25: Reusable Adult SpO2 Sensor | G25: M1191B | H25: PHILIPS | I25: 414 | J25: pz
A26: M1574A | B26: Reusable NIBP Comfort Cuff/ adult | C26: 10 | F26: SPO2 Reus Neo Hnd-Ft Wrap Sensor M1193A | G26: 989803205881 | H26: PHILIPS | I26: 4 | J26: pz
A27: M1576A | B27: Reusable NIBP Comfort Cuff/thigh | C27: 1 | F27: SPO2 Reus Ped-Adult Glove Sensor M1192A | G27: 989803205871 | H27: PHILIPS | I27: 33 | J27: pz
A28: M1599B | B28: Adult Pressure Interconnect Cable 3.0m | C28: 100 | F28: Temperature Parameter Module | G28: M1029A | H28: PHILIPS | I28: 84 | J28: pz
A29: M1642A | B29: CBL Cardiac Output Cable | C29: 9 | F29: Thermal Array Recorder Module | G29: M1116C | H29: PHILIPS | I29: 0 | J29: pz
A30: M1644A | B30: CBL 5 Leadset Snap AAMI ICU | C30: 83
A31: M1663A | B31: CBL 10 Lead ECG Trunk AAMI/IEC 2m | C31: 7
A32: M1669A | B32: CBL 3 Lead ECG Trunk AAMI/IEC 2.7m | C32: 15
A33: M1671A | B33: CBL 3 Leadset Grabber AAMI ICU | C33: 0
A34: M1673A | B34: CBL 3 Leadset Snap AAMI ICU | C34: 10
A35: M1870S | B35: Neonatal Soft Single-Patient Cuff Size#3 | C35: 15
A36: M1910A | B36: Fetal monitoring recording pape | C36: 215
A37: M1941A | B37: CBL SpO2 Extension Cable 2m | C37: 106
A38: M1943AL | B38: Sp02 8-pin D-sub Adapter cable 3m (8pin) | C38: 2
A39: M1943NL | B39: Sp02 8-pin D-sub Adapter cbl (8pin) Oxi | C39: 5
A40: M1968A | B40: CBL 5 Leadset Grabber AAMI ICU | C40: 13
A41: M2267A | B41: Calibration Regulator | C41: 1
... A49: M4816A | B49: Thermal Array Paper | C49: 40

Sheet IMSS BIENESTAR QUINTANA ROO IM-
A1: PEDIDO | B1: PARTIDA | C1: DESCRIPCIÓN | D1: CANTIDAD | E1: UDM | F1: MARCA | G1: MODELO | H1: CÓDIGO | I1: PROVEEDOR | J1: Empresa que vende | K1: COSTO | L1: MONEDA COSTO | M1: EMPRESA QUE COMPRA | N1: OC | O1: B2B | P1: OBSERVACIONES | Q1: ESTATUS | R1: OV-INT | S1: Status de Interempresa | T1: OC-INT | U1: Status de Interempresa | V1: FACTURA CIEGA | W1: PEDIMENTO | X1: CARTA DE FABRICACION
A2: MAN12662 | B2: 8 | C2: Báscula electrónica | D2: 1 | E2: PIEZA | F2: SECA | G2: 354m | H2: seca 354 | I2: SECA | J2: Manprec | K2: 3900 | L2: MXN | M2: Manprec | N2: Stock | O2: FALSE | P2: Se recupera equipo en OC MAN00863 | Q2: ALMACEN 11 | R2: N/A | S2: TRUE | T2: N/A | U2: TRUE | V2: COMPARTIDO | W2: COMPARTIDO | X2: COMPARTIDO
A3: MAN12662 | B3: 9 | C3: Cama camilla radiotransparente | D3: 1 | E3: PIEZA | F3: GIVAS | G3: BT1205 | H3: BT1205 | I3: GIVAS | J3: Manprec | L3: EURO | M3: ITH | N3: Stock | O3: FALSE | Q3: STOCK | R3: ITH00917 | S3: TRUE | T3: MAN00890 | U3: TRUE | V3: COMPARTIDO | W3: COMPARTIDO | X3: COMPARTIDO
A4: MAN12662 | B4: 15 | C4: Electrocardiógrafo multicanal con interpretación. | D4: 1 | E4: PIEZA | F4: SCHILLER | G4: CARDIOVIT AT-102 G2 | H4: 0A.108000 | I4: SCHILLER | J4: Manprec | K4: 65190 | L4: USD | M4: ITH | N4: Stock | O4: TRUE | Q4: ALMACEN 11 | R4: ITH00917 | S4: TRUE | T4: MAN00890 | U4: TRUE | V4: COMPARTIDO | W4: COMPARTIDO | X4: COMPARTIDO
B5: 15 | C5: SCHILLER Culprit Coronary Artery Algorithm Software (CCAA) AT-102 G2 Identifies the site of obstruction in the coronary artery and | D5: 1 | E5: PIEZA | F5: Schiller | H5: 5.108004 | I5: SCHILLER | J5: Manprec | K5: 816 | L5: USD | M5: ITH | N5: ITH00171 | O5: FALSE | Q5: ALMACEN 11 | R5: ITH00917 | S5: TRUE | T5: MAN00890 | U5: TRUE
B6: 15 | C6: Carro de transporte | D6: 1 | E6: PIEZA | F6: TPX | H6: RP050-6 | I6: TPX | J6: Manprec | K6: 127.5 | L6: USD | M6: MPC | N6: Stock | O6: FALSE | Q6: ALMACEN 11 | R6: MPC25190 | S6: TRUE | T6: MAN00871 | U6: TRUE
B7: 15 | C7: Gel 250 ML | D7: 2 | E7: PIEZA | F7: Ultrasonic | H7: ALT 040 | I7: PRONAMAC | J7: Manprec | K7: 55.86 | L7: MXN | M7: MPC | N7: Stock | O7: FALSE | Q7: ALMACEN 11 | R7: MPC25190 | S7: TRUE | T7: MAN00871 | U7: TRUE
B8: 15 | C8: Thermal chart paper AT-102, AT-102 plus, AT-102 G2, | D8: 3 | E8: PIEZA | F8: Schiller | H8: 2.157050 | I8: SCHILLER | J8: Manprec | K8: 18 | L8: USD | M8: ITH | N8: ITH00171 | O8: TRUE | Q8: ALMACEN 11 | R8: ITH00917 | S8: TRUE | T8: MAN00890 | U8: TRUE
B9: 15 | C9: Electrodos desechables Bolsa de 100 pz | D9: 5 | E9: PIEZA | F9: Cardinal | H9: 31050522 | I9: HOSPIINNOVA | J9: Manprec | K9: 250 | L9: MXN | M9: Manprec | N9: Stock | O9: FALSE | Q9: ALMACEN 11 | R9: N/A | S9: TRUE | T9: N/A | U9: TRUE
B10: 15 | C10: Li-ion Battery AT-102 G2 (caution AT-102 G2 must | D10: 1 | E10: PIEZA | F10: Schiller | H10: 4.350066A | I10: SCHILLER | J10: Manprec | K10: 368 | L10: USD | M10: ITH | N10: ITH00171 | O10: FALSE | Q10: ALMACEN 11 | R10: ITH00917 | S10: TRUE | T10: MAN00890 | U10: TRUE
A11: MAN12662 | B11: 50 | C11: Unidad radiológica portatil digital | D11: 1 | E11: PIEZA | F11: PHILIPS | G11: MOBILEDIAGNOST WDR | H11: WDR40PMX | I11: PHILIPS | J11: Manprec | K11: =95000+6000 -> 101000 | L11: USD | M11: Manprec | N11: MAN00865 | O11: FALSE | Q11: CON PHILIPS | R11: N/A | S11: TRUE | T11: N/A | U11: TRUE | V11: COMPARTIDO | W11: COMPARTIDO | X11: SOLICITADO
C12: Mandil plomado | D12: 1 | E12: PIEZA | H12: JDS536 | I12: NAFARRATE | J12: Manprec | K12: 2931.6 | L12: MXN | M12: Manprec | N12: MAN00862 | O12: FALSE | Q12: ALMACEN 11 | R12: N/A | S12: TRUE | T12: N/A | U12: TRUE
C13: Goggles de plomo | D13: 1 | E13: PIEZA | H13: JD53 | I13: NAFARRATE | J13: Manprec | K13: 2981 | L13: MXN | M13: Manprec | N13: MAN00862 | O13: FALSE | Q13: ALMACEN 11 | R13: N/A | S13: TRUE | T13: N/A | U13: TRUE
C14: Protector de tiroides de plomo | D14: 1 | E14: PIEZA | H14: JD611NSL | I14: NAFARRATE | J14: Manprec | K14: 543.4 | L14: MXN | M14: Manprec | N14: Stock | O14: FALSE | Q14: ALMACEN 11 | R14: MPC25190 | S14: TRUE | T14: MAN00871 | U14: TRUE
C15: Protector de gonadas de plomo | D15: 1 | E15: PIEZA | H15: JD806L | I15: NAFARRATE | J15: Manprec | K15: 720.2 | L15: MXN | M15: Manprec | N15: Stock | O15: FALSE | Q15: ALMACEN 11 | R15: MPC25190 | S15: TRUE | T15: MAN00871 | U15: TRUE
C16: Guantes de plomo | D16: 1 | E16: PIEZA | H16: JD100V-DKB | I16: NAFARRATE | J16: Manprec | K16: 3731.6 | L16: MXN | M16: Manprec | N16: Stock | O16: FALSE | Q16: ALMACEN 11 | R16: MPC25190 | S16: TRUE | T16: MAN00871 | U16: TRUE
C17: DVD's Torre de 100 pz | D17: 2 | E17: C/100 | H17: B00O0IDJT2 | I17: AMAZON | J17: Manprec | K17: 382.76 | L17: MXN | M17: MPC | N17: MPC03113 | O17: FALSE | Q17: ALMACEN 11 | R17: MPC25190 | S17: TRUE | T17: MAN00871 | U17: TRUE
C18: Regulador supresor de picos 3KVA | D18: 1 | E18: PIEZA | H18: LAN-15 | I18: MERCADOLIBRE | J18: Manprec | K18: 12753.88 | L18: MXN | M18: MPC | N18: MPC03823 | O18: FALSE | Q18: SE COMPRO POR MERCADOLIBRE | R18: MPC25190 | S18: TRUE | T18: MAN00871 | U18: TRUE
A19: MAN12662 | B19: 71 | C19: REFRIGERADOR VERTICAL PARA LABORATORIO CAP. 20 PIES CUBICOS | D19: 1 | E19: EQUIPO | F19: REFRIMED | G19: RVCCDV-20 | H19: RVCCDV-20 | I19: REFRIMED | J19: Manprec | K19: 62000 | L19: MXN | M19: Manprec | N19: MAN00861 | O19: FALSE | Q19: ENTREGADA | R19: N/A | S19: TRUE | T19: N/A | U19: TRUE | V19: COMPARTIDO | W19: N/A | X19: COMPARTIDO

Sheet SSCDMX- SRMAS-JUDCCM.ADQ.150-25
A1: PEDIDO | B1: PARTIDA | C1: DESCRIPCIÓN | D1: CANTIDAD | E1: UDM | F1: MARCA | G1: MODELO | H1: CÓDIGO | I1: PROVEEDOR | J1: Empresa que vende | K1: COSTO | L1: MONEDA COSTO | M1: EMPRESA QUE COMPRA | N1: OC | O1: B2B | P1: OBSERVACIONES | Q1: ESTATUS | R1: OV-INT | S1: Status de Interempresa | T1: OC-INT | U1: Status de Interempresa
A2: MPC27121 / MPC26257 | B2: 1 | C2: Densitómetro oseo | D2: 2 | E2: PZ | F2: Hologic | G2: Discovery Wii | H2: Discovery Wii | I2: SMH | J2: MPC | K2: 52000 | L2: USD | M2: CEO | N2: CEO00131 | O2: FALSE | P2: - | Q2: ENTREGADO DIRECTO | R2: CEO00273 | S2: TRUE | T2: MPC04010 | U2: TRUE
C3: UPS 2KVA | D3: 2 | E3: PZ | J3: MPC | K3: 0 | L3: USD | M3: CEO | N3: CEO00131 | O3: FALSE | P3: Parte del equipo | Q3: ENTREGADO DIRECTO | R3: CEO00273 | S3: TRUE | T3: MPC04010 | U3: TRUE
C4: Impresora | D4: 2 | E4: PZ | J4: MPC | K4: 0 | L4: USD | M4: CEO | N4: CEO00131 | O4: FALSE | P4: Parte del equipo | Q4: ENTREGADO DIRECTO | R4: CEO00273 | S4: TRUE | T4: MPC04010 | U4: TRUE
C5: Cartucho de tinta o toner para impresoa | D5: 2 | E5: PZ | J5: MPC | K5: 0 | L5: USD | M5: CEO | N5: CEO00131 | O5: FALSE | P5: Parte del equipo | Q5: ENTREGADO DIRECTO | R5: CEO00273 | S5: TRUE | T5: MPC04010 | U5: TRUE
C6: CPU con monitor. | D6: 2 | E6: PZ | J6: MPC | K6: 0 | L6: USD | M6: CEO | N6: CEO00131 | O6: FALSE | P6: Parte del equipo | Q6: ENTREGADO DIRECTO | R6: CEO00273 | S6: TRUE | T6: MPC04010 | U6: TRUE
C7: paquete de 500 hojas | D7: 2 | E7: PZ | J7: MPC | L7: MXN | M7: MPC | N7: Stock | O7: FALSE | P7: Se enviará sin salida | Q7: EN ALMACEN 11 | S7: FALSE | U7: FALSE
B8: 2 | C8: Congelador para vacunas | D8: 2 | E8: PZ | F8: Refrimed | G8: CH-7 | H8: CH-7 | I8: REFRIMED | J8: MPC | K8: 28675.5 | L8: MXN | M8: MPC | N8: MPC03814 | O8: FALSE | P8: Se cancelan para este proyecto | Q8: CANCELADO | R8: N/A | S8: TRUE | T8: N/A | U8: TRUE
B9: 8 | C9: Ultrasonografo | D9: 2 | E9: PZ | F9: Philips | G9: Affiniti 30 | I9: PHILIPS | J9: MPC | L9: USD | M9: Manprec | O9: FALSE | P9: - | Q9: ENTREGADO DIRECTO | R9: MAN12887 | S9: TRUE | T9: MPC03977 | U9: TRUE
C10: UPS EN LÍNEA DE DOBLE CONVERSIÓN, AUTOMÁTICO QUE INCLUYA SUPRESOR DE PICOS. | D10: 2 | E10: PZ | H10: PA MG+15-2200-UN | I10: ALTERNATIVA | J10: MPC | K10: 3884 | L10: MXN | M10: Gamit | N10: GAM00042 | O10: FALSE | P10: - | Q10: EN ALMACEN 11 | R10: GAM00148 | S10: TRUE | T10: MPC04024 | U10: TRUE
C11: CD'S | D11: 20 | E11: PZ | J11: MPC | M11: MPC | O11: FALSE | P11: - | Q11: EN ALMACEN 11 | R11: N/A | S11: TRUE | T11: N/A | U11: TRUE
C12: CAJAS DE PELÍCULA PARA IMPRESORA | D12: 2 | E12: PZ | J12: MPC | M12: MPC | O12: FALSE | P12: - | Q12: CANCELADO | R12: N/A | S12: TRUE | T12: N/A | U12: TRUE
C13: GALONES DE GEL CONDUCTOR | D13: 2 | E13: PZ | H13: ALT 039 | I13: PRONAMAC | J13: MPC | M13: MPC | O13: FALSE | P13: - | Q13: EN ALMACEN 11 | R13: N/A | S13: TRUE | T13: N/A | U13: TRUE
B14: 10 | C14: Lámpara de examinación | D14: 2 | E14: PZ | F14: Rimsa | G14: AlfaFlex | H14: ALFA-FLEX | I14: RIMSA | J14: MPC | K14: 184.8 | L14: EURO | M14: MPC | O14: FALSE | P14: - | Q14: EN ALMACEN 11 | R14: N/A | S14: TRUE | T14: N/A | U14: TRUE
B15: 11 | C15: Estatoscopio de capsula doble | D15: 25 | E15: PZ | F15: Welch Allyn | G15: Spectrum | H15: WA5079-135 | I15: NAFARRATE | J15: MPC | K15: 1601.8 | L15: MXN | M15: MPC | N15: MPC03818 | O15: FALSE | P15: - | Q15: EN ALMACEN 11 | R15: N/A | S15: TRUE | T15: N/A | U15: TRUE
B16: 12 | C16: Estuche de diagnostico | D16: 10 | E16: PZ | F16: Welch Allyn | G16: 97200-CL | H16: WA97200-CL | I16: NAFARRATE | J16: MPC | K16: 7373.8 | L16: MXN | M16: MPC | N16: MPC03818 | O16: FALSE | P16: - | Q16: EN ALMACEN 11 | R16: N/A | S16: TRUE | T16: N/A | U16: TRUE
C17: ESPECULO REUSABLE P/OTOSCOPIO JUEGO CON 4 | D17: 10 | E17: PZ | F17: Welch Allyn | H17: WA24400-U | I17: NAFARRATE | J17: MPC | K17: 208.8 | L17: MXN | M17: MPC | N17: MPC03818 | O17: FALSE | P17: - | Q17: EN ALMACEN 11 | R17: N/A | S17: TRUE | T17: N/A | U17: TRUE
C18: Porta depresor de lengua 3.5 halógeno | D18: 10 | E18: PZ | F18: Welch Allyn | H18: WA28100 | I18: NAFARRATE | J18: MPC | K18: 4262.4 | L18: MXN | M18: MPC | N18: MPC03818 | O18: FALSE | P18: - | Q18: EN ALMACEN 11 | R18: N/A | S18: TRUE | T18: N/A | U18: TRUE
B19: 14 | C19: Refrigerador de laboratorio | D19: 1 | E19: PZ | F19: Refrimed | G19: RVCCDV-2 | H19: RVCCDV-2 | I19: REFRIMED | J19: MPC | K19: 23775.3 | L19: MXN | M19: MPC | N19: MPC03814 | O19: FALSE | P19: Se cancelan para este proyecto | Q19: CANCELADO | R19: N/A | S19: TRUE | T19: N/A | U19: TRUE
B20: 15 | C20: Refrigerador para vacunas | D20: 1 | E20: PZ | F20: Refrimed | G20: RVASCV-17 | H20: RVASCV-17 | I20: REFRIMED | J20: MPC | K20: 61978.6 | L20: MXN | M20: MPC | N20: MPC03814 | O20: FALSE | P20: Se cancelan para este proyecto | Q20: CANCELADO | R20: N/A | S20: TRUE | T20: N/A | U20: TRUE
B21: 18 | C21: Analizador de composición corporal | D21: 2 | E21: PZ | F21: Seca | G21: 525 | H21: Seca 525 | I21: SECA | J21: MPC | K21: =141631.88+7200+7200 -> 156031.88 | L21: MXN | M21: Manprec | N21: MAN00894 | O21: FALSE | P21: - | Q21: EN ALMACEN 11 | R21: MAN12887 | S21: TRUE | T21: MPC03977 | U21: TRUE
C22: LAPTOP WINDOWS 10 PRO 64, 4 GB RAM, DISCO DURO 1 TB, PUERTOS USB, CONECTIVIDAD LAN/ETHERNET, INTERFAZ CONEXIÓN IMPRESORA | D22: 2 | E22: PZ | F22: ThinkPad E14 Gen 5 | H22: B0G8SYBGST | I22: AMAZON | J22: MPC | K22: 7757.76 | L22: MXN | M22: MPC | N22: MPC03994 | O22: FALSE | P22: - | Q22: EN ALMACEN 11 | R22: N/A | S22: TRUE | T22: N/A | U22: TRUE

Sheet SEMAR MAZATLAN
A1: PEDIDO | B1: PARTIDA | C1: DESCRIPCIÓN | D1: CANTIDAD | E1: UDM | F1: MARCA | G1: MODELO | H1: CÓDIGO | I1: PROVEEDOR | J1: Empresa que vende | K1: COSTO | L1: MONEDA COSTO | M1: EMPRESA QUE COMPRA | N1: OC | O1: B2B | P1: OBSERVACIONES | Q1: ESTATUS | R1: OV-INT | S1: Status de Interempresa | T1: OC-INT | U1: Status de Interempresa
A2: ITH00948 | B2: 1 | C2: Unidad De Electrocirugía De Uso General | D2: 1 | E2: PZ | F2: WEM | G2: SS501SX | H2: 06725 | I2: METRONIC | J2: ITH | K2: 119949 | L2: MXN | M2: MPC | N2: MPC04136 | O2: FALSE | Q2: EN ALMACEN 11 | R2: MPC27570 | S2: TRUE | T2: ITH00190 | U2: TRUE
A3: ITH00948 | C3: WEM - CARRO PORTA EQUIPO | D3: 1 | E3: PZ | H3: 04718 | I3: METRONIC | J3: ITH | K3: 16913 | L3: MXN | M3: MPC | N3: MPC04136 | O3: FALSE | Q3: EN ALMACEN 11 | R3: MPC27570 | S3: TRUE | T3: ITH00190 | U3: TRUE
A4: ITH00948 | C4: WEM SS501SX/SS601MCA - PEDAL MONOPOLAR | D4: 1 | E4: PZ | H4: 06523 | I4: METRONIC | J4: ITH | K4: 13531 | L4: MXN | M4: MPC | N4: MPC04136 | O4: FALSE | Q4: EN ALMACEN 11 | R4: MPC27570 | S4: TRUE | T4: ITH00190 | U4: TRUE
A5: ITH00948 | C5: WEM SS501SX - PEDAL BIPOLAR SIMPLE | D5: 1 | E5: PZ | H5: 09922 | I5: METRONIC | J5: ITH | K5: 7881 | L5: MXN | M5: MPC | N5: MPC04136 | O5: FALSE | Q5: EN ALMACEN 11 | R5: MPC27570 | S5: TRUE | T5: ITH00190 | U5: TRUE
A6: ITH00948 | C6: LÁPIZ RELIANT BUTTON SWITCH Y HOLSTER (3M) | D6: 1 | E6: C/50 | H6: E2516 | I6: METRONIC | J6: ITH | K6: 11800 | L6: MXN | M6: MPC | N6: STOCK | O6: FALSE | Q6: EN ALMACEN 11 | R6: MPC27570 | S6: TRUE | T6: ITH00190 | U6: TRUE
A7: ITH00948 | C7: PLACA REM POLYHESIVE II CON CABLE ADULTO | D7: 1 | E7: C/50 | H7: E7507 | I7: METRONIC | J7: ITH | K7: 5040 | L7: MXN | M7: MPC | N7: MPC04136 | O7: FALSE | Q7: EN ALMACEN 11 | R7: MPC27570 | S7: TRUE | T7: ITH00190 | U7: TRUE
A8: ITH00948 | C8: FORCEPS BIPOLARES - CABLE REUSABLE | D8: 1 | E8: PZ | H8: E0020V | I8: METRONIC | J8: ITH | K8: 4960 | L8: MXN | M8: MPC | N8: STOCK | O8: FALSE | Q8: EN ALMACEN 11 | R8: MPC27570 | S8: TRUE | T8: ITH00190 | U8: TRUE
A9: ITH00948 | C9: FORCEPS BIPOLARES - BAYONETA SCOVILLE 19.7CM - 1.5MM | D9: 1 | E9: PZ | H9: E4051-CT | I9: METRONIC | J9: ITH | K9: 9413 | L9: MXN | M9: MPC | N9: MPC04136 | O9: FALSE | Q9: EN ALMACEN 11 | R9: MPC27570 | S9: TRUE | T9: ITH00190 | U9: TRUE
A10: ITH00948 | C10: FORCEPS BIPOLARES - RECTOS CUSHING 17.8CM - 1.5MM | D10: 1 | E10: PZ | H10: E4052-CT | I10: METRONIC | J10: ITH | K10: 8806 | L10: MXN | M10: MPC | N10: STOCK | O10: FALSE | Q10: EN ALMACEN 11 | R10: MPC27570 | S10: TRUE | T10: ITH00190 | U10: TRUE
A11: ITH00948 | C11: ELECTRODO DE TUNGTENO MICRO AGUJA RECTA 2.13" (5.4CM) | D11: 10 | E11: PZ | H11: E1651 | J11: ITH | K11: 1112.5 | L11: MXN | M11: Manprec | N11: MAN00943 | O11: FALSE | P11: GENERICO | Q11: EN ALMACEN 11 | R11: MAN13176 | S11: TRUE | T11: ITH00189 | U11: TRUE
A12: ITH00948 | C12: ELECTRODO DE TUNGTENO MICRO AGUJA ANGULADO 2.13" (2.13CM) 1CM DE LA PUNTA | D12: 10 | E12: PZ | H12: E1551G | I12: METRONIC | J12: ITH | K12: =7814/150 -> 52.093333 | L12: MXN | M12: MPC | N12: STOCK | O12: FALSE | Q12: EN ALMACEN 11 | R12: MPC27570 | S12: TRUE | T12: ITH00190 | U12: TRUE
A13: ITH00948 | C13: LLETZ BOLA 5MM | D13: 10 | E13: PZ | H13: E1564 | J13: ITH | K13: 200 | L13: MXN | M13: Manprec | N13: MAN00943 | O13: FALSE | P13: GENERICO | Q13: EN ALMACEN 11 | R13: MAN13176 | S13: TRUE | T13: ITH00189 | U13: TRUE
A14: CEO00282 | B14: 2 | C14: Centrifuga | D14: 1 | E14: PZ | F14: THERMO | G14: SORVAL ST1 PLUS | H14: 75016007 | I14: LAB-TECH | J14: CEO | K14: 9901.72 | L14: USD | M14: CEO | N14: CEO00135 | O14: FALSE | Q14: EN ALMACEN 11 | R14: N/A | S14: TRUE | T14: N/A | U14: TRUE
A15: CEO00282 | B15: 3 | C15: Congelador De Laboratorio | D15: 1 | E15: PZ | F15: HERLMER | G15: iLF120-GX | H15: 5222120-1 | I15: LAB-TECH | J15: CEO | K15: 10836.85 | L15: USD | M15: CEO | N15: CEO00135 | O15: FALSE | Q15: EN ALMACEN 11 | R15: N/A | S15: TRUE | T15: N/A | U15: TRUE
A16: MPC27523 | B16: 4 | C16: Monitor De Signos Vitales Para El Traslado Del Paciente | D16: 1 | E16: PZ | F16: PHILIPS | G16: EFFICIA CM12 | H16: 863303.1 | I16: PHILIPS | J16: MPC | K16: 1506.61 | L16: USD | M16: Manprec | N16: STOCK | O16: FALSE | Q16: EN ALMACEN 11 | R16: MAN13177 | S16: TRUE | T16: MPC04272 | U16: TRUE
A17: MPC27523 | C17: CBL 3 Lead ECG Trunk AAMI/IEC 2.7m | D17: 1 | E17: PZ | F17: PHILIPS | H17: M1669A | I17: PHILIPS | J17: MPC | K17: 55.2 | L17: USD | M17: Manprec | N17: STOCK | O17: TRUE | Q17: EN ALMACEN 11 | R17: MAN13177 | S17: TRUE | T17: MPC04272 | U17: TRUE
A18: MPC27523 | C18: CBL 3 Leadset Snap AAMI ICU | D18: 1 | E18: PZ | F18: PHILIPS | H18: M1673A | I18: PHILIPS | J18: MPC | K18: 46.2 | L18: USD | M18: Manprec | N18: STOCK | O18: TRUE | Q18: EN ALMACEN 11 | R18: MAN13177 | S18: TRUE | T18: MPC04272 | U18: TRUE
A19: MPC27523 | C19: Easy Care Cuff 1 Hose Pediatric (1) | D19: 1 | E19: PZ | F19: PHILIPS | H19: M4553B | I19: PHILIPS | J19: MPC | K19: 22.62 | L19: USD | M19: Manprec | N19: STOCK | O19: TRUE | Q19: EN ALMACEN 11 | R19: MAN13177 | S19: TRUE | T19: MPC04272 | U19: TRUE
A20: MPC27523 | C20: Easy Care Cuff 1 Hose Adult (1) | D20: 1 | E20: PZ | F20: PHILIPS | H20: M4555B | I20: PHILIPS | J20: MPC | K20: 11.34 | L20: USD | M20: Manprec | N20: STOCK | O20: TRUE | Q20: EN ALMACEN 11 | R20: MAN13177 | S20: TRUE | T20: MPC04272 | U20: TRUE
A21: MPC27523 | C21: Adult NIBP Air Hose 3.0m | D21: 1 | E21: PZ | F21: PHILIPS | H21: 989803209771 | I21: PHILIPS | J21: MPC | K21: 24.66 | L21: USD | M21: Manprec | N21: STOCK | O21: TRUE | Q21: EN ALMACEN 11 | R21: MAN13177 | S21: TRUE | T21: MPC04272 | U21: TRUE
A22: MPC27523 | C22: SPO2 Reus Neo Hnd-Ft Wrap Sensor M1193A | D22: 1 | E22: PZ | F22: PHILIPS | H22: 989803205881 | I22: PHILIPS | J22: MPC | K22: 101.4 | L22: USD | M22: Manprec | N22: STOCK | O22: TRUE | Q22: EN ALMACEN 11 | R22: MAN13177 | S22: TRUE | T22: MPC04272 | U22: TRUE
A23: MPC27523 | C23: CBL SpO2 Extension Cable 2m | D23: 1 | E23: PZ | F23: PHILIPS | H23: M1941A | I23: PHILIPS | J23: MPC | K23: 46.2 | L23: USD | M23: Manprec | N23: STOCK | O23: TRUE | Q23: EN ALMACEN 11 | R23: MAN13177 | S23: TRUE | T23: MPC04272 | U23: TRUE
A24: MPC27523 | C24: Reusable Adult SpO2 Sensor | D24: 1 | E24: PZ | F24: PHILIPS | H24: M1191B | I24: PHILIPS | J24: MPC | K24: 96.6 | L24: USD | M24: Manprec | N24: STOCK | O24: TRUE | Q24: EN ALMACEN 11 | R24: MAN13177 | S24: TRUE | T24: MPC04272 | U24: TRUE
A25: MPC27523 | C25: Skin Temperature Probe, Reusable | D25: 1 | E25: PZ | F25: HOSPIINNOVA | H25: 21078ST | I25: HOSPIINNOVA | J25: MPC | K25: 1050 | L25: MXN | M25: Manprec | N25: MAN00939 | O25: TRUE | Q25: EN ALMACEN 11 | R25: MAN13177 | S25: TRUE | T25: MPC04272 | U25: TRUE
A26: MPC27523 | C26: Rolling Stand--For Patient Monitor | D26: 1 | E26: PZ | F26: TPX | H26: RP050 | I26: TPX | J26: MPC | K26: 115 | L26: USD | M26: MPC | N26: STOCK | O26: TRUE | Q26: EN ALMACEN 11 | R26: N/A | S26: TRUE | T26: N/A | U26: TRUE
A27: MPC27523 | C27: ELECTRODOS NEONATAL | D27: 35 | E27: B/3 | F27: HOSPIINNOVA | H27: 31424743 | I27: HOSPIINNOVA | J27: MPC | K27: =4900/300 -> 16.333333 | L27: MXN | M27: Manprec | N27: STOCK | O27: FALSE | Q27: EN ALMACEN 11 | R27: MAN13177 | S27: TRUE | T27: MPC04272 | U27: TRUE
A28: MPC27523 | C28: ELECTRODO DE MONITOREO ECG PACIENTE ADULTO MT200 CAJA CON 10 SOBRES CON 100 PIEZAS | D28: 1 | E28: B/100 | F28: HOSPIINNOVA | H28: 31050522 | I28: HOSPIINNOVA | J28: MPC | K28: 250 | L28: MXN | M28: Manprec | N28: STOCK | O28: FALSE | Q28: EN ALMACEN 11 | R28: MAN13177 | S28: TRUE | T28: MPC04272 | U28: TRUE
A29: ITH00948 | B29: 5 | C29: Cama-cuna clínica eléctrica | D29: 2 | E29: PZ | F29: GIVAS | G29: VEGA | H29: EBT509 | I29: GIVAS | J29: ITH | K29: 2029.5 | L29: EURO | M29: ITH | N29: STOCK | O29: FALSE | Q29: EN ALMACEN 11 | R29: N/A | S29: TRUE | T29: N/A | U29: TRUE
A30: ITH00948 | C30: Colchon | D30: 2 | E30: PZ | F30: ACOLSA | H30: D20 | I30: ACOLSA | J30: ITH | K30: 2250 | L30: MXN | M30: MPC | N30: MPC04208 | O30: FALSE | Q30: EN ALMACEN 11 | R30: MPC27570 | S30: TRUE | T30: ITH00190 | U30: TRUE
A31: ITH00948 | C31: COLCHON EXTENSION | D31: 2 | E31: PZ | F31: ACOLSA | H31: D20EXT | I31: ACOLSA | J31: ITH | K31: 450 | L31: MXN | M31: MPC | N31: MPC04208 | O31: FALSE | Q31: EN ALMACEN 11 | R31: MPC27570 | S31: TRUE | T31: ITH00190 | U31: TRUE
A32: ITH00948 | C32: Colchon de precion alterna | D32: 2 | E32: PZ | F32: YUWELL | H32: M5-C | I32: YUWELL | J32: ITH | K32: 120 | L32: USD | M32: ITH | N32: STOCK | O32: FALSE | Q32: EN ALMACEN 11 | R32: N/A | S32: TRUE | T32: N/A | U32: TRUE
A33: MPC27523 | B33: 6 | C33: Cardiotocógrafo con accesorios y carro de transporte | D33: 4 | E33: PZ | F33: PHILIPS | G33: AVALON FM20 | H33: M2702A.1 | I33: PHILIPS | J33: MPC | K33: 2483.65 | L33: USD | M33: Manprec | N33: STOCK | O33: FALSE | Q33: EN ALMACEN 11 | R33: MAN13177 | S33: TRUE | T33: MPC04272 | U33: TRUE
A34: MPC27523 | C34: Avalon US Transducer | D34: 4 | E34: PZ | F34: PHILIPS | H34: 867246 | I34: PHILIPS | J34: MPC | K34: 520.2 | L34: USD | M34: Manprec | N34: STOCK | O34: TRUE | Q34: EN ALMACEN 11 | R34: MAN13177 | S34: TRUE | T34: MPC04272 | U34: TRUE
A35: MPC27523 | C35: Avalon TOCO MP Transducer | D35: 4 | E35: PZ | F35: PHILIPS | H35: 867248 | I35: PHILIPS | J35: MPC | K35: 566.4 | L35: USD | M35: Manprec | N35: STOCK | O35: TRUE | Q35: EN ALMACEN 11 | R35: MAN13177 | S35: TRUE | T35: MPC04272 | U35: TRUE
A36: MPC27523 | C36: Remote Event Marker | D36: 4 | E36: PZ | F36: PHILIPS | H36: 989803143411 | I36: PHILIPS | J36: MPC | K36: 107.4 | L36: USD | M36: Manprec | N36: STOCK | O36: TRUE | Q36: EN ALMACEN 11 | R36: MAN13177 | S36: TRUE | T36: MPC04272 | U36: TRUE
A37: MPC27523 | C37: Reusable Abdominal Belt- 60mm Wd 1.3M Lg | D37: 4 | E37: PZ | F37: HOSPIINNOVA | H37: CINFM | I37: CABLES Y SENSORES | J37: MPC | K37: =1424/10 -> 142.4 | L37: MXN | M37: Manprec | N37: STOCK | O37: TRUE | Q37: EN ALMACEN 11 | R37: MAN13177 | S37: TRUE | T37: MPC04272 | U37: TRUE
A38: MPC27523 | C38: R01 GCX Rollstand: FM20/30 | D38: 4 | E38: PZ | F38: TPX | H38: RP050-FM | I38: TPX | J38: MPC | K38: 115 | L38: USD | M38: MPC | N38: STOCK | O38: TRUE | P38: SE ENTREGAN CARROS TPX | Q38: EN ALMACEN 11 | R38: N/A | S38: TRUE | T38: N/A | U38: TRUE
A39: MPC27523 | C39: Fetal monitoring recording paper | D39: 4 | E39: CAJA | F39: PHILIPS | H39: M1910A | I39: PHILIPS | J39: MPC | K39: 112.2 | L39: USD | M39: Manprec | N39: STOCK | O39: TRUE | Q39: EN ALMACEN 11 | R39: MAN13177 | S39: TRUE | T39: MPC04272 | U39: TRUE
A40: MPC27523 | B40: 7 | C40: Refrigerador con congelador grado medico con control de temperatura de 24 ft³ | D40: 3 | E40: PZ | F40: REFRIMED | G40: RVASCV-24 | H40: RVASCV-24 | I40: REFRIMED | J40: MPC | K40: 88373.98 | L40: MXN | M40: MPC | N40: MPC04151 | O40: FALSE | Q40: EN ALMACEN 11 | R40: N/A | S40: TRUE | T40: N/A | U40: TRUE
A41: CEO00282 | B41: 8 | C41: Refrigerador grado médico para farmacia de 24 ft³ | D41: 3 | E41: PZ | F41: REFRIMED | G41: RVCCDV-24 | H41: RVCCDV-24 | I41: REFRIMED | J41: CEO | K41: 86846.5 | L41: MXN | M41: MPC | N41: MPC04151 | O41: FALSE | P41: ENVIADA | Q41: EN ALMACEN 11 | R41: MPC27343 | S41: TRUE | T41: CEO00137 | U41: TRUE
A42: CEO00282 | B42: 9 | C42: Refrigerador para cadáveres de 02 plazas | D42: 1 | E42: PZ | F42: REFRIMED | G42: GCAH-2 | H42: GCAH-2 | I42: REFRIMED | J42: CEO | K42: 231131.27 | L42: MXN | M42: MPC | N42: MPC04151 | O42: FALSE | P42: ENVIADA | Q42: EN ALMACEN 11 | R42: MPC27343 | S42: TRUE | T42: CEO00137 | U42: TRUE
A43: CEO00282 | B43: 10 | C43: Refrigerador para laboratorio con control de temperatura regulable de 2°C a 23°C con capacidad de 17ft³ | D43: 1 | E43: PZ | F43: REFRIMED | G43: RVCCDV-17 | H43: RVCCDV-17 | I43: REFRIMED | J43: CEO | K43: 70840.21 | L43: MXN | M43: MPC | N43: MPC04151 | O43: FALSE | P43: ENVIADA | Q43: EN ALMACEN 11 | R43: MPC27343 | S43: TRUE | T43: CEO00137 | U43: TRUE
A44: ITH00948 | B44: 11 | C44: Buró clínico de plástico con acabado sanitario de alto impacto con un cajón, un compartimento con puerta y ruedas de alta resistencia | D44: 26 | E44: PZ | F44: GIVAS | G44: HC8130 | H44: HC8130 | I44: GIVAS | J44: ITH | K44: 234.9 | L44: EURO | M44: ITH | N44: ITH00183 | O44: FALSE | Q44: PENDIENTE | R44: N/A | S44: TRUE | T44: N/A | U44: TRUE
H46: 137579

Sheet TABASCO IM007
A1: PEDIDO | B1: PARTIDA | C1: DESCRIPCIÓN | D1: CANTIDAD | E1: UDM | F1: MARCA | G1: MODELO | H1: CÓDIGO | I1: PROVEEDOR | J1: Empresa que vende | K1: COSTO | L1: MONEDA COSTO | M1: EMPRESA QUE COMPRA | N1: OC | O1: B2B | P1: OBSERVACIONES | Q1: ESTATUS | R1: OV-INT | S1: Status de Interempresa | T1: OC-INT | U1: Status de Interempresa
A2: MAN13243 | B2: 1 | C2: CENTRAL DE MONITOREO PARA MÚLTIPLES CAMAS (14 MONITORES) | D2: 1 | E2: PZ | F2: PHILIPS | H2: 866389 | I2: PHILIPS | J2: Manprec | K2: 28758.2 | L2: USD | M2: Manprec | N2: MAN00928 | O2: FALSE | Q2: EN ALMACEN 11 | R2: N/A | S2: FALSE | U2: FALSE
C3: PIC iX Hardware | D3: 1 | E3: PZ | F3: PHILIPS | H3: 866424 | I3: PHILIPS | J3: Manprec | K3: 0 | L3: USD | M3: Manprec | N3: MAN00928 | O3: FALSE | Q3: EN ALMACEN 11 | R3: N/A | S3: FALSE | U3: FALSE
C4: 24" Widescreen LCD Display - touch | D4: 1 | E4: PZ | F4: PHILIPS | H4: 866126 | I4: PHILIPS | J4: Manprec | K4: 0 | L4: USD | M4: Manprec | N4: MAN00928 | O4: FALSE | Q4: EN ALMACEN 11 | R4: N/A | S4: FALSE | U4: FALSE
C5: 24" Widescreen LCD Display - touch | D5: 1 | E5: PZ | F5: PHILIPS | H5: 866126 | I5: PHILIPS | J5: Manprec | K5: 0 | L5: USD | M5: Manprec | N5: MAN00993 | O5: FALSE | Q5: EN ALMACEN 11 | R5: N/A | S5: FALSE | U5: FALSE
C6: Layer 2 Switch | D6: 1 | E6: PZ | F6: PHILIPS | H6: 867392 | I6: PHILIPS | J6: Manprec | K6: 0 | L6: USD | M6: Manprec | N6: MAN00928 | O6: FALSE | Q6: EN ALMACEN 11 | R6: N/A | S6: FALSE | U6: FALSE
C7: Belden Bobina UTO Cat 5E | D7: 1 | E7: PZ | F7: PCEL | H7: B0C3BPG4FS | I7: PCEL | J7: Manprec | K7: 257.75862 | L7: MXN | M7: MPC | N7: MPC04501 | O7: FALSE | Q7: EN ALMACEN 11 | R7: MPC27909 | S7: TRUE | T7: MAN01031 | U7: TRUE
C8: JACK RJ45 CAT5E UTP KEYST | D8: 14 | E8: PZ | F8: Mercadolibre | H8: B07PBTSJYT | I8: PCEL | J8: Manprec | K8: 177 | L8: MXN | M8: MPC | N8: MPC04486/STOCK | O8: FALSE | Q8: EN ALMACEN 11 | R8: MPC27909 | S8: TRUE | T8: MAN01031 | U8: TRUE
C9: Tapa para caja RJ45 (sencilla) marca: Intellinet o Belden | D9: 14 | E9: PZ | F9: PCEL | H9: X00221V4R9 | I9: PCEL | J9: Manprec | K9: 50 | L9: MXN | M9: MPC | N9: STOCK | O9: FALSE | P9: STOCK | Q9: EN ALMACEN 11 | R9: MPC27909 | S9: TRUE | T9: MAN01031 | U9: TRUE
C10: IMPRESORA HP LASERJET 501DN | D10: 1 | E10: PZ | F10: PCEL | H10: J8H61A | I10: PCEL | J10: Manprec | K10: 5602.59 | L10: MXN | M10: MPC | N10: MPC04492 | O10: FALSE | Q10: EN ALMACEN 11 | R10: MPC27909 | S10: TRUE | T10: MAN01031 | U10: TRUE
C11: UPS RESPALDO DE 1 HORA | D11: 1 | E11: PZ | F11: ALTERNATIVA | H11: PA MG+15 1000-UN | I11: ALTERNATIVA | J11: Manprec | K11: 154 | L11: USD | M11: Gamit | N11: STOCK | O11: FALSE | Q11: EN ALMACEN 11 | R11: GAM00157 | S11: TRUE | T11: MAN01031 | U11: TRUE
C12: SOPORTE RODABLE TPX | D12: 1 | E12: PZ | F12: TPX | H12: RP050 | I12: TPX | J12: Manprec | K12: 115 | L12: USD | M12: MPC | N12: STOCK | O12: FALSE | Q12: EN ALMACEN 11 | R12: MPC27909 | S12: TRUE | T12: MAN01031 | U12: TRUE
A13: MAN13243 | B13: 2 | C13: CENTRAL DE MONITOREO PARA MÚLTIPLES CAMAS (8 MONITORES) | D13: 1 | E13: PZ | F13: PHILIPS | H13: 866389 | I13: PHILIPS | J13: Manprec | K13: 17853.2 | L13: USD | M13: Manprec | N13: MAN00928 | O13: FALSE | Q13: EN ALMACEN 11 | R13: N/A | S13: FALSE | U13: FALSE
C14: PIC iX Hardware | D14: 1 | E14: PZ | F14: PHILIPS | H14: 866424 | I14: PHILIPS | J14: Manprec | K14: 0 | L14: USD | M14: Manprec | N14: MAN00928 | O14: FALSE | Q14: EN ALMACEN 11 | R14: N/A | S14: FALSE | U14: FALSE
C15: 24" Widescreen LCD Display - touch | D15: 1 | E15: PZ | F15: PHILIPS | H15: 866126 | I15: PHILIPS | J15: Manprec | K15: 0 | L15: USD | M15: Manprec | N15: MAN00928 | O15: FALSE | Q15: EN ALMACEN 11 | R15: N/A | S15: FALSE | U15: FALSE
C16: 24" Widescreen LCD Display - touch | D16: 1 | E16: PZ | F16: PHILIPS | H16: 866126 | I16: PHILIPS | J16: Manprec | K16: 0 | L16: USD | M16: Manprec | N16: MAN00993 | O16: FALSE | Q16: EN ALMACEN 11 | R16: N/A | S16: FALSE | U16: FALSE
C17: Layer 2 Switch | D17: 1 | E17: PZ | F17: PHILIPS | H17: 867392 | I17: PHILIPS | J17: Manprec | K17: 0 | L17: USD | M17: Manprec | N17: MAN00928 | O17: FALSE | Q17: EN ALMACEN 11 | R17: N/A | S17: FALSE | U17: FALSE
C18: Belden Bobina UTO Cat 5E | D18: 1 | E18: PZ | F18: PCEL | H18: B0C3BPG4FS | I18: PCEL | J18: Manprec | K18: 257.75862 | L18: MXN | M18: MPC | N18: MPC04501 | O18: FALSE | Q18: EN ALMACEN 11 | R18: MPC27909 | S18: TRUE | T18: MAN01031 | U18: TRUE
C19: JACK RJ45 CAT5E UTP KEYST | D19: 9 | E19: PZ | F19: Mercadolibre | H19: B07PBTSJYT | I19: PCEL | J19: Manprec | K19: 177 | L19: MXN | M19: MPC | N19: MPC04486/STOCK | O19: FALSE | Q19: EN ALMACEN 11 | R19: MPC27909 | S19: TRUE | T19: MAN01031 | U19: TRUE
C20: Tapa para caja RJ45 (sencilla) marca: Intellinet o Belden | D20: 9 | E20: PZ | F20: PCEL | H20: X00221V4R9 | I20: PCEL | J20: Manprec | K20: 50 | L20: MXN | M20: MPC | N20: STOCK | O20: FALSE | P20: STOCK | Q20: EN ALMACEN 11 | R20: MPC27909 | S20: TRUE | T20: MAN01031 | U20: TRUE
C21: IMPRESORA HP LASERJET 501DN | D21: 1 | E21: PZ | F21: PCEL | H21: J8H61A | I21: PCEL | J21: Manprec | K21: 5602.59 | L21: MXN | M21: MPC | N21: MPC04492 | O21: FALSE | Q21: EN ALMACEN 11 | R21: MPC27909 | S21: TRUE | T21: MAN01031 | U21: TRUE
C22: UPS RESPALDO DE 1 HORA | D22: 1 | E22: PZ | F22: ALTERNATIVA | H22: PA MG+15 1000-UN | I22: ALTERNATIVA | J22: Manprec | K22: 154 | L22: MXN | M22: Gamit | N22: STOCK | O22: FALSE | Q22: EN ALMACEN 11 | R22: GAM00157 | S22: TRUE | T22: MAN01031 | U22: TRUE
C23: SOPORTE RODABLE TPX | D23: 1 | E23: PZ | F23: TPX | H23: RP050 | I23: TPX | J23: Manprec | K23: 115 | L23: USD | M23: MPC | N23: STOCK | O23: FALSE | Q23: EN ALMACEN 11 | R23: MPC27909 | S23: TRUE | T23: MAN01031 | U23: TRUE
A24: MAN13243 | B24: 12 | C24: MESA PARA AUTOPSIAS CON TRITURADOR | D24: 1 | E24: PZ | F24: REFRIMED | H24: MATT | I24: REFRIMED | J24: Manprec | K24: 464256.8 | L24: MXN | M24: MPC | N24: MPC04380 | O24: FALSE | Q24: EN ALMACEN 11 | R24: MPC27909 | S24: TRUE | T24: MAN01031 | U24: TRUE
O25: FALSE | S25: FALSE | U25: FALSE
O26: FALSE | S26: FALSE | U26: FALSE
O27: FALSE | S27: FALSE | U27: FALSE
O28: FALSE | S28: FALSE | U28: FALSE
O29: FALSE | S29: FALSE | U29: FALSE
O30: FALSE | S30: FALSE | U30: FALSE
O31: FALSE | S31: FALSE | U31: FALSE
O32: FALSE | S32: FALSE | U32: FALSE
O33: FALSE | S33: FALSE | U33: FALSE
O34: FALSE | S34: FALSE | U34: FALSE
O35: FALSE | S35: FALSE | U35: FALSE
O36: FALSE | S36: FALSE | U36: FALSE
... O51: FALSE | S51: FALSE | U51: FALSE

Sheet IMSS BIENESTAR TABASCO 053
A1: PEDIDO | B1: PARTIDA | C1: DESCRIPCIÓN | D1: CANTIDAD | E1: UDM | F1: MARCA | G1: MODELO | H1: CÓDIGO | I1: PROVEEDOR | J1: Empresa que vende | K1: COSTO | L1: MONEDA COSTO | M1: EMPRESA QUE COMPRA | N1: OC | O1: B2B | P1: OBSERVACIONES | Q1: ESTATUS | R1: OV-INT | S1: Status de Interempresa | T1: OC-INT | U1: Status de Interempresa
A2: MAN13244 | B2: 90 / 107 | C2: MONITOR DE SIGNOS VITALES AVANZADO | D2: 22 | E2: PZ | F2: PHILIPS | G2: MX500 | H2: 866064.6 | I2: PHILIPS | J2: Manprec | K2: 4311.1 | L2: USD | M2: Manprec | N2: MAN00993 | O2: FALSE | P2: CDD 01 Junio | Q2: PENDIENTE | R2: N/A | S2: TRUE | T2: N/A | U2: TRUE
B3: 90 | C3: IntelliVue MMX | D3: 22 | E3: PZ | H3: 867036.1 | I3: PHILIPS | J3: Manprec | K3: 1100 | L3: USD | M3: Manprec | N3: MAN00993 | O3: FALSE | P3: CDD 01 Junio | Q3: PENDIENTE | R3: N/A | S3: TRUE | T3: N/A | U3: TRUE
B4: 90 | C4: IntelliVue Capnography Extension | D4: 22 | E4: PZ | H4: 867040.2 | I4: PHILIPS | J4: Manprec | K4: 1694.63 | L4: USD | M4: Manprec | N4: MAN00993 | O4: FALSE | P4: CDD 01 Junio | Q4: PENDIENTE | R4: N/A | S4: TRUE | T4: N/A | U4: TRUE
B5: 90 | C5: Mainstream Sensor | D5: 22 | E5: PZ | H5: M2501A | I5: PHILIPS | J5: Manprec | K5: 1630.8 | L5: USD | M5: Manprec | N5: Stock | O5: TRUE | Q5: EN ALMACEN 11 | R5: N/A | S5: TRUE | T5: N/A | U5: TRUE
B6: 90 | C6: SPO2 Reus Ped-Adult Glove Sensor M1192A | D6: 22 | E6: PZ | H6: 989803205871 | I6: PHILIPS | J6: Manprec | K6: 102 | L6: USD | M6: Manprec | N6: Stock | O6: TRUE | Q6: EN ALMACEN 11 | R6: N/A | S6: TRUE | T6: N/A | U6: TRUE
B7: 90 | C7: CBL SpO2 Extension Cable 2m | D7: 44 | E7: PZ | H7: M1941A | I7: PHILIPS | J7: Manprec | K7: 46.2 | L7: USD | M7: Manprec | N7: MAN01003 | O7: TRUE | Q7: PENDIENTE | R7: N/A | S7: TRUE | T7: N/A | U7: TRUE
B8: 90 | C8: Reusable Adult SpO2 Sensor | D8: 22 | E8: PZ | H8: M1191B | I8: PHILIPS | J8: Manprec | K8: 96.6 | L8: USD | M8: Manprec | N8: Stock | O8: TRUE | Q8: EN ALMACEN 11 | R8: N/A | S8: TRUE | T8: N/A | U8: TRUE
B9: 90 | C9: Skin Temperature Probe, Reusable | D9: 44 | E9: PZ | H9: 21078ST | I9: HOSPIINNOVA | J9: Manprec | K9: 840 | L9: MXN | M9: Manprec | N9: MAN00996 | O9: FALSE | Q9: EN ALMACEN 11 | R9: N/A | S9: TRUE | T9: N/A | U9: TRUE
B10: 90 | C10: Easy Care Cuff 1 Hose Pediatric (1) | D10: 22 | E10: PZ | H10: M4553B | I10: PHILIPS | J10: Manprec | K10: 23.94 | L10: USD | M10: Manprec | N10: MAN01003 | O10: TRUE | Q10: PENDIENTE | R10: N/A | S10: TRUE | T10: N/A | U10: TRUE
B11: 90 | C11: Easy Care Cuff 1 Hose Adult (1) | D11: 22 | E11: PZ | H11: M4555B | I11: PHILIPS | J11: Manprec | K11: 11.34 | L11: USD | M11: Manprec | N11: MAN01003 | O11: TRUE | Q11: PENDIENTE | R11: N/A | S11: TRUE | T11: N/A | U11: TRUE
B12: 90 | C12: Adult NIBP Air Hose 3.0m | D12: 22 | E12: PZ | H12: 989803209771 | I12: PHILIPS | J12: Manprec | K12: 24.66 | L12: USD | M12: Manprec | N12: Stock | O12: TRUE | Q12: EN ALMACEN 11 | R12: N/A | S12: TRUE | T12: N/A | U12: TRUE
B13: 90 | C13: CBL 5 Lead ECG Trunk AAMI/IEC 2.7m | D13: 22 | E13: PZ | H13: M1668A | I13: PHILIPS | J13: Manprec | K13: 70.8 | L13: USD | M13: Manprec | N13: MAN01003 | O13: TRUE | Q13: PENDIENTE | R13: N/A | S13: TRUE | T13: N/A | U13: TRUE
B14: 90 | C14: CBL 5 Leadset Snap AAMI ICU | D14: 22 | E14: PZ | H14: M1644A | I14: PHILIPS | J14: Manprec | K14: 67.8 | L14: USD | M14: Manprec | N14: Stock | O14: TRUE | Q14: EN ALMACEN 11 | R14: N/A | S14: TRUE | T14: N/A | U14: TRUE
B15: 90 | C15: CBL 10 Lead ECG Trunk AAMI/IEC 2m | D15: 22 | E15: PZ | H15: M1663A | I15: PHILIPS | J15: Manprec | K15: 153 | L15: USD | M15: Manprec | N15: MAN01003 | O15: TRUE | Q15: PENDIENTE | R15: N/A | S15: TRUE | T15: N/A | U15: TRUE
B16: 90 | C16: CBL 5 Leadset Grabber AAMI ICU | D16: 22 | E16: PZ | H16: M1968A | I16: PHILIPS | J16: Manprec | K16: 54 | L16: USD | M16: Manprec | N16: Stock | O16: TRUE | Q16: EN ALMACEN 11 | R16: N/A | S16: TRUE | T16: N/A | U16: TRUE
B17: 90 | C17: CBL 5 Leadset Grabber Chest AAMI ICU | D17: 22 | E17: PZ | H17: M1976A | I17: PHILIPS | J17: Manprec | K17: 68.4 | L17: USD | M17: Manprec | N17: Stock | O17: TRUE | Q17: EN ALMACEN 11 | R17: N/A | S17: TRUE | T17: N/A | U17: TRUE
B18: 90 | C18: SPO2 Reus Neo Hnd-Ft Wrap Sensor M1193A | D18: 22 | E18: PZ | H18: 989803205881 | I18: PHILIPS | J18: Manprec | K18: 101.4 | L18: USD | M18: Manprec | N18: MAN01003 | O18: TRUE | Q18: PENDIENTE | R18: N/A | S18: TRUE | T18: N/A | U18: TRUE
B19: 90 | C19: Neonatal NIBP Air Hose 3.0m | D19: 22 | E19: PZ | H19: 989803209751 | I19: PHILIPS | J19: Manprec | K19: 23.94 | L19: USD | M19: Manprec | N19: Stock | O19: TRUE | Q19: EN ALMACEN 11 | R19: N/A | S19: TRUE | T19: N/A | U19: TRUE
B20: 90 | C20: Neonatal Soft Single-Patient Cuff Size#2 | D20: =22*10 -> 220 | E20: PZ | H20: M1868S | I20: PHILIPS | J20: Manprec | K20: 136.8 | L20: USD | M20: Manprec | N20: Stock | O20: TRUE | Q20: EN ALMACEN 11 | R20: N/A | S20: TRUE | T20: N/A | U20: TRUE
B21: 90 | C21: Neonatal Soft Single-Patient Cuff Size#3 | D21: =22*10 -> 220 | E21: PZ | H21: M1870S | I21: PHILIPS | J21: Manprec | K21: 141.6 | L21: USD | M21: Manprec | N21: Stock | O21: TRUE | Q21: EN ALMACEN 11 | R21: N/A | S21: TRUE | T21: N/A | U21: TRUE
B22: 90 | C22: CBL 3 Lead ECG Trunk AAMI/IEC 2.7m | D22: 22 | E22: PZ | H22: M1669A | I22: PHILIPS | J22: Manprec | K22: 54 | L22: USD | M22: Manprec | N22: Stock | O22: TRUE | Q22: EN ALMACEN 11 | R22: N/A | S22: TRUE | T22: N/A | U22: TRUE
B23: 90 | C23: CBL Unshielded 3 Ld Miniclip AAMI 0.7m | D23: 22 | E23: PZ | H23: M1624A | I23: PHILIPS | J23: Manprec | K23: 27.96 | L23: USD | M23: Manprec | N23: Stock | O23: TRUE | Q23: EN ALMACEN 11 | R23: N/A | S23: TRUE | T23: N/A | U23: TRUE
B24: 90 | C24: Airway Adapter-Reusable-Adult/Pediatric | D24: 22 | E24: PZ | H24: 989803206591 | I24: PHILIPS | J24: Manprec | K24: 115.8 | L24: USD | M24: Manprec | N24: Stock | O24: TRUE | Q24: EN ALMACEN 11 | R24: N/A | S24: TRUE | T24: N/A | U24: TRUE
B25: 90 | C25: CBL Cardiac Output Cable | D25: 22 | E25: PZ | H25: M1642A | I25: PHILIPS | J25: Manprec | K25: 130.8 | L25: USD | M25: Manprec | N25: Stock | O25: TRUE | Q25: EN ALMACEN 11 | R25: N/A | S25: TRUE | T25: N/A | U25: TRUE
B26: 90 | C26: Wall Mount with adjustable height | D26: 22 | E26: PZ | H26: WP010-MX | I26: TPX | J26: Manprec | K26: 78 | L26: USD | M26: MPC | N26: Stock | O26: FALSE | Q26: PENDIENTE | R26: MPC28349 | S26: TRUE | T26: MAN01030 | U26: TRUE
B27: 90 | C27: ELECTRODO DE MONITOREO ECG PACIENTE ADULTO MT200 CAJA CON 10 SOBRES CON 100 PIEZAS | D27: =3*22 -> 66 | E27: B/100 | F27: CARDINAL | H27: 31050522 | I27: HOSPIINNOVA | J27: Manprec | L27: MXN | M27: Manprec | N27: Stock | O27: FALSE | Q27: EN ALMACEN 11 | R27: N/A | S27: TRUE | T27: N/A | U27: TRUE
B28: 90 | C28: ELECTRODOS NEONATAL DE ECG | D28: =(22*300/3) -> 2200 | E28: B/3 | F28: CARDINAL | H28: 31424743 | I28: HOSPIINNOVA | J28: Manprec | K28: =4512/100 -> 45.12 | L28: MXN | M28: Manprec | N28: MAN01078 | O28: FALSE | Q28: PENDIENTE | R28: N/A | S28: TRUE | T28: N/A | U28: TRUE
B29: 90 | C29: Co-Set(TM) Injectate Temp Probe - 7'9 | D29: 22 | E29: PZ | H29: 23001A | I29: INNOVACION | J29: Manprec | K29: 546 | L29: USD | M29: Manprec | N29: MAN01032 | O29: FALSE | Q29: PENDIENTE | R29: N/A | S29: TRUE | T29: N/A | U29: TRUE
B30: 90 | C30: Ice Bath Temperature Probe | D30: 22 | E30: PZ | H30: 23002A | I30: INNOVACION | J30: Manprec | K30: 234 | L30: USD | M30: Manprec | N30: MAN01032 | O30: FALSE | Q30: EN ALMACEN 11 | R30: N/A | S30: TRUE | T30: N/A | U30: TRUE
B31: 90 | C31: Transductor reusable logical. | D31: 44 | E31: PZ | H31: MX960 | I31: ATSA | J31: Manprec | K31: 3142.1 | L31: MXN | M31: Manprec | N31: MAN01001 | O31: TRUE | Q31: EN ALMACEN 11 | R31: N/A | S31: TRUE | T31: N/A | U31: TRUE
B32: 90 | C32: Soporte porta transductor logical reusable | D32: 22 | E32: PZ | H32: MX261 | I32: ATSA | J32: Manprec | K32: 491.9 | L32: MXN | M32: Manprec | N32: MAN01001 | O32: TRUE | Q32: EN ALMACEN 11 | R32: N/A | S32: TRUE | T32: N/A | U32: TRUE
B33: 90 | C33: Bracket para dos transductores logical reusable | D33: 22 | E33: PZ | H33: MX262 | I33: ATSA | J33: Manprec | K33: 337.3 | L33: MXN | M33: Manprec | N33: MAN01001 | O33: TRUE | Q33: EN ALMACEN 11 | R33: N/A | S33: TRUE | T33: N/A | U33: TRUE
B34: 90 | C34: Cable logical interface HP /PHILIPS reusable un canal | D34: =22*2 -> 44 | E34: PZ | H34: BC-HP-MX1 | I34: ATSA | J34: Manprec | K34: 1014.3 | L34: MXN | M34: Manprec | N34: MAN01001 | O34: TRUE | Q34: EN ALMACEN 11 | R34: N/A | S34: TRUE | T34: N/A | U34: TRUE
B35: 90 | C35: Kit transductor logical domo, llaves, flush, | D35: =20*22 -> 440 | E35: PZ | H35: MX9604A | I35: ATSA | J35: Manprec | K35: =3638/10 -> 363.8 | L35: MXN | M35: Manprec | N35: MAN01001 | O35: TRUE | Q35: EN ALMACEN 11 | R35: N/A | S35: TRUE | T35: N/A | U35: TRUE
A36: MAN13244 | B36: 232 | C36: MONITOR DE SIGNOS VITALES | D36: 31 | E36: PZ | F36: PHILIPS | G36: MX500 | H36: 866064.6 | I36: PHILIPS | J36: Manprec | K36: 3487.02 | L36: USD | M36: Manprec | N36: MAN00993 | O36: FALSE | P36: CDD 01 Junio | Q36: PENDIENTE | R36: N/A | S36: TRUE | T36: N/A | U36: TRUE
B37: 232 | C37: IntelliVue MMX | D37: 31 | E37: PZ | H37: 867036.1 | I37: PHILIPS | J37: Manprec | K37: 1100 | L37: USD | M37: Manprec | N37: MAN00993 | O37: FALSE | P37: CDD 01 Junio | Q37: PENDIENTE | R37: N/A | S37: TRUE | T37: N/A | U37: TRUE
B38: 232 | C38: Temperature Parameter Module | D38: 31 | E38: PZ | H38: M1029A | I38: PHILIPS | J38: Manprec | K38: 247.93 | L38: USD | M38: Manprec | N38: MAN00993 | O38: FALSE | P38: CDD 01 Junio | Q38: PENDIENTE | R38: N/A | S38: TRUE | T38: N/A | U38: TRUE
B39: 232 | C39: SPO2 Reus Ped-Adult Glove Sensor M1192A | D39: 31 | E39: PZ | H39: 989803205871 | I39: PHILIPS | J39: Manprec | K39: 102 | L39: USD | M39: Manprec | N39: Stock | O39: TRUE | Q39: EN ALMACEN 11 | R39: N/A | S39: TRUE | T39: N/A | U39: TRUE
B40: 232 | C40: SPO2 Reus Neo Hnd-Ft Wrap Sensor M1193A | D40: 31 | E40: PZ | H40: 989803205881 | I40: PHILIPS | J40: Manprec | K40: 101.4 | L40: USD | M40: Manprec | N40: MAN01003 | O40: TRUE | Q40: PENDIENTE | R40: N/A | S40: TRUE | T40: N/A | U40: TRUE
B41: 232 | C41: CBL SpO2 Extension Cable 2m | D41: =31*2 -> 62 | E41: PZ | H41: M1941A | I41: PHILIPS | J41: Manprec | K41: 46.2 | L41: USD | M41: Manprec | N41: MAN01003 | O41: TRUE | Q41: PENDIENTE | R41: N/A | S41: TRUE | T41: N/A | U41: TRUE
B42: 232 | C42: Reusable Adult SpO2 Sensor | D42: 31 | E42: PZ | H42: M1191B | I42: PHILIPS | J42: Manprec | K42: 96.6 | L42: USD | M42: Manprec | N42: Stock | O42: TRUE | Q42: EN ALMACEN 11 | R42: N/A | S42: TRUE | T42: N/A | U42: TRUE
B43: 232 | C43: Skin Temperature Probe, Reusable | D43: =31*2 -> 62 | E43: PZ | H43: 21078ST | I43: HOSPIINNOVA | J43: Manprec | K43: 840 | L43: MXN | M43: Manprec | N43: MAN00996 | O43: FALSE | Q43: EN ALMACEN 11 | R43: N/A | S43: TRUE | T43: N/A | U43: TRUE
B44: 232 | C44: Easy Care Cuff 1 Hose Pediatric (1) | D44: 31 | E44: PZ | H44: M4553B | I44: PHILIPS | J44: Manprec | K44: 23.94 | L44: USD | M44: Manprec | N44: MAN01003 | O44: TRUE | Q44: PENDIENTE | R44: N/A | S44: TRUE | T44: N/A | U44: TRUE
B45: 232 | C45: Easy Care Cuff 1 Hose Adult (1) | D45: 31 | E45: PZ | H45: M4555B | I45: PHILIPS | J45: Manprec | K45: 11.34 | L45: USD | M45: Manprec | N45: MAN01003 | O45: TRUE | Q45: PENDIENTE | R45: N/A | S45: TRUE | T45: N/A | U45: TRUE
B46: 232 | C46: Adult NIBP Air Hose 3.0m | D46: 31 | E46: PZ | H46: 989803209771 | I46: PHILIPS | J46: Manprec | K46: 24.66 | L46: USD | M46: Manprec | N46: Stock | O46: TRUE | Q46: EN ALMACEN 11 | R46: N/A | S46: TRUE | T46: N/A | U46: TRUE
B47: 232 | C47: Neonatal NIBP Air Hose 3.0m | D47: 31 | E47: PZ | H47: 989803209751 | I47: PHILIPS | J47: Manprec | K47: 23.94 | L47: USD | M47: Manprec | N47: Stock | O47: TRUE | Q47: EN ALMACEN 11 | R47: N/A | S47: TRUE | T47: N/A | U47: TRUE
B48: 232 | C48: Neonatal Soft Single-Patient Cuff Size#1 | D48: =31*10 -> 310 | E48: PZ | H48: M1866S | I48: PHILIPS | J48: Manprec | K48: 167.4 | L48: USD | M48: Manprec | N48: Stock | O48: TRUE | Q48: EN ALMACEN 11 | R48: N/A | S48: TRUE | T48: N/A | U48: TRUE
B49: 232 | C49: Neonatal Soft Single-Patient Cuff Size#3 | D49: =31*10 -> 310 | E49: PZ | H49: M1870S | I49: PHILIPS | J49: Manprec | K49: 141.6 | L49: USD | M49: Manprec | N49: Stock | O49: TRUE | Q49: EN ALMACEN 11 | R49: N/A | S49: TRUE | T49: N/A | U49: TRUE
B50: 232 | C50: CBL 5 Lead ECG Trunk AAMI/IEC 2.7m | D50: 31 | E50: PZ | H50: M1668A | I50: PHILIPS | J50: Manprec | K50: 70.8 | L50: USD | M50: Manprec | N50: MAN01003 | O50: TRUE | Q50: PENDIENTE | R50: N/A | S50: TRUE | T50: N/A | U50: TRUE
B51: 232 | C51: CBL 5 Leadset Snap AAMI ICU | D51: 31 | E51: PZ | H51: M1644A | I51: PHILIPS | J51: Manprec | K51: 67.8 | L51: USD | M51: Manprec | N51: Stock | O51: TRUE | Q51: EN ALMACEN 11 | R51: N/A | S51: TRUE | T51: N/A | U51: TRUE
B52: 232 | C52: CBL 3 Lead ECG Trunk AAMI/IEC 2.7m | D52: 31 | E52: PZ | H52: M1669A | I52: PHILIPS | J52: Manprec | K52: 54 | L52: USD | M52: Manprec | N52: Stock | O52: TRUE | Q52: EN ALMACEN 11 | R52: N/A | S52: TRUE | T52: N/A | U52: TRUE
B53: 232 | C53: CBL Unshielded 3 Ld Miniclip AAMI 0.7m | D53: 31 | E53: PZ | H53: M1624A | I53: PHILIPS | J53: Manprec | K53: 27.96 | L53: USD | M53: Manprec | N53: Stock | O53: TRUE | Q53: EN ALMACEN 11 | R53: N/A | S53: TRUE | T53: N/A | U53: TRUE
B54: 232 | C54: Rolling Stand--For Patient Monitor | D54: 31 | E54: PZ | H54: RP050 | I54: TPX | J54: Manprec | K54: 115 | L54: USD | M54: MPC | N54: MPC04399 | O54: FALSE | Q54: PENDIENTE | R54: MPC28349 | S54: TRUE | T54: MAN01030 | U54: TRUE
B55: 232 | C55: BASE PARA MONITOR PHILIPS MX | D55: 31 | H55: PL-MX | I55: TPX | J55: Manprec | K55: 12 | L55: USD | M55: MPC | N55: Stock | O55: FALSE | Q55: EN ALMACEN 11 | R55: MPC28349 | S55: TRUE | T55: MAN01030 | U55: TRUE
B56: 232 | C56: ELECTRODOS NEONATAL | D56: =(31*300)/3 -> 3100 | E56: B/3 | F56: CARDINAL | H56: 31424743 | I56: HOSPIINNOVA | J56: Manprec | K56: =4512/100 -> 45.12 | L56: MXN | M56: Manprec | N56: MAN01078 | O56: FALSE | Q56: PENDIENTE | R56: N/A | S56: TRUE | T56: N/A | U56: TRUE
B57: 232 | C57: ELECTRODO DE MONITOREO ECG PACIENTE ADULTO MT200 CAJA CON 10 SOBRES CON 100 PIEZAS | D57: =31*3 -> 93 | E57: B/100 | F57: CARDINAL | H57: 31050522 | I57: HOSPIINNOVA | J57: Manprec | L57: MXN | M57: Manprec | N57: Stock | O57: FALSE | Q57: EN ALMACEN 11 | R57: N/A | S57: TRUE | T57: N/A | U57: TRUE
B58: 232 | C58: CONSIDERAR 20 PARCHES PARA SENSOR DE TEMPERATURA | D58: 31 | E58: B/50 | H58: MU06942 | I58: ARROBA | J58: Manprec | K58: =878.46/50 -> 17.5692 | L58: MXN | M58: Manprec | N58: MAN00997 | O58: FALSE | P58: Pedir recolección | Q58: EN ALMACEN 11 | R58: N/A | S58: TRUE | T58: N/A | U58: TRUE
A59: MAN13244 | B59: 232 / 248 | C59: MONITOR DE SIGNOS VITALES (RODABLE) | D59: 15 | E59: PZ | F59: PHILIPS | G59: MX500 | H59: 866064.6 | I59: PHILIPS | J59: Manprec | K59: 3487.02 | L59: USD | M59: Manprec | N59: MAN00993 | O59: FALSE | P59: CDD 01 Junio | Q59: PENDIENTE | R59: N/A | S59: TRUE | T59: N/A | U59: TRUE
B60: 232 | C60: IntelliVue MMX | D60: 15 | E60: PZ | H60: 867036.1 | I60: PHILIPS | J60: Manprec | K60: 1100 | L60: USD | M60: Manprec | N60: MAN00993 | O60: FALSE | P60: CDD 01 Junio | Q60: PENDIENTE | R60: N/A | S60: TRUE | T60: N/A | U60: TRUE
B61: 232 | C61: Temperature Parameter Module | D61: 15 | E61: PZ | H61: M1029A | I61: PHILIPS | J61: Manprec | K61: 247.93 | L61: USD | M61: Manprec | N61: MAN00993 | O61: FALSE | P61: CDD 01 Junio | Q61: PENDIENTE | R61: N/A | S61: TRUE | T61: N/A | U61: TRUE
B62: 232 | C62: SPO2 Reus Ped-Adult Glove Sensor M1192A | D62: 15 | E62: PZ | H62: 989803205871 | I62: PHILIPS | J62: Manprec | K62: 102 | L62: USD | M62: Manprec | N62: Stock | O62: TRUE | Q62: EN ALMACEN 11 | R62: N/A | S62: TRUE | T62: N/A | U62: TRUE
B63: 232 | C63: SPO2 Reus Neo Hnd-Ft Wrap Sensor M1193A | D63: 15 | E63: PZ | H63: 989803205881 | I63: PHILIPS | J63: Manprec | K63: 101.4 | L63: USD | M63: Manprec | N63: MAN01003 | O63: TRUE | Q63: PENDIENTE | R63: N/A | S63: TRUE | T63: N/A | U63: TRUE
B64: 232 | C64: CBL SpO2 Extension Cable 2m | D64: =15*2 -> 30 | E64: PZ | H64: M1941A | I64: PHILIPS | J64: Manprec | K64: 46.2 | L64: USD | M64: Manprec | N64: MAN01003 | O64: TRUE | Q64: PENDIENTE | R64: N/A | S64: TRUE | T64: N/A | U64: TRUE
B65: 232 | C65: Reusable Adult SpO2 Sensor | D65: 15 | E65: PZ | H65: M1191B | I65: PHILIPS | J65: Manprec | K65: 96.6 | L65: USD | M65: Manprec | N65: Stock | O65: TRUE | Q65: EN ALMACEN 11 | R65: N/A | S65: TRUE | T65: N/A | U65: TRUE
B66: 232 | C66: Skin Temperature Probe, Reusable | D66: =15*2 -> 30 | E66: PZ | H66: 21078ST | I66: HOSPIINNOVA | J66: Manprec | K66: 840 | L66: MXN | M66: Manprec | N66: MAN00996 | O66: FALSE | Q66: EN ALMACEN 11 | R66: N/A | S66: TRUE | T66: N/A | U66: TRUE
B67: 232 | C67: Easy Care Cuff 1 Hose Pediatric (1) | D67: 15 | E67: PZ | H67: M4553B | I67: PHILIPS | J67: Manprec | K67: 23.94 | L67: USD | M67: Manprec | N67: MAN01003 | O67: TRUE | Q67: PENDIENTE | R67: N/A | S67: TRUE | T67: N/A | U67: TRUE
B68: 232 | C68: Easy Care Cuff 1 Hose Adult (1) | D68: 15 | E68: PZ | H68: M4555B | I68: PHILIPS | J68: Manprec | K68: 11.34 | L68: USD | M68: Manprec | N68: MAN01003 | O68: TRUE | Q68: PENDIENTE | R68: N/A | S68: TRUE | T68: N/A | U68: TRUE
B69: 232 | C69: Adult NIBP Air Hose 3.0m | D69: 15 | E69: PZ | H69: 989803209771 | I69: PHILIPS | J69: Manprec | K69: 24.66 | L69: USD | M69: Manprec | N69: Stock | O69: TRUE | Q69: EN ALMACEN 11 | R69: N/A | S69: TRUE | T69: N/A | U69: TRUE
B70: 232 | C70: Neonatal NIBP Air Hose 3.0m | D70: 15 | E70: PZ | H70: 989803209751 | I70: PHILIPS | J70: Manprec | K70: 23.94 | L70: USD | M70: Manprec | N70: Stock | O70: TRUE | Q70: EN ALMACEN 11 | R70: N/A | S70: TRUE | T70: N/A | U70: TRUE
B71: 232 | C71: Neonatal Soft Single-Patient Cuff Size#1 | D71: =15*10 -> 150 | E71: PZ | H71: M1866S | I71: PHILIPS | J71: Manprec | K71: 167.4 | L71: USD | M71: Manprec | N71: Stock | O71: TRUE | Q71: EN ALMACEN 11 | R71: N/A | S71: TRUE | T71: N/A | U71: TRUE
B72: 232 | C72: Neonatal Soft Single-Patient Cuff Size#3 | D72: =15*10 -> 150 | E72: PZ | H72: M1870S | I72: PHILIPS | J72: Manprec | K72: 141.6 | L72: USD | M72: Manprec | N72: Stock | O72: TRUE | Q72: EN ALMACEN 11 | R72: N/A | S72: TRUE | T72: N/A | U72: TRUE
B73: 232 | C73: CBL 5 Lead ECG Trunk AAMI/IEC 2.7m | D73: 15 | E73: PZ | H73: M1668A | I73: PHILIPS | J73: Manprec | K73: 70.8 | L73: USD | M73: Manprec | N73: MAN01003 | O73: TRUE | Q73: PENDIENTE | R73: N/A | S73: TRUE | T73: N/A | U73: TRUE
B74: 232 | C74: CBL 5 Leadset Snap AAMI ICU | D74: 15 | E74: PZ | H74: M1644A | I74: PHILIPS | J74: Manprec | K74: 67.8 | L74: USD | M74: Manprec | N74: Stock | O74: TRUE | Q74: EN ALMACEN 11 | R74: N/A | S74: TRUE | T74: N/A | U74: TRUE
B75: 232 | C75: CBL 3 Lead ECG Trunk AAMI/IEC 2.7m | D75: 15 | E75: PZ | H75: M1669A | I75: PHILIPS | J75: Manprec | K75: 54 | L75: USD | M75: Manprec | N75: Stock | O75: TRUE | Q75: EN ALMACEN 11 | R75: N/A | S75: TRUE | T75: N/A | U75: TRUE
B76: 232 | C76: CBL Unshielded 3 Ld Miniclip AAMI 0.7m | D76: 15 | E76: PZ | H76: M1624A | I76: PHILIPS | J76: Manprec | K76: 27.96 | L76: USD | M76: Manprec | N76: Stock | O76: TRUE | Q76: EN ALMACEN 11 | R76: N/A | S76: TRUE | T76: N/A | U76: TRUE
B77: 232 | C77: Rolling Stand--For Patient Monitor | D77: 15 | E77: PZ | H77: RP050 | I77: TPX | J77: Manprec | K77: 115 | L77: USD | M77: MPC | N77: MPC04399 | O77: FALSE | Q77: PENDIENTE | R77: MPC28349 | S77: TRUE | T77: MAN01030 | U77: TRUE
B78: 232 | C78: BASE PARA MONITOR PHILIPS MX | D78: 15 | H78: PL-MX | I78: TPX | J78: Manprec | K78: 12 | L78: USD | M78: MPC | N78: Stock | O78: FALSE | Q78: EN ALMACEN 11 | R78: MPC28349 | S78: TRUE | T78: MAN01030 | U78: TRUE
B79: 232 | C79: ELECTRODOS NEONATAL | D79: =(15*300)/3 -> 1500 | E79: B/3 | F79: CARDINAL | H79: 31424743 | I79: HOSPIINNOVA | J79: Manprec | K79: =4512/100 -> 45.12 | L79: MXN | M79: Manprec | N79: MAN01078 | O79: FALSE | Q79: PENDIENTE | R79: N/A | S79: TRUE | T79: N/A | U79: TRUE
B80: 232 | C80: ELECTRODO DE MONITOREO ECG PACIENTE ADULTO MT200 CAJA CON 10 SOBRES CON 100 PIEZAS | D80: =15*3 -> 45 | E80: B/100 | F80: CARDINAL | H80: 31050522 | I80: HOSPIINNOVA | J80: Manprec | L80: MXN | M80: Manprec | N80: Stock | O80: FALSE | Q80: EN ALMACEN 11 | R80: N/A | S80: TRUE | T80: N/A | U80: TRUE
B81: 232 | C81: CONSIDERAR 20 PARCHES PARA SENSOR DE TEMPERATURA | D81: =15 -> 15 | E81: B/50 | H81: MU06942 | I81: ARROBA | J81: Manprec | K81: =878.46/50 -> 17.5692 | L81: MXN | M81: Manprec | N81: MAN00997 | O81: FALSE | P81: Pedir recolección | Q81: EN ALMACEN 11 | R81: N/A | S81: TRUE | T81: N/A | U81: TRUE
A82: MAN13244 | B82: 233 / 249 | C82: MONITOR DE SIGNOS VITALES (PEDIATRICO) | D82: 1 | E82: PZ | F82: PHILIPS | G82: MX550 | H82: 866066.6 | I82: PHILIPS | J82: Manprec | K82: 4040.96 | L82: USD | M82: Manprec | N82: MAN00993 | O82: FALSE | P82: CDD 01 Junio | Q82: PENDIENTE | R82: N/A | S82: TRUE | T82: N/A | U82: TRUE
B83: 233 | C83: Thermal Array Recorder Module | D83: 1 | E83: PZ | H83: M1116C | I83: PHILIPS | J83: Manprec | K83: 782.4 | L83: USD | M83: Manprec | N83: MAN01003 | O83: TRUE | Q83: PENDIENTE | R83: N/A | S83: TRUE | T83: N/A | U83: TRUE
B84: 233 | C84: IntelliVue MMX | D84: 1 | E84: PZ | H84: 867036.1 | I84: PHILIPS | J84: Manprec | K84: 1100 | L84: USD | M84: Manprec | N84: MAN00993 | O84: FALSE | P84: CDD 01 Junio | Q84: PENDIENTE | R84: N/A | S84: TRUE | T84: N/A | U84: TRUE
B85: 233 | C85: IntelliVue Capnography Extension | D85: 1 | E85: PZ | H85: 867040 | I85: PHILIPS | J85: Manprec | K85: 1361.87 | L85: USD | M85: Manprec | N85: MAN00993 | O85: FALSE | P85: CDD 01 Junio | Q85: PENDIENTE | R85: N/A | S85: TRUE | T85: N/A | U85: TRUE
B86: 233 | C86: Mainstream Sensor | D86: 1 | E86: PZ | H86: M2501A | I86: PHILIPS | J86: Manprec | K86: 1630.8 | L86: USD | M86: Manprec | N86: Stock | O86: TRUE | Q86: EN ALMACEN 11 | R86: N/A | S86: TRUE | T86: N/A | U86: TRUE
B87: 233 | C87: SPO2 Reus Ped-Adult Glove Sensor M1192A | D87: 1 | E87: PZ | H87: 989803205871 | I87: PHILIPS | J87: Manprec | K87: 102 | L87: USD | M87: Manprec | N87: Stock | O87: TRUE | Q87: EN ALMACEN 11 | R87: N/A | S87: TRUE | T87: N/A | U87: TRUE
B88: 233 | C88: CBL SpO2 Extension Cable 2m | D88: 2 | E88: PZ | H88: M1941A | I88: PHILIPS | J88: Manprec | K88: 46.2 | L88: USD | M88: Manprec | N88: MAN01003 | O88: TRUE | Q88: PENDIENTE | R88: N/A | S88: TRUE | T88: N/A | U88: TRUE
B89: 233 | C89: Reusable Adult SpO2 Sensor | D89: 1 | E89: PZ | H89: M1191B | I89: PHILIPS | J89: Manprec | K89: 96.6 | L89: USD | M89: Manprec | N89: Stock | O89: TRUE | Q89: EN ALMACEN 11 | R89: N/A | S89: TRUE | T89: N/A | U89: TRUE
B90: 233 | C90: Skin Temperature Probe, Reusable | D90: 2 | E90: PZ | H90: 21078ST | I90: HOSPIINNOVA | J90: Manprec | K90: 840 | L90: MXN | M90: Manprec | N90: MAN00996 | O90: FALSE | Q90: EN ALMACEN 11 | R90: N/A | S90: TRUE | T90: N/A | U90: TRUE
B91: 233 | C91: Easy Care Cuff 1 Hose Pediatric (1) | D91: 1 | E91: PZ | H91: M4553B | I91: PHILIPS | J91: Manprec | K91: 23.94 | L91: USD | M91: Manprec | N91: MAN01003 | O91: TRUE | Q91: PENDIENTE | R91: N/A | S91: TRUE | T91: N/A | U91: TRUE
B92: 233 | C92: Easy Care Cuff 1 Hose Adult (1) | D92: 1 | E92: PZ | H92: M4555B | I92: PHILIPS | J92: Manprec | K92: 11.34 | L92: USD | M92: Manprec | N92: MAN01003 | O92: TRUE | Q92: PENDIENTE | R92: N/A | S92: TRUE | T92: N/A | U92: TRUE
B93: 233 | C93: Adult NIBP Air Hose 3.0m | D93: 1 | E93: PZ | H93: 989803209771 | I93: PHILIPS | J93: Manprec | K93: 24.66 | L93: USD | M93: Manprec | N93: Stock | O93: TRUE | Q93: EN ALMACEN 11 | R93: N/A | S93: TRUE | T93: N/A | U93: TRUE
B94: 233 | C94: CBL 5 Lead ECG Trunk AAMI/IEC 2.7m | D94: 1 | E94: PZ | H94: M1668A | I94: PHILIPS | J94: Manprec | K94: 70.8 | L94: USD | M94: Manprec | N94: MAN01003 | O94: TRUE | Q94: PENDIENTE | R94: N/A | S94: TRUE | T94: N/A | U94: TRUE
B95: 233 | C95: CBL 5 Leadset Snap AAMI ICU | D95: 1 | E95: PZ | H95: M1644A | I95: PHILIPS | J95: Manprec | K95: 67.8 | L95: USD | M95: Manprec | N95: Stock | O95: TRUE | Q95: EN ALMACEN 11 | R95: N/A | S95: TRUE | T95: N/A | U95: TRUE
B96: 233 | C96: CBL 10 Lead ECG Trunk AAMI/IEC 2m | D96: 1 | E96: PZ | H96: M1663A | I96: PHILIPS | J96: Manprec | K96: 153 | L96: USD | M96: Manprec | N96: MAN01003 | O96: TRUE | Q96: PENDIENTE | R96: N/A | S96: TRUE | T96: N/A | U96: TRUE
B97: 233 | C97: CBL 5 Leadset Grabber AAMI ICU | D97: 1 | E97: PZ | H97: M1968A | I97: PHILIPS | J97: Manprec | K97: 54 | L97: USD | M97: Manprec | N97: Stock | O97: TRUE | Q97: EN ALMACEN 11 | R97: N/A | S97: TRUE | T97: N/A | U97: TRUE
B98: 233 | C98: CBL 5 Leadset Grabber Chest AAMI ICU | D98: 1 | E98: PZ | H98: M1976A | I98: PHILIPS | J98: Manprec | K98: 68.4 | L98: USD | M98: Manprec | N98: Stock | O98: TRUE | Q98: EN ALMACEN 11 | R98: N/A | S98: TRUE | T98: N/A | U98: TRUE
B99: 233 | C99: SPO2 Reus Neo Hnd-Ft Wrap Sensor M1193A | D99: 1 | E99: PZ | H99: 989803205881 | I99: PHILIPS | J99: Manprec | K99: 101.4 | L99: USD | M99: Manprec | N99: MAN01003 | O99: TRUE | Q99: PENDIENTE | R99: N/A | S99: TRUE | T99: N/A | U99: TRUE
B100: 233 | C100: Neonatal NIBP Air Hose 3.0m | D100: 1 | E100: PZ | H100: 989803209751 | I100: PHILIPS | J100: Manprec | K100: 23.94 | L100: USD | M100: Manprec | N100: Stock | O100: TRUE | Q100: EN ALMACEN 11 | R100: N/A | S100: TRUE | T100: N/A | U100: TRUE
...

Sheet Comercializadora de la Puebla d
A1: PEDIDO | B1: PARTIDA | C1: DESCRIPCIÓN | D1: CANTIDAD | E1: UDM | F1: MARCA | G1: MODELO | H1: CÓDIGO | I1: PROVEEDOR | J1: Empresa que vende | K1: COSTO | L1: MONEDA COSTO | M1: EMPRESA QUE COMPRA | N1: OC | O1: B2B | P1: OBSERVACIONES | Q1: ESTATUS | R1: OV-INT | S1: Status de Interempresa | T1: OC-INT | U1: Status de Interempresa
A2: MPC27819 | B2: 1 | C2: Monitor materno fetal (Cardiotocógrafo) | D2: 1 | E2: PZ | H2: M2702A.1 | I2: PHILIPS | J2: MPC | K2: 2483.65 | L2: USD | M2: Manprec | N2: Stock | O2: FALSE | Q2: EN ALMACEN 11 | R2: MAN13294 | S2: TRUE | T2: MPC04479 | U2: TRUE
C3: Avalon US Transducer | D3: 2 | E3: PZ | H3: 867246 | I3: PHILIPS | J3: MPC | K3: 553.2 | L3: USD | M3: Manprec | O3: FALSE | R3: MAN13294 | S3: TRUE | T3: MPC04479 | U3: TRUE
C4: Avalon TOCO | D4: 2 | E4: PZ | H4: 867248 | I4: PHILIPS | J4: MPC | K4: 601.8 | L4: USD | M4: Manprec | O4: FALSE | R4: MAN13294 | S4: TRUE | T4: MPC04479 | U4: TRUE
C5: Remote Event Marker | D5: 1 | E5: PZ | H5: 989803143411 | I5: PHILIPS | J5: MPC | K5: 114 | L5: USD | M5: Manprec | O5: FALSE | R5: MAN13294 | S5: TRUE | T5: MPC04479 | U5: TRUE
C6: Reusable Abdominal Belt- 60mm Wd 1.3M Lg | D6: 2 | E6: PZ | H6: CINFM | I6: GUSTAVO EDUARDO AVILA WOO | J6: MPC | K6: =1092/8 -> 136.5 | L6: MXN | M6: Manprec | N6: MAN00961 | O6: FALSE | P6: STOCK | Q6: EN ALMACEN 11 | R6: MAN13294 | S6: TRUE | T6: MPC04479 | U6: TRUE
C7: Carro de transporte TPX para Cardiotoco Avalon FM20/FM30 | D7: 1 | E7: PZ | H7: RP050-FM | I7: TPX | J7: MPC | K7: 115 | L7: USD | M7: N/A | N7: MPC04399 | O7: FALSE | Q7: EN ALMACEN 11 | R7: N/A | S7: TRUE | T7: N/A | U7: TRUE
C8: Fetal monitoring recording paper | D8: 1 | E8: C/40 | H8: M1910A | I8: AKUASUL | J8: MPC | K8: 2640 | L8: MXN | M8: Manprec | N8: MAN01009 | O8: FALSE | Q8: EN ALMACEN 11 | R8: MAN13294 | S8: TRUE | T8: MPC04479 | U8: TRUE
A9: MPC27819 | B9: 2 | C9: Monitor IntelliVue MX500 | D9: 0 | E9: PZ | H9: 866064.3 | I9: PHILIPS | J9: MPC | K9: 3089.63 | L9: USD | M9: MPC | N9: MPC04368 | O9: FALSE | Q9: PENDIENTE | S9: FALSE | U9: FALSE
A10: MPC27819 | B10: 2.1 | C10: Módulo IntelliVue MMX | D10: 0 | E10: PZ | H10: 867036.4 | I10: PHILIPS | J10: MPC | K10: 2183.85 | L10: USD | M10: MPC | N10: MPC04368 | O10: FALSE | Q10: PENDIENTE | S10: FALSE | U10: FALSE
C11: Temperature Parameter Module | D11: 0 | E11: PZ | H11: M1029A | I11: PHILIPS | J11: MPC | K11: 267.27 | L11: USD | M11: MPC | N11: MPC04368 | O11: FALSE | Q11: PENDIENTE | S11: FALSE | U11: FALSE
C12: Reusable Adult SpO2 Sensor | D12: 0 | E12: PZ | H12: M1191BL | I12: PHILIPS | J12: MPC | K12: 93.08 | L12: USD | M12: MPC | N12: MPC04368 | O12: FALSE | Q12: PENDIENTE | S12: FALSE | U12: FALSE
C13: SPO2 Reus Ped-Adult Glove Sensor M1192A | D13: 0 | E13: PZ | H13: 989803205871 | I13: PHILIPS | J13: MPC | K13: 92.54 | L13: USD | M13: MPC | N13: MPC04368 | O13: FALSE | Q13: PENDIENTE | S13: FALSE | U13: FALSE
C14: CBL SpO2 Extension Cable 2m | D14: 0 | E14: PZ | H14: M1941A | I14: PHILIPS | J14: MPC | K14: 41.91 | L14: USD | M14: MPC | N14: MPC04368 | O14: FALSE | Q14: PENDIENTE | S14: FALSE | U14: FALSE
C15: CBL 5 Lead ECG Trunk AAMI/IEC 2.7m | D15: 0 | E15: PZ | H15: M1668A | I15: PHILIPS | J15: MPC | K15: 64.23 | L15: USD | M15: MPC | N15: MPC04368 | O15: FALSE | Q15: PENDIENTE | S15: FALSE | U15: FALSE
C16: CBL 5 Leadset Snap AAMI ICU | D16: 0 | E16: PZ | H16: M1644A | I16: PHILIPS | J16: MPC | K16: 61.51 | L16: USD | M16: MPC | N16: MPC04368 | O16: FALSE | Q16: PENDIENTE | S16: FALSE | U16: FALSE
C17: Adult NIBP Air Hose 3.0m | D17: 0 | E17: PZ | H17: 989803209771 | I17: PHILIPS | J17: MPC | K17: 22.37 | L17: USD | M17: MPC | N17: MPC04368 | O17: FALSE | Q17: PENDIENTE | S17: FALSE | U17: FALSE
C18: Mainstream Sensor | D18: 0 | E18: PZ | H18: M2501A | I18: PHILIPS | J18: MPC | K18: 1340.14 | L18: USD | M18: MPC | N18: MPC04368 | O18: FALSE | Q18: PENDIENTE | S18: FALSE | U18: FALSE
C19: Airway Adapter-Reusable-Adult/Pediatric | D19: 0 | E19: PZ | H19: 989803206591 | I19: PHILIPS | J19: MPC | K19: 105.06 | L19: USD | M19: MPC | N19: MPC04368 | O19: FALSE | Q19: PENDIENTE | S19: FALSE | U19: FALSE
C20: Easy Care Cuff 1 Hose Infant (1) | D20: 0 | E20: PZ | H20: M4552B | I20: PHILIPS | J20: MPC | K20: 9.04 | L20: USD | M20: MPC | N20: MPC04368 | O20: FALSE | Q20: PENDIENTE | S20: FALSE | U20: FALSE
C21: Easy Care Cuff 1 Hose Pediatric (1) | D21: 0 | E21: PZ | H21: M4553B | I21: PHILIPS | J21: MPC | K21: 21.72 | L21: USD | M21: MPC | N21: MPC04368 | O21: FALSE | Q21: PENDIENTE | S21: FALSE | U21: FALSE
C22: Easy Care Cuff 1 Hose Adult (1) | D22: 0 | E22: PZ | H22: M4555B | I22: PHILIPS | J22: MPC | K22: 10.29 | L22: USD | M22: MPC | N22: MPC04368 | O22: FALSE | Q22: PENDIENTE | S22: FALSE | U22: FALSE
C23: SENSOR DE TEMPERATURA | D23: 0 | E23: PZ | H23: 21078ST | I23: HOSPIINNOVA | J23: MPC | K23: 871.3 | L23: MXN | M23: Manprec | O23: FALSE | S23: FALSE | U23: FALSE
C24: PLACA DE TRANSDUCTOR LOGICAL REUSABLE | D24: 0 | E24: PZ | H24: MX960 | I24: ATSA | J24: MPC | K24: 3142.1 | L24: MXN | M24: Manprec | N24: MAN01013 | O24: FALSE | Q24: EN ALMACEN 11 | S24: FALSE | U24: FALSE
C25: SOPORTE P/ PLACA DE TRANSDUCTOR LOGICAL | D25: 0 | E25: PZ | H25: MX261 | I25: ATSA | J25: MPC | K25: 491.9 | L25: MXN | M25: Manprec | N25: MAN01013 | O25: FALSE | Q25: EN ALMACEN 11 | S25: FALSE | U25: FALSE
C26: BRACKET PARA DOS TRANSDUCTORES | D26: 0 | E26: PZ | H26: MX262 | I26: ATSA | J26: MPC | K26: 337.3 | L26: MXN | M26: Manprec | N26: MAN01013 | O26: FALSE | Q26: EN ALMACEN 11 | S26: FALSE | U26: FALSE
C27: CABLE TRONCAL MONITOR PHILIPS TECNOLOGIA LOGICAL | D27: 0 | E27: PZ | H27: BC-HP-MX1 | I27: ATSA | J27: MPC | K27: 1014.3 | L27: MXN | M27: Manprec | N27: MAN01013 | O27: FALSE | Q27: EN ALMACEN 11 | S27: FALSE | U27: FALSE
C28: KIT DE MONITOREO LOGICAL DESECHABLE | D28: 0 | E28: PZ | H28: MX9604A | I28: ATSA | J28: MPC | K28: 363.8 | L28: MXN | M28: Manprec | N28: MAN01013 | O28: FALSE | Q28: EN ALMACEN 11 | S28: FALSE | U28: FALSE
C29: Brazo de soporte giratorio TPX | D29: 0 | E29: PZ | H29: WP010-MX | I29: TPX | J29: MPC | K29: 115 | L29: USD | M29: MPC | N29: MPC04399 | O29: FALSE | Q29: PENDIENTE | R29: N/A | S29: TRUE | T29: N/A | U29: TRUE
A30: MPC27819 | B30: 3 | C30: Monitor IntelliVue MX450 | D30: 1 | E30: PZ | H30: 866062.2 | I30: PHILIPS | J30: MPC | K30: 2366.75 | L30: USD | M30: N/A | N30: MPC04368 | O30: FALSE | Q30: EN ALMACEN 11 | S30: FALSE | U30: FALSE
A31: MPC27819 | B31: 3.1 | C31: Módulo IntelliVue MMX | D31: 1 | E31: PZ | H31: 867036.1 | I31: PHILIPS | J31: MPC | K31: 1167.58 | L31: USD | M31: N/A | N31: MPC04368 | O31: FALSE | Q31: EN ALMACEN 11 | S31: FALSE | U31: FALSE
C32: CBL 5 Lead ECG Trunk AAMI/IEC 2.7m | D32: 4 | E32: PZ | H32: M1668A | I32: PHILIPS | J32: MPC | K32: 64.23 | L32: USD | M32: N/A | N32: MPC04368 | O32: FALSE | Q32: EN ALMACEN 11 | S32: FALSE | U32: FALSE
C33: CBL 5 Leadset Snap AAMI ICU | D33: 4 | E33: PZ | H33: M1644A | I33: PHILIPS | J33: MPC | K33: 61.51 | L33: USD | M33: N/A | N33: MPC04368 | O33: FALSE | Q33: EN ALMACEN 11 | S33: FALSE | U33: FALSE
C34: CBL 3 Lead ECG Trunk AAMI/IEC 2.7m | D34: 2 | E34: PZ | H34: M1669A | I34: PHILIPS | J34: MPC | K34: 50.08 | L34: USD | M34: N/A | N34: MPC04368 | O34: FALSE | Q34: EN ALMACEN 11 | S34: FALSE | U34: FALSE
C35: CBL 3 Leadset Snap AAMI ICU | D35: 2 | E35: PZ | H35: M1673A | I35: PHILIPS | J35: MPC | K35: 41.91 | L35: USD | M35: N/A | N35: MPC04368 | O35: FALSE | Q35: EN ALMACEN 11 | S35: FALSE | U35: FALSE
C36: Easy Care Cuff 1 Hose Adult (1) | D36: 5 | E36: PZ | H36: M4555B | I36: PHILIPS | J36: MPC | K36: 10.29 | L36: USD | M36: N/A | N36: MPC04368 | O36: FALSE | Q36: EN ALMACEN 11 | S36: FALSE | U36: FALSE
C37: Adult NIBP Air Hose 3.0m | D37: 1 | E37: PZ | H37: 989803209771 | I37: PHILIPS | J37: MPC | K37: 22.37 | L37: USD | M37: N/A | N37: MPC04368 | O37: FALSE | Q37: EN ALMACEN 11 | S37: FALSE | U37: FALSE
C38: SPO2 Reus Ped-Adult Glove Sensor M1192A | D38: 2 | E38: PZ | H38: 989803205871 | I38: PHILIPS | J38: MPC | K38: 92.54 | L38: USD | M38: N/A | N38: MPC04368 | O38: FALSE | Q38: EN ALMACEN 11 | S38: FALSE | U38: FALSE
C39: SPO2 Reus Neo Hnd-Ft Wrap Sensor M1193A | D39: 2 | E39: PZ | H39: 989803205881 | I39: PHILIPS | J39: MPC | K39: 91.99 | L39: USD | M39: N/A | N39: MPC04368 | O39: FALSE | Q39: EN ALMACEN 11 | S39: FALSE | U39: FALSE
C40: CBL SpO2 Extension Cable 2m | D40: 1 | E40: PZ | H40: M1941A | I40: PHILIPS | J40: MPC | K40: 41.91 | L40: USD | M40: N/A | N40: MPC04368 | O40: FALSE | Q40: EN ALMACEN 11 | S40: FALSE | U40: FALSE
C41: Reusable Adult SpO2 Sensor | D41: 2 | E41: PZ | H41: M1191BL | I41: PHILIPS | J41: MPC | K41: 93.08 | L41: USD | M41: N/A | N41: MPC04368 | O41: FALSE | Q41: EN ALMACEN 11 | S41: FALSE | U41: FALSE
C42: Easy Care Cuff 1 Hose Infant (1) | D42: 5 | E42: PZ | H42: M4552B | I42: PHILIPS | J42: MPC | K42: 9.04 | L42: USD | M42: N/A | N42: MPC04368 | O42: FALSE | Q42: EN ALMACEN 11 | S42: FALSE | U42: FALSE
C43: Easy Care Cuff 1 Hose Pediatric (1) | D43: 6 | E43: PZ | H43: M4553B | I43: PHILIPS | J43: MPC | K43: 21.72 | L43: USD | M43: N/A | N43: MPC04368 | O43: FALSE | Q43: EN ALMACEN 11 | S43: FALSE | U43: FALSE
C44: SENSOR DE TEMPERATURA | D44: 6 | E44: PZ | H44: 21078ST | I44: HOSPIINNOVA | J44: MPC | K44: 871.3 | L44: MXN | M44: Manprec | N44: MAN00996 | O44: FALSE | Q44: EN ALMACEN 11 | S44: FALSE | U44: FALSE
C45: Carro de transporte TPX para monitor de S.V. Philips Efficia/Goldway | D45: 1 | E45: PZ | H45: RP050 | I45: TPX | J45: MPC | K45: 115 | L45: USD | M45: N/A | N45: MPC04399 | O45: FALSE | Q45: EN ALMACEN 11 | R45: N/A | S45: TRUE | T45: N/A | U45: TRUE
A46: MPC27819 | B46: 4 | C46: Monitor IntelliVue MX450 | D46: 0 | E46: PZ | H46: 866062.2 | I46: PHILIPS | J46: MPC | K46: 2366.75 | L46: USD | M46: MPC | N46: MPC04368 | O46: FALSE | Q46: PENDIENTE | S46: FALSE | U46: FALSE
A47: MPC27819 | B47: 4.1 | C47: Módulo IntelliVue MMX | D47: 0 | E47: PZ | H47: 867036.1 | I47: PHILIPS | J47: MPC | K47: 1167.58 | L47: USD | M47: MPC | N47: MPC04368 | O47: FALSE | Q47: PENDIENTE | S47: FALSE | U47: FALSE
C48: CBL 5 Lead ECG Trunk AAMI/IEC 2.7m | D48: 0 | E48: PZ | H48: M1668A | I48: PHILIPS | J48: MPC | K48: 64.23 | L48: USD | M48: MPC | N48: MPC04368 | O48: FALSE | Q48: PENDIENTE | S48: FALSE | U48: FALSE
C49: CBL 5 Leadset Snap AAMI ICU | D49: 0 | E49: PZ | H49: M1644A | I49: PHILIPS | J49: MPC | K49: 61.51 | L49: USD | M49: MPC | N49: MPC04368 | O49: FALSE | Q49: PENDIENTE | S49: FALSE | U49: FALSE
C50: CBL 3 Lead ECG Trunk AAMI/IEC 2.7m | D50: 0 | E50: PZ | H50: M1669A | I50: PHILIPS | J50: MPC | K50: 50.08 | L50: USD | M50: MPC | N50: MPC04368 | O50: FALSE | Q50: PENDIENTE | S50: FALSE | U50: FALSE
C51: CBL 3 Leadset Snap AAMI ICU | D51: 0 | E51: PZ | H51: M1673A | I51: PHILIPS | J51: MPC | K51: 41.91 | L51: USD | M51: MPC | N51: MPC04368 | O51: FALSE | Q51: PENDIENTE | S51: FALSE | U51: FALSE
C52: Easy Care Cuff 1 Hose Adult (1) | D52: 0 | E52: PZ | H52: M4555B | I52: PHILIPS | J52: MPC | K52: 10.29 | L52: USD | M52: MPC | N52: MPC04368 | O52: FALSE | Q52: PENDIENTE | S52: FALSE | U52: FALSE
C53: Adult NIBP Air Hose 3.0m | D53: 0 | E53: PZ | H53: 989803209771 | I53: PHILIPS | J53: MPC | K53: 22.37 | L53: USD | M53: MPC | N53: MPC04368 | O53: FALSE | Q53: PENDIENTE | S53: FALSE | U53: FALSE
C54: SPO2 Reus Ped-Adult Glove Sensor M1192A | D54: 0 | E54: PZ | H54: 989803205871 | I54: PHILIPS | J54: MPC | K54: 92.54 | L54: USD | M54: MPC | N54: MPC04368 | O54: FALSE | Q54: PENDIENTE | S54: FALSE | U54: FALSE
C55: SPO2 Reus Neo Hnd-Ft Wrap Sensor M1193A | D55: 0 | E55: PZ | H55: 989803205881 | I55: PHILIPS | J55: MPC | K55: 91.99 | L55: USD | M55: MPC | N55: MPC04368 | O55: FALSE | Q55: PENDIENTE | S55: FALSE | U55: FALSE
C56: CBL SpO2 Extension Cable 2m | D56: 0 | E56: PZ | H56: M1941A | I56: PHILIPS | J56: MPC | K56: 41.91 | L56: USD | M56: MPC | N56: MPC04368 | O56: FALSE | Q56: PENDIENTE | S56: FALSE | U56: FALSE
C57: Reusable Adult SpO2 Sensor | D57: 0 | E57: PZ | H57: M1191BL | I57: PHILIPS | J57: MPC | K57: 93.08 | L57: USD | M57: MPC | N57: MPC04368 | O57: FALSE | Q57: PENDIENTE | S57: FALSE | U57: FALSE
C58: Easy Care Cuff 1 Hose Infant (1) | D58: 0 | E58: PZ | H58: M4552B | I58: PHILIPS | J58: MPC | K58: 9.04 | L58: USD | M58: MPC | N58: MPC04368 | O58: FALSE | Q58: PENDIENTE | S58: FALSE | U58: FALSE
C59: Easy Care Cuff 1 Hose Pediatric (1) | D59: 0 | E59: PZ | H59: M4553B | I59: PHILIPS | J59: MPC | K59: 21.72 | L59: USD | M59: MPC | N59: MPC04368 | O59: FALSE | Q59: PENDIENTE | S59: FALSE | U59: FALSE
C60: SENSOR DE TEMPERATURA | D60: 0 | E60: PZ | H60: 21078ST | I60: HOSPIINNOVA | J60: MPC | K60: 871.3 | L60: USD | M60: Manprec | O60: FALSE | S60: FALSE | U60: FALSE
C61: Carro de transporte TPX para monitor de S.V. Philips Efficia/Goldway | D61: 0 | E61: PZ | H61: RP050 | I61: TPX | J61: MPC | K61: 115 | L61: USD | M61: MPC | N61: MPC04399 | O61: FALSE | Q61: PENDIENTE | R61: N/A | S61: TRUE | T61: N/A | U61: TRUE
A62: MPC27819 | B62: 5 | C62: Monitor IntelliVue MX450 | D62: 0 | E62: PZ | H62: 866062.2 | I62: PHILIPS | J62: MPC | K62: 2366.75 | L62: USD | M62: MPC | N62: MPC04368 | O62: FALSE | Q62: PENDIENTE | S62: FALSE | U62: FALSE
A63: MPC27819 | B63: 5.1 | C63: Módulo IntelliVue MMX | D63: 0 | E63: PZ | H63: 867036.1 | I63: PHILIPS | J63: MPC | K63: 1167.58 | L63: USD | M63: MPC | N63: MPC04368 | O63: FALSE | Q63: PENDIENTE | S63: FALSE | U63: FALSE
C64: CBL 3 Lead ECG Trunk AAMI/IEC 2.7m | D64: 0 | E64: PZ | H64: M1669A | I64: PHILIPS | J64: MPC | K64: 50.08 | L64: USD | M64: MPC | N64: MPC04368 | O64: FALSE | Q64: PENDIENTE | S64: FALSE | U64: FALSE
C65: CBL 3 Leadset Snap AAMI ICU | D65: 0 | E65: PZ | H65: M1673A | I65: PHILIPS | J65: MPC | K65: 41.91 | L65: USD | M65: MPC | N65: MPC04368 | O65: FALSE | Q65: PENDIENTE | S65: FALSE | U65: FALSE
C66: Easy Care Cuff 1 Hose Adult (1) | D66: 0 | E66: PZ | H66: M4555B | I66: PHILIPS | J66: MPC | K66: 10.29 | L66: USD | M66: MPC | N66: MPC04368 | O66: FALSE | Q66: PENDIENTE | S66: FALSE | U66: FALSE
C67: Adult NIBP Air Hose 3.0m | D67: 0 | E67: PZ | H67: 989803209771 | I67: PHILIPS | J67: MPC | K67: 22.37 | L67: USD | M67: MPC | N67: MPC04368 | O67: FALSE | Q67: PENDIENTE | S67: FALSE | U67: FALSE
C68: Reusable Adult SpO2 Sensor | D68: 0 | E68: PZ | H68: M1191BL | I68: PHILIPS | J68: MPC | K68: 93.08 | L68: USD | M68: MPC | N68: MPC04368 | O68: FALSE | Q68: PENDIENTE | S68: FALSE | U68: FALSE
C69: Easy Care Cuff 1 Hose Pediatric (1) | D69: 0 | E69: PZ | H69: M4553B | I69: PHILIPS | J69: MPC | K69: 21.72 | L69: USD | M69: MPC | N69: MPC04368 | O69: FALSE | Q69: PENDIENTE | S69: FALSE | U69: FALSE
C70: SENSOR DE TEMPERATURA | D70: 0 | E70: PZ | H70: 21078ST | I70: HOSPIINNOVA | J70: MPC | K70: 871.3 | L70: MXN | M70: Manprec | O70: FALSE | S70: FALSE | U70: FALSE
C71: Carro de transporte TPX para monitor de S.V. Philips Efficia/Goldway | D71: 0 | E71: PZ | H71: RP050 | I71: TPX | J71: MPC | K71: 115 | L71: USD | M71: MPC | N71: MPC04399 | O71: FALSE | Q71: PENDIENTE | R71: N/A | S71: TRUE | T71: N/A | U71: TRUE
A72: MPC27819 | B72: 6 | C72: Monitor IntelliVue MX500 | D72: 0 | E72: PZ | H72: 866064.3 | I72: PHILIPS | J72: MPC | K72: 3089.63 | L72: USD | M72: MPC | N72: MPC04368 | O72: FALSE | Q72: PENDIENTE | S72: FALSE | U72: FALSE
A73: MPC27819 | B73: 6.1 | C73: Módulo IntelliVue MMX | D73: 0 | E73: PZ | H73: 867036.1 | I73: PHILIPS | J73: MPC | K73: 1232.36 | L73: USD | M73: MPC | N73: MPC04368 | O73: FALSE | Q73: PENDIENTE | S73: FALSE | U73: FALSE
C74: Temperature Parameter Module | D74: 0 | E74: PZ | H74: M1029A | I74: PHILIPS | J74: MPC | K74: 267.27 | L74: USD | M74: MPC | N74: MPC04368 | O74: FALSE | Q74: PENDIENTE | S74: FALSE | U74: FALSE
C75: Reusable Adult SpO2 Sensor | D75: 0 | E75: PZ | H75: M1191BL | I75: PHILIPS | J75: MPC | K75: 93.08 | L75: USD | M75: MPC | N75: MPC04368 | O75: FALSE | Q75: PENDIENTE | S75: FALSE | U75: FALSE
C76: SPO2 Reus Neo Hnd-Ft Wrap Sensor M1193A | D76: 0 | E76: PZ | H76: 989803205881 | I76: PHILIPS | J76: MPC | K76: 91.99 | L76: USD | M76: MPC | N76: MPC04368 | O76: FALSE | Q76: PENDIENTE | S76: FALSE | U76: FALSE
C77: CBL SpO2 Extension Cable 2m | D77: 0 | E77: PZ | H77: M1941A | I77: PHILIPS | J77: MPC | K77: 41.91 | L77: USD | M77: MPC | N77: MPC04368 | O77: FALSE | Q77: PENDIENTE | S77: FALSE | U77: FALSE
C78: CBL 5 Lead ECG Trunk AAMI/IEC 2.7m | D78: 0 | E78: PZ | H78: M1668A | I78: PHILIPS | J78: MPC | K78: 64.23 | L78: USD | M78: MPC | N78: MPC04368 | O78: FALSE | Q78: PENDIENTE | S78: FALSE | U78: FALSE
C79: CBL 5 Leadset Snap AAMI ICU | D79: 0 | E79: PZ | H79: M1644A | I79: PHILIPS | J79: MPC | K79: 61.51 | L79: USD | M79: MPC | N79: MPC04368 | O79: FALSE | Q79: PENDIENTE | S79: FALSE | U79: FALSE
C80: Adult NIBP Air Hose 3.0m | D80: 0 | E80: PZ | H80: 989803209771 | I80: PHILIPS | J80: MPC | K80: 22.37 | L80: USD | M80: MPC | N80: MPC04368 | O80: FALSE | Q80: PENDIENTE | S80: FALSE | U80: FALSE
C81: Easy Care Cuff 1 Hose Infant (1) | D81: 0 | E81: PZ | H81: M4552B | I81: PHILIPS | J81: MPC | K81: 9.04 | L81: USD | M81: MPC | N81: MPC04368 | O81: FALSE | Q81: PENDIENTE | S81: FALSE | U81: FALSE
C82: Easy Care Cuff 1 Hose Pediatric (1) | D82: 0 | E82: PZ | H82: M4553B | I82: PHILIPS | J82: MPC | K82: 21.72 | L82: USD | M82: MPC | N82: MPC04368 | O82: FALSE | Q82: PENDIENTE | S82: FALSE | U82: FALSE
C83: Easy Care Cuff 1 Hose Adult (1) | D83: 0 | E83: PZ | H83: M4555B | I83: PHILIPS | J83: MPC | K83: 10.29 | L83: USD | M83: MPC | N83: MPC04368 | O83: FALSE | Q83: PENDIENTE | S83: FALSE | U83: FALSE
C84: Easy Care Cuff 1 Hose Thigh (1) | D84: 0 | E84: PZ | H84: M4559B | I84: PHILIPS | J84: MPC | K84: 30.48 | L84: USD | M84: MPC | N84: MPC04368 | O84: FALSE | Q84: PENDIENTE | S84: FALSE | U84: FALSE
C85: SENSOR DE TEMPERATURA | D85: 0 | E85: PZ | H85: 21078ST | I85: HOSPIINNOVA | J85: MPC | K85: 871.3 | L85: MXN | M85: Manprec | O85: FALSE | S85: FALSE | U85: FALSE
C86: PLACA DE TRANSDUCTOR LOGICAL REUSABLE | D86: 0 | E86: PZ | H86: MX960 | I86: ATSA | J86: MPC | K86: 3142.1 | L86: MXN | M86: Manprec | N86: MAN01013 | O86: FALSE | Q86: EN ALMACEN 11 | S86: FALSE | U86: FALSE
C87: SOPORTE P/ PLACA DE TRANSDUCTOR LOGICAL | D87: 0 | E87: PZ | H87: MX261 | I87: ATSA | J87: MPC | K87: 491.9 | L87: MXN | M87: Manprec | N87: MAN01013 | O87: FALSE | Q87: EN ALMACEN 11 | S87: FALSE | U87: FALSE
C88: BRACKET PARA DOS TRANSDUCTORES | D88: 0 | E88: PZ | H88: MX262 | I88: ATSA | J88: MPC | K88: 337.3 | L88: MXN | M88: Manprec | N88: MAN01013 | O88: FALSE | Q88: EN ALMACEN 11 | S88: FALSE | U88: FALSE
C89: CABLE TRONCAL MONITOR PHILIPS TECNOLOGIA LOGICAL | D89: 0 | E89: PZ | H89: BC-HP-MX1 | I89: ATSA | J89: MPC | K89: 1014.3 | L89: MXN | M89: Manprec | N89: MAN01013 | O89: FALSE | Q89: EN ALMACEN 11 | S89: FALSE | U89: FALSE
C90: KIT DE MONITOREO LOGICAL DESECHABLE | D90: 0 | E90: PZ | H90: MX9604A | I90: ATSA | J90: MPC | K90: 363.8 | L90: MXN | M90: Manprec | N90: MAN01013 | O90: FALSE | Q90: EN ALMACEN 11 | S90: FALSE | U90: FALSE
C91: Brazo de soporte giratorio TPX | D91: 0 | E91: PZ | H91: WP010-MX | I91: TPX | J91: MPC | K91: 78 | L91: USD | M91: MPC | N91: MPC04399 | O91: FALSE | Q91: PENDIENTE | R91: N/A | S91: TRUE | T91: N/A | U91: TRUE
A92: MPC27819 | B92: 7 | C92: Monitor materno fetal (Cardiotocógrafo) | D92: 5 | E92: PZ | H92: M2702A.1 | I92: PHILIPS | J92: MPC | K92: 2483.65 | L92: USD | M92: Manprec | N92: Stock | O92: FALSE | Q92: - | S92: FALSE | U92: FALSE
C93: Avalon US Transducer | D93: 10 | E93: PZ | H93: 867246 | I93: PHILIPS | J93: MPC | K93: 553.2 | L93: USD | M93: MPC | O93: FALSE | S93: FALSE | U93: FALSE
C94: Avalon TOCO | D94: 10 | E94: PZ | H94: 867248 | I94: PHILIPS | J94: MPC | K94: 601.8 | L94: USD | M94: MPC | O94: FALSE | S94: FALSE | U94: FALSE
C95: Remote Event Marker | D95: 5 | E95: PZ | H95: 989803143411 | I95: PHILIPS | J95: MPC | K95: 114 | L95: USD | M95: MPC | O95: FALSE | S95: FALSE | U95: FALSE
C96: Reusable Abdominal Belt- 60mm Wd 1.3M Lg | D96: 10 | E96: PZ | H96: CINFM | I96: GUSTAVO EDUARDO AVILA WOO | J96: MPC | K96: =1092/8 -> 136.5 | L96: MXN | M96: Manprec | N96: MAN00961 | O96: FALSE | P96: STOCK | Q96: EN ALMACEN 11 | R96: MAN13294 | S96: TRUE | T96: MPC04479 | U96: TRUE
C97: Carro de transporte TPX para Cardiotoco Avalon FM20/FM30 | D97: 5 | E97: PZ | H97: RP050-FM | I97: TPX | J97: MPC | K97: 115 | L97: USD | M97: MPC | N97: MPC04399 | O97: FALSE | Q97: PENDIENTE | R97: N/A | S97: TRUE | T97: N/A | U97: TRUE
C98: Fetal monitoring recording paper | D98: 5 | E98: C/40 | H98: M1910A | I98: AKUASUL | J98: MPC | K98: 120 | L98: USD | M98: N/A | O98: FALSE | Q98: EN ALMACEN 11 | S98: FALSE | U98: FALSE
A99: MPC27819 | B99: 8 | C99: Sistema de ultrasonido | D99: 0 | E99: PZ | H99: NUSX001 | I99: PHILIPS | J99: MPC | K99: 121682.94 | L99: USD | M99: MPC | N99: MPC04367 | O99: FALSE | Q99: - | S99: FALSE | U99: FALSE
C100: UPS de 2KVA | D100: 0 | E100: PZ | H100: PA MG+15-2200-UN | I100: ALTERNATIVA | J100: MPC | K100: 260.63 | L100: USD | M100: Gamit | N100: GAM00053 | O100: FALSE | S100: FALSE | U100: FALSE
...

Sheet ABASTECEDORA MUNDO MEDICO
A1: PEDIDO | B1: PARTIDA | C1: DESCRIPCIÓN | D1: CANTIDAD | E1: UDM | F1: MARCA | G1: MODELO | H1: CÓDIGO | I1: PROVEEDOR | J1: Empresa que vende | K1: COSTO | L1: MONEDA COSTO | M1: EMPRESA QUE COMPRA | N1: OC | O1: B2B | P1: OBSERVACIONES | Q1: ESTATUS | R1: OV-INT | S1: Status de Interempresa | T1: OC-INT | U1: Status de Interempresa
A2: MAN13251 | B2: 1 | C2: CARDIOTOCOGRAFOAVALON FM30 GEMELAR CON BATERIA | D2: 3 | E2: PZ | H2: M2703A.2 | I2: PHILIPS | J2: Manprec | K2: 4419.35 | L2: USD | M2: Manprec | N2: MAN01007 | O2: FALSE | P2: SIN CDD | Q2: EN ALMACEN 11 | R2: N/A | S2: TRUE | T2: N/A | U2: TRUE
C3: TRANSDUCTOR DE ACTIVIDAD UTERINA | D3: 3 | E3: PZ | H3: 867248 | I3: PHILIPS | J3: Manprec | K3: 553.2 | L3: USD | M3: Manprec | N3: MAN01012 | O3: TRUE | Q3: EN ALMACEN 11 | R3: N/A | S3: TRUE | T3: N/A | U3: TRUE
C4: TRANSDUCTOR ULTRASONIDO | D4: 6 | E4: PZ | H4: 867246 | I4: PHILIPS | J4: Manprec | K4: 601.8 | L4: USD | M4: Manprec | N4: MAN01012 | O4: TRUE | Q4: EN ALMACEN 11 | R4: N/A | S4: TRUE | T4: N/A | U4: TRUE
C5: MARCADOR DE EVENTOS | D5: 3 | E5: PZ | H5: 989803143411 | I5: PHILIPS | J5: Manprec | K5: 114 | L5: USD | M5: Manprec | N5: STOCK | O5: TRUE | P5: Stock | Q5: EN ALMACEN 11 | R5: N/A | S5: TRUE | T5: N/A | U5: TRUE
C6: CARRO PORTA EQUIIPO | D6: 3 | E6: PZ | H6: RP050-FM | I6: TPX | J6: Manprec | K6: 115 | L6: USD | M6: MPC | N6: STOCK | O6: FALSE | Q6: EN ALMACEN 11 | R6: MPC28380 | S6: TRUE | T6: MAN01034 | U6: TRUE
C7: CINTURONES | D7: 6 | E7: PZ | H7: CINFM | I7: HOSPIINNOVA | J7: Manprec | K7: =1092/8 -> 136.5 | L7: MXN | M7: Manprec | N7: MAN00961 | O7: FALSE | Q7: EN ALMACEN 11 | R7: N/A | S7: TRUE | T7: N/A | U7: TRUE

Sheet SEDENA T-302
A1: PEDIDO | B1: PARTIDA | C1: DESCRIPCIÓN | D1: CANTIDAD | E1: UDM | F1: MARCA | G1: MODELO | H1: CÓDIGO | I1: PROVEEDOR | J1: Empresa que vende | K1: COSTO | L1: MONEDA COSTO | M1: EMPRESA QUE COMPRA | N1: OC | O1: B2B | P1: OBSERVACIONES | Q1: ESTATUS | R1: OV-INT | S1: Status de Interempresa | T1: OC-INT | U1: Status de Interempresa
A2: MPC27982 | B2: 99 | C2: Radiovisiografo dental | D2: 1 | E2: PZ | F2: Carestream dental | G2: RVG 6200 | H2: 5319819 | I2: Carestream dental | J2: MPC | K2: =2300*18 -> 41400 | L2: USD | M2: Manprec | N2: MAN01005 | O2: FALSE | Q2: - | R2: MAN13363 | S2: FALSE | U2: FALSE
C3: Base móvil para CS 2200 | D3: 1 | E3: PZ | F3: Carestream dental | H3: 5154281 | I3: Carestream dental | J3: MPC | K3: =1064*18 -> 19152 | L3: USD | M3: Manprec | N3: Stock | O3: FALSE | Q3: - | R3: MAN13363 | S3: FALSE | U3: FALSE
C4: RVG 6200 Radiovisógrafo Tamaño 2 + Licencia CSI8 10 activación | D4: 1 | E4: PZ | F4: Carestream dental | H4: 5310727 | I4: Carestream dental | J4: MPC | K4: =2490*18 -> 44820 | L4: USD | M4: Manprec | N4: MAN01005 | O4: FALSE | Q4: - | R4: MAN13363 | S4: FALSE | U4: FALSE
C5: Mandil Emplomado Para Rayos X Con Cinta Marca Shielding | D5: 1 | E5: PZ | H5: JDS536 | I5: NAFARRATE | J5: MPC | K5: =2931.6 -> 2931.6 | L5: MXN | M5: Manprec | N5: Stock | O5: FALSE | Q5: - | R5: MAN13363 | S5: FALSE | U5: FALSE
C6: Protector De Tiroides Marca Shielding | D6: 1 | E6: PZ | H6: JD611NSL | I6: NAFARRATE | J6: MPC | K6: 720.2 | L6: MXN | M6: N/A | N6: Stock | O6: FALSE | Q6: - | S6: FALSE | U6: FALSE
C7: Impresora monocromatica AGFA | D7: 1 | E7: PZ | F7: AGFA | H7: 5302 | I7: CHEYSER | J7: MPC | K7: 51300 | L7: MXN | M7: N/A | N7: MPC04490 | O7: FALSE | Q7: ENVIADA | S7: FALSE | U7: FALSE
C8: Laptop gamer | D8: 1 | E8: PZ | F8: DELL | H8: 210-BQPQ | I8: DELL | J8: MPC | K8: 2409.99 | L8: USD | M8: N/A | N8: MPC04487 | O8: FALSE | Q8: ENVIADA | S8: FALSE | U8: FALSE
C9: Licencia de windows 11 pro | D9: 1 | E9: PZ | H9: 43231513 | J9: MPC | K9: 2300 | L9: MXN | M9: N/A | N9: MPC04665 | O9: FALSE | Q9: - | S9: FALSE | U9: FALSE
C10: Pelicula AFGA DT500 | D10: 100 | E10: PZ | I10: ERRU6 | J10: MPC | K10: 2500 | L10: MXN | M10: N/A | N10: MPC04746 | O10: FALSE | P10: programar recoleccion | Q10: ENVIADA | S10: FALSE | U10: FALSE
O11: FALSE | Q11: - | S11: FALSE | U11: FALSE
O12: FALSE | Q12: - | S12: FALSE | U12: FALSE
O13: FALSE | Q13: - | S13: FALSE | U13: FALSE
O14: FALSE | Q14: - | S14: FALSE | U14: FALSE
O15: FALSE | Q15: - | S15: FALSE | U15: FALSE
O16: FALSE | Q16: - | S16: FALSE | U16: FALSE
O17: FALSE | Q17: - | S17: FALSE | U17: FALSE
O18: FALSE | Q18: - | S18: FALSE | U18: FALSE
O19: FALSE | Q19: - | S19: FALSE | U19: FALSE
O20: FALSE | Q20: - | S20: FALSE | U20: FALSE
O21: FALSE | Q21: - | S21: FALSE | U21: FALSE
O22: FALSE | Q22: - | S22: FALSE | U22: FALSE
... O30: FALSE | Q30: - | S30: FALSE | U30: FALSE

Sheet IMSS AGUASCALIENTES N-28
A1: PEDIDO | B1: PARTIDA | C1: DESCRIPCIÓN | D1: CANTIDAD | E1: UDM | F1: MARCA | G1: MODELO | H1: CÓDIGO | I1: PROVEEDOR | J1: Empresa que vende | K1: COSTO | L1: MONEDA COSTO | M1: EMPRESA QUE COMPRA | N1: OC | O1: B2B | P1: OBSERVACIONES | Q1: ESTATUS | R1: OV-INT | S1: Status de Interempresa | T1: OC-INT | U1: Status de Interempresa
B2: 2 | C2: LÁMPARA DE HENDIDURA | D2: 3 | E2: PZ | F2: CARL ZEISS | G2: SL 220 | H2: SL 220-R | I2: Carl Zeiss | J2: Manprec | K2: 794837.67 | L2: USD | M2: MPC | N2: MPC04549 | O2: FALSE | P2: estarian entregando el 14 y 15 de julio | Q2: ENVIADA | R2: MPC28582 | S2: TRUE | U2: FALSE
B3: 3 | C3: LÁMPARA QUIRÚRGICA DOBLE DE LED | D3: 4 | E3: PZ | F3: RIMSA | G3: PENTA30E+30E | H3: PENTA30E+30E-R | I3: Rimsa | J3: Manprec | L3: EURO | M3: MPC | N3: Stock | O3: FALSE | Q3: EN ALMACEN 11 | R3: MPC28582 | S3: TRUE | U3: FALSE
C4: Panel de control de pared | D4: 4 | E4: PZ | F4: RIMSA | I4: Rimsa | J4: Manprec | L4: EURO | M4: MPC | N4: Stock | O4: FALSE | Q4: EN ALMACEN 11 | R4: MPC28582 | S4: TRUE | U4: FALSE
C5: UPS DE 4 HORAS | D5: 4 | E5: PZ | F5: POWER ALL | H5: KI+15-2000RM-CT | I5: Alternativa | J5: Manprec | K5: 473 | L5: USD | M5: Gamit | N5: GAM00051 | O5: FALSE | R5: GAM00161 | S5: TRUE | U5: FALSE
C6: BANCO DE BATERIAS | D6: 4 | E6: PZ | F6: POWER ALL | H6: PAGBKi+1-RM3-8A 9 | I6: Alternativa | J6: Manprec | K6: 695 | L6: USD | M6: Gamit | N6: GAM00051 | O6: FALSE | R6: GAM00161 | S6: TRUE | U6: FALSE
B7: 4 | C7: REFRIGERADOR VERTICAL PARA LABORATORIO 20 PIES CÚBICOS | D7: 9 | E7: PZ | F7: REFRIMED | G7: RVCCDV-20 | H7: RVCCDV-20-R | I7: Refrimed | J7: Manprec | K7: 66985 | L7: MXN | M7: MPC | N7: MPC04550 | O7: FALSE | Q7: ENVIADA | R7: MPC28582 | S7: TRUE | U7: FALSE
B8: 6 | C8: ESTUFA BACTERIOLÓGICA DE 75 CM CON DOBLE PUERTA | D8: 1 | E8: PZ | F8: JP SELECTA | G8: 2000264 | H8: 2000264-R | I8: Lab-med | J8: Manprec | K8: 2875 | L8: EURO | M8: CEO | N8: CEO00146 | O8: FALSE | P8: tomar lo de tikul | Q8: ENVIADA | R8: MPC28582 | S8: TRUE | U8: FALSE
A9: MAN13378 | B9: 9 | C9: CONGELADOR HORIZONTAL DE REFRIGERANTES PARA VACUNAS | D9: 1 | E9: PZ | F9: REFRIMED | G9: CH-5 | H9: CH-5-R | I9: Refrimed | J9: Manprec | K9: 14987 | L9: MXN | M9: MPC | N9: MPC04550 | O9: FALSE | Q9: ENVIADA | R9: MPC28582 | S9: TRUE | U9: FALSE
C10: regulador de voltaje | F10: KOBLENS | H10: B08LP7F79M-R | I10: AMAZON | J10: Manprec | K10: 343.96552 | L10: MXN | M10: MPC | N10: MPC04683 | O10: FALSE | R10: MPC28582 | S10: TRUE | U10: FALSE
B11: 11 | C11: REFRIGERADOR PARA VACUNAS | D11: 3 | E11: PZ | F11: REFRIMED | G11: RVASCV-17 | H11: RVASCV-17-R | I11: Refrimed | J11: Manprec | K11: 62890 | L11: MXN | M11: MPC | N11: MPC04550 | O11: FALSE | Q11: ENVIADA | R11: MPC28582 | S11: TRUE | U11: FALSE
B12: 16 | C12: MICROSCOPIO QUIRÚRGICO OFTALMOLÓGICO BÁSICO | D12: 1 | E12: PZ | F12: CARL ZEISS | G12: OPMI LUMERA I | H12: 01LUMERAI-R | I12: Carl Zeiss | J12: Manprec | K12: 3245984.5 | L12: MXN | M12: MPC | N12: MPC04549 | O12: FALSE | P12: estarian entregando el 14 y 15 de julio | Q12: - | R12: MPC28582 | S12: TRUE | U12: FALSE
C13: UPS DE 15 MIN | D13: 1 | E13: PZ | F13: POWER ALL | H13: KI+15-2000RM-CT | I13: Alternativa | J13: Manprec | K13: 473 | L13: USD | M13: Gamit | O13: FALSE | P13: revisar si se agrego en el pedido de entrega | R13: GAM00161 | S13: TRUE | U13: FALSE
O14: FALSE | Q14: - | S14: FALSE | U14: FALSE
O15: FALSE | Q15: - | S15: FALSE | U15: FALSE
O16: FALSE | Q16: - | S16: FALSE | U16: FALSE
O17: FALSE | Q17: - | S17: FALSE | U17: FALSE
O18: FALSE | Q18: - | S18: FALSE | U18: FALSE
O19: FALSE | Q19: - | S19: FALSE | U19: FALSE
O20: FALSE | Q20: - | S20: FALSE | U20: FALSE
O21: FALSE | Q21: - | S21: FALSE | U21: FALSE
O22: FALSE | Q22: - | S22: FALSE | U22: FALSE
O23: FALSE | Q23: - | S23: FALSE | U23: FALSE
O24: FALSE | Q24: - | S24: FALSE | U24: FALSE
O25: FALSE | Q25: - | S25: FALSE | U25: FALSE
... O35: FALSE | Q35: - | S35: FALSE | U35: FALSE

Sheet SEDENA T-359
A1: PEDIDO | B1: PARTIDA | C1: DESCRIPCIÓN | D1: CANTIDAD | E1: UDM | F1: MARCA | G1: MODELO | H1: CÓDIGO | I1: PROVEEDOR | J1: Empresa que vende | K1: COSTO | L1: MONEDA COSTO | M1: EMPRESA QUE COMPRA | N1: OC | O1: B2B | P1: NÚMERO DE SERIE / LOTE | Q1: ESTATUS | R1: OV-INT | S1: Status de Interempresa | T1: OC-INT | U1: Status de Interempresa
A2: MPC28729 | B2: 1 | C2: Radiovisiografo dental | D2: 1 | E2: PZ | F2: Carestream dental | G2: RVG 6200 | H2: 5319819 | I2: Carestream dental | J2: MPC | K2: 2300 | L2: USD | M2: Manprec | N2: MAN01061 | O2: FALSE | P2: OEYW002 | Q2: EN ALMACEN 11 | R2: MAN13470 | S2: TRUE | T2: MPC04955 | U2: TRUE
C3: Base móvil para CS 2200 | D3: 1 | E3: PZ | F3: Carestream dental | H3: 5154281 | I3: Carestream dental | J3: MPC | K3: 1065 | L3: USD | M3: Manprec | N3: MAN01061 | O3: FALSE | Q3: ENVIADA | R3: MAN13470 | S3: TRUE | T3: MPC04955 | U3: TRUE
C4: RVG 6200 Radiovisógrafo Tamaño 2 + Licencia CSI8 10 activación | D4: 1 | E4: PZ | F4: Carestream dental | H4: 5310727 | I4: Carestream dental | J4: MPC | K4: 2704 | L4: USD | M4: Manprec | N4: MAN01061 | O4: FALSE | P4: 0AJB0136 | Q4: EN ALMACEN 11 | R4: MAN13470 | S4: TRUE | T4: MPC04955 | U4: TRUE
C5: Mandil Emplomado Para Rayos X Con Cinta Marca Shielding | D5: 1 | E5: PZ | G5: Nafarrate | H5: JDS536 | I5: NAFARRATE | J5: MPC | K5: 2931.6 | L5: MXN | M5: ITH | N5: ITH00206 | O5: FALSE | P5: 2024.10.31.258 | Q5: EN ALMACEN 11 | R5: ITH00967 | S5: TRUE | T5: MPC04744 | U5: TRUE
C6: Laptop gamer | D6: 1 | E6: PZ | G6: DELL | H6: 210-BQPQ | I6: DELL | J6: MPC | K6: 1980.97 | L6: USD | M6: MPC | N6: MPC04702 | O6: FALSE | Q6: EN ALMACEN 11 | R6: N/A | S6: TRUE | T6: N/A | U6: TRUE
C7: Licencia de windows 11 pro | D7: 1 | E7: PZ | H7: 43231513 | J7: MPC | K7: 2300 | L7: MXN | M7: MPC | N7: MPC04739 | O7: FALSE | Q7: EN ALMACEN 11 | R7: N/A | S7: TRUE | T7: N/A | U7: TRUE
C8: IMPRESORA MONOCROMATICA AGFA DRYSTAR AXYS | D8: 1 | E8: PZ | G8: AGFA | H8: 5302 | I8: CHEYSER | J8: MPC | K8: 51300 | L8: MXN | M8: MPC | N8: MPC04691 | O8: FALSE | P8: 760957 | Q8: EN ALMACEN 11 | R8: N/A | S8: TRUE | T8: N/A | U8: TRUE
C9: Pelicula AFGA DT500 | D9: 100 | E9: PZ | H9: ERRU6 | I9: CHEYSER | J9: MPC | K9: =2500/100 -> 25 | L9: MXN | M9: MPC | N9: MPC04746 | O9: FALSE | P9: 82010028 | Q9: EN ALMACEN 11 | R9: N/A | S9: TRUE | T9: N/A | U9: TRUE
C10: Dell Mochila Ecologica Profesional para Laptop 17" CP5723 EcoLoop Negra | D10: 1 | E10: pz | H10: B09V1W7VS2 | I10: AMAZON | J10: MPC | K10: 721.55 | L10: MXN | M10: MPC | N10: MPC04907 | O10: FALSE | Q10: EN ALMACEN 11 | R10: N/A | S10: FALSE | U10: FALSE
B11: 2 | C11: Lámpara ALFA-FLEX | D11: 3 | E11: PZ | G11: Rimsa | H11: ALFA-FLEX | I11: Rimsa | J11: MPC | K11: 230 | L11: EURO | M11: MPC | N11: MPC04695 | O11: FALSE | P11: 007524 007525 007521 | Q11: EN ALMACEN 11 | R11: N/A | S11: TRUE | T11: N/A | U11: TRUE
C12: RL Alfa | Base con ruedas para ALFA-FLEX | D12: 3 | E12: PZ | G12: Rimsa | H12: RLALFA | I12: Rimsa | J12: MPC | K12: 84 | L12: EURO | M12: MPC | N12: MPC04695 | O12: FALSE | P12: S/N | Q12: EN ALMACEN 11 | R12: N/A | S12: TRUE | T12: N/A | U12: TRUE
V18: Radiovisiografo dental | W18: OEYW002
V19: RVG 6200 Radiovisógrafo Tamaño 2 + Licencia CSI8 10 activación | W19: 0AJB0136
V20: Mandil Emplomado Para Rayos X Con Cinta Marca Shielding | W20: 2024.10.31.258
V21: IMPRESORA MONOCROMATICA AGFA DRYSTAR AXYS | W21: 760957
V22: Pelicula AFGA DT500 | W22: 82010028
V23: Lámpara ALFA-FLEX | W23: 007524 007525
V24: RL Alfa | Base con ruedas para ALFA-FLEX | W24: S/N

Sheet Star Medica Queretaro
A1: PEDIDO | B1: PARTIDA | C1: DESCRIPCIÓN | D1: CANTIDAD | E1: UDM | F1: MARCA | G1: MODELO | H1: CÓDIGO | I1: PROVEEDOR | J1: Empresa que vende | K1: COSTO | L1: MONEDA COSTO | M1: EMPRESA QUE COMPRA | N1: OC | O1: B2B | P1: OBSERVACIONES | Q1: ESTATUS | R1: OV-INT | S1: Status de Interempresa | T1: OC-INT | U1: Status de Interempresa
A2: MPC27997 | B2: 1 | C2: Avalon FM30 Fetal Monitor | D2: 1 | E2: PZ | H2: M2703A.2 | I2: PHILIPS | J2: MPC | K2: 4485.76 | L2: USD | M2: Manprec | N2: MAN01056 | O2: FALSE | Q2: EN ALMACEN 11 | R2: MAN13479 | S2: TRUE | T2: MPC04899 | U2: TRUE
C3: Avalon US Transducer | D3: 1 | E3: PZ | H3: 867246 | I3: PHILIPS | J3: MPC | K3: 553.2 | L3: USD | M3: Manprec | N3: MAN01012 | O3: TRUE | Q3: EN ALMACEN 11 | R3: MAN13479 | S3: TRUE | T3: MPC04899 | U3: TRUE
C4: Avalon TOCO MP Transducer | D4: 1 | E4: PZ | H4: 867248 | I4: PHILIPS | J4: MPC | K4: 601.8 | L4: USD | M4: Manprec | N4: MAN01012 | O4: TRUE | Q4: EN ALMACEN 11 | R4: MAN13479 | S4: TRUE | T4: MPC04899 | U4: TRUE
C5: Remote Event Marker | D5: 1 | E5: PZ | H5: 989803143411 | I5: PHILIPS | J5: MPC | K5: 114 | L5: USD | M5: Manprec | N5: Stock | O5: FALSE | Q5: EN ALMACEN 11 | R5: MAN13479 | S5: TRUE | T5: MPC04899 | U5: TRUE
C6: Reusable Abdominal Belt- 60mm Wd,1.3M Lg | D6: 2 | E6: PZ | H6: CINFM | I6: HOSPIINNOVA | J6: MPC | K6: 136.5 | L6: MXN | M6: Manprec | N6: Stock | O6: FALSE | Q6: EN ALMACEN 11 | R6: MAN13479 | S6: TRUE | T6: MPC04899 | U6: TRUE
C7: R01 GCX Rollstand: FM20/30 | D7: 1 | E7: PZ | H7: M2740A_R01 | I7: PHILIPS | J7: MPC | K7: 407.4 | L7: USD | M7: MPC | N7: Stock | O7: FALSE | Q7: EN ALMACEN 11 | R7: N/A | S7: TRUE | T7: N/A | U7: TRUE
C8: Fetal Monitoring Recording Paper | D8: 1 | E8: CJ/40 | H8: M1910A | I8: PHILIPS | J8: MPC | K8: 120 | L8: USD | M8: Manprec | N8: Stock | O8: FALSE | Q8: EN ALMACEN 11 | R8: MAN13479 | S8: FALSE | T8: MPC04899 | U8: TRUE
O9: FALSE | Q9: - | S9: FALSE | U9: FALSE
O10: FALSE | Q10: - | S10: FALSE | U10: FALSE
O11: FALSE | Q11: - | S11: FALSE | U11: FALSE
O12: FALSE | Q12: - | S12: FALSE | U12: FALSE
O13: FALSE | Q13: - | S13: FALSE | U13: FALSE
O14: FALSE | Q14: - | S14: FALSE | U14: FALSE
O15: FALSE | Q15: - | S15: FALSE | U15: FALSE
O16: FALSE | Q16: - | S16: FALSE | U16: FALSE

Sheet GESTUM
A1: PEDIDO | B1: PARTIDA | C1: DESCRIPCIÓN | D1: CANTIDAD | E1: UDM | F1: MARCA | G1: MODELO | H1: CÓDIGO | I1: PROVEEDOR | J1: Empresa que vende | K1: COSTO | L1: MONEDA COSTO | M1: EMPRESA QUE COMPRA | N1: OC | O1: B2B | P1: OBSERVACIONES | Q1: ESTATUS | R1: OV-INT | S1: Status de Interempresa | T1: OC-INT | U1: Status de Interempresa
A2: MAN12880 | B2: 1 | C2: Avalon FM30 Fetal Monitor | D2: 2 | E2: PZ | H2: M2703A.2 | I2: PHILIPS | J2: Manprec | K2: 4485.76 | L2: USD | M2: Manprec | N2: MAN01056 | O2: FALSE | P2: CDD 11 Sept | Q2: EN ALMACEN 11 | R2: N/A | S2: TRUE | T2: N/A | U2: TRUE
C3: Avalon US Transducer | D3: 2 | E3: PZ | H3: 867246 | I3: PHILIPS | J3: Manprec | K3: 553.2 | L3: USD | M3: Manprec | N3: MAN01012 | O3: TRUE | P3: CDD 29 Julio | Q3: EN ALMACEN 11 | R3: N/A | S3: TRUE | T3: N/A | U3: TRUE
C4: Avalon TOCO MP Transducer | D4: 2 | E4: PZ | H4: 867248 | I4: PHILIPS | J4: Manprec | K4: 601.8 | L4: USD | M4: Manprec | N4: MAN01012 | O4: TRUE | P4: CDD 29 Julio | Q4: EN ALMACEN 11 | R4: N/A | S4: TRUE | T4: N/A | U4: TRUE
C5: Remote Event Marker | D5: 2 | E5: PZ | H5: 989803143411 | I5: PHILIPS | J5: Manprec | K5: 114 | L5: MXN | M5: Manprec | N5: Stock | O5: TRUE | Q5: EN ALMACEN 11 | R5: N/A | S5: TRUE | T5: N/A | U5: TRUE
C6: Reusable Abdominal Belt- 60mm Wd,1.3M Lg | D6: 4 | E6: PZ | H6: CINFM | I6: HOSPIINNOVA | J6: Manprec | K6: 136.5 | L6: USD | M6: Manprec | N6: Stock | O6: FALSE | Q6: EN ALMACEN 11 | R6: N/A | S6: TRUE | T6: N/A | U6: TRUE
C7: R01 GCX Rollstand: FM20/30 | D7: 2 | E7: PZ | H7: M2740A_R01 | I7: PHILIPS | J7: Manprec | K7: 407.4 | L7: USD | M7: MPC | N7: Stock | O7: FALSE | P7: falta intercomp | Q7: EN ALMACEN 11 | R7: MPC29742 | S7: FALSE | U7: FALSE
C8: Fetal Monitoring Recording Paper | D8: 2 | E8: CJ/40 | H8: M1910A | I8: PHILIPS | J8: Manprec | K8: 120 | L8: USD | M8: Manprec | N8: Stock | O8: TRUE | Q8: EN ALMACEN 11 | R8: N/A | S8: TRUE | T8: N/A | U8: TRUE

Sheet Sedena T400
A1: PEDIDO | B1: PARTIDA | C1: DESCRIPCIÓN | D1: CANTIDAD | E1: UDM | F1: MARCA | G1: MODELO | H1: CÓDIGO | I1: PROVEEDOR | J1: Empresa que vende | K1: COSTO | L1: MONEDA COSTO | M1: EMPRESA QUE COMPRA | N1: OC | O1: B2B | P1: OBSERVACIONES | Q1: ESTATUS | R1: OV-INT | S1: Status de Interempresa | T1: OC-INT | U1: Status de Interempresa
A2: MPC27022 | B2: 1 | C2: Radiovisiografo dental | D2: 2 | E2: PZ | F2: Carestream dental | G2: RVG 6200 | H2: 5319819 | I2: Carestream dental | J2: MPC | K2: 2300 | L2: USD | M2: Manprec | N2: MAN01076 | O2: FALSE | Q2: EN ALMACEN 11 | R2: MAN13722 | S2: TRUE | T2: MAN13722 | U2: TRUE
C3: Base móvil para CS 2200 | D3: 2 | E3: PZ | F3: Carestream dental | H3: 5154281 | I3: Carestream dental | J3: MPC | K3: 1065 | L3: USD | M3: Manprec | N3: MAN01076 | O3: FALSE | P3: revisar que procede con la base | Q3: EN ALMACEN 11 | R3: MAN13722 | S3: TRUE | T3: MAN13722 | U3: TRUE
C4: RVG 6200 Radiovisógrafo Tamaño 2 + Licencia CSI8 10 activación | D4: 2 | E4: PZ | F4: Carestream dental | H4: 5310727 | I4: Carestream dental | J4: MPC | K4: 2704 | L4: USD | M4: Manprec | N4: MAN01076 | O4: FALSE | Q4: EN ALMACEN 11 | R4: MAN13722 | S4: TRUE | T4: MAN13722 | U4: TRUE
C5: Mandil Emplomado Para Rayos X Con Cinta Marca Shielding | D5: 2 | E5: PZ | H5: JDS536 | I5: NAFARRATE | J5: MPC | K5: 2931.6 | L5: MXN | M5: ITH | N5: ITH00211 | O5: FALSE | Q5: EN ALMACEN 11 | R5: ITH00983 | S5: TRUE | T5: MPC05181 | U5: TRUE
C6: Protector de tiroides | D6: 2 | E6: PZ | H6: JD611NSL | I6: NAFARRATE | J6: MPC | L6: MXN | M6: MPC | N6: Stock | O6: FALSE | Q6: EN ALMACEN 11 | R6: N/A | S6: TRUE | T6: N/A | U6: TRUE
C7: Laptop gamer | D7: 2 | E7: PZ | H7: 210-BQPQ | I7: DELL | J7: MPC | K7: 1679.99 | L7: USD | M7: MPC | N7: MPC04992 | O7: FALSE | P7: ya se compraron en el portal | Q7: EN ALMACEN 11 | R7: N/A | S7: TRUE | T7: N/A | U7: TRUE
C8: Licencia de windows 11 pro | D8: 2 | E8: PZ | H8: 43231513 | I8: GERARDO TONATIHU | J8: MPC | K8: 2300 | L8: MXN | M8: MPC | N8: MPC04861 | O8: FALSE | Q8: EN ALMACEN 11 | R8: N/A | S8: TRUE | T8: N/A | U8: TRUE
C9: IMPRESORA MONOCROMATICA AGFA DRYSTAR AXYS | D9: 2 | E9: PZ | H9: 5302 | I9: CHEYSER | J9: MPC | K9: 51300 | L9: MXN | M9: MPC | N9: MPC04838 | O9: FALSE | P9: Dar entrada virtual | Q9: EN ALMACEN 11 | R9: N/A | S9: TRUE | T9: N/A | U9: TRUE
C10: Pelicula AFGA DT500 | D10: 200 | E10: PZ | H10: ERRU6 | I10: CHEYSER | J10: MPC | K10: 2500 | L10: MXN | M10: MPC | N10: MPC05005 | O10: FALSE | Q10: EN ALMACEN 11 | R10: N/A | S10: TRUE | T10: N/A | U10: TRUE
C11: Dell Mochila Ecologica Profesional para Laptop 17" CP5723 EcoLoop Negra | D11: 2 | E11: pz | H11: B09V1W7VS2 | I11: AMAZON | J11: MPC | K11: 721.55 | L11: MXN | M11: MPC | N11: MPC04907 | O11: FALSE | Q11: EN ALMACEN 11 | R11: N/A | S11: TRUE | T11: N/A | U11: TRUE

Sheet SSA HIDALGO N24
A1: PEDIDO | B1: PARTIDA | C1: DESCRIPCIÓN | D1: CANTIDAD | E1: UDM | F1: MARCA | G1: MODELO | H1: CÓDIGO | I1: PROVEEDOR | J1: Empresa que vende | K1: COSTO | L1: MONEDA COSTO | M1: EMPRESA QUE COMPRA | N1: OC | O1: B2B | P1: OBSERVACIONES | Q1: ESTATUS | R1: OV-INT | S1: Status de Interempresa | T1: OC-INT | U1: Status de Interempresa
A2: MPC29006 | B2: 11 | C2: EQUIPO DE RAYOS X CON FLUOROSCOPIA MÓVIL DIGITAL TIPO ARCO EN "C" | D2: 2 | E2: PZ | F2: PHILIPS | G2: ZENITION 70 | H2: NMCA425 | I2: PHILIPS | J2: MPC | K2: 129000 | L2: USD | M2: Manprec | N2: MAN00941 | O2: FALSE | Q2: PENDIENTE | R2: MAN13553 | S2: TRUE | T2: MPC04875 | U2: FALSE
B3: 2.2 | C3: Cubierta esteriles para arco | D3: 100 | E3: PZ | F3: HOSPIINNOVA | H3: DYNJE4500 | I3: HOSPIINNOVA | J3: MPC | K3: =8880/20 -> 444 | L3: MXN | M3: Manprec | N3: MAN01078 | O3: FALSE | Q3: PARCIAL | R3: MAN13553 | S3: TRUE | T3: MPC04875 | U3: FALSE
B4: 2.3 | C4: Funda cubierta protectora de equipo | D4: 2 | E4: PZ | F4: AMAZON | H4: B0C22ST7TX | I4: AMAZON | J4: MPC | K4: 392 | L4: MXN | M4: MPC | N4: MPC04916 | O4: FALSE | Q4: EN ALMACEN 11 | R4: N/A | S4: TRUE | T4: N/A | U4: TRUE
B5: 2.4 | C5: Mandil emplomado | D5: 4 | E5: PZ | F5: NAFARRATE | H5: JDS536 | I5: NAFARRATE | J5: MPC | K5: 2931.6 | L5: MXN | M5: ITH | N5: ITH00210 | O5: FALSE | Q5: EN ALMACEN 11 | R5: ITH00971 | S5: TRUE | T5: MPC05014 | U5: TRUE
B6: 2.5 | C6: Lentes para proteccion de RX | D6: 4 | E6: PZ | F6: NAFARRATE | H6: JD53 | I6: NAFARRATE | J6: MPC | K6: 2981 | L6: MXN | M6: ITH | N6: ITH00210 | O6: FALSE | Q6: EN ALMACEN 11 | R6: ITH00971 | S6: TRUE | T6: MPC05014 | U6: TRUE
B7: 2.6 | C7: Guantes de plomo | D7: 4 | E7: PZ | F7: NAFARRATE | H7: JD100V-DKB | I7: NAFARRATE | J7: MPC | K7: 3731.6 | L7: MXN | M7: ITH | N7: ITH00210 | O7: FALSE | Q7: EN ALMACEN 11 | R7: ITH00971 | S7: TRUE | T7: MPC05014 | U7: TRUE
B8: 2.7 | C8: Acondicionador de lina a 120V monofasico de por lo menos 5 KVA | D8: 2 | E8: PZ | F8: MERCADO LIBRE | H8: LAN-15 | I8: MERCADO LIBRE | J8: MPC | K8: 19885 | L8: MXN | M8: MPC | O8: FALSE | Q8: EN ALMACEN 11 | R8: N/A | S8: TRUE | T8: N/A | U8: TRUE
A9: MPC29006 | B9: 15 | C9: ULTRASONOGRAFO (GINECO-OBSTÉTRICO SEGUNDO NIVEL) | D9: 15 | E9: PZ | F9: PHILIPS | G9: AFFINITI 50 | H9: NUSM253 | I9: PHILIPS | J9: MPC | K9: 38376 | L9: USD | M9: MPC | N9: MPC04767 (7) MPC04776 (8) | O9: FALSE | Q9: PENDIENTE | R9: N/A | S9: TRUE | T9: N/A | U9: TRUE
B10: 2.8 | C10: UPS con respaldo de 10 min | D10: 15 | E10: PZ | F10: POWER ALL | H10: KR+19-3000-01UN | I10: ALTERNATIVA | J10: MPC | K10: 749 | L10: USD | M10: Gamit | N10: GAM00053 | O10: FALSE | Q10: EN ALMACEN 11 | R10: GAM00164 | S10: TRUE | T10: MPC04873 | U10: FALSE
B11: 2.9 | C11: Impresora a color | D11: 15 | E11: PZ | F11: HP | H11: 3D4L3A | I11: AMAZON | J11: MPC | K11: 2154.31 | L11: MXN | M11: MPC | N11: MPC04908 | O11: FALSE | Q11: EN ALMACEN 11 | R11: N/A | S11: TRUE | T11: N/A | U11: TRUE
B12: 3.1 | C12: Galon de gel | D12: 15 | E12: PZ | F12: PRONAMAC | H12: ALT 039 | I12: PRONAMAC | J12: MPC | K12: 450.83 | L12: MXN | M12: MPC | N12: MPC04832 | O12: FALSE | Q12: PENDIENTE | R12: N/A | S12: TRUE | T12: N/A | U12: TRUE
B13: 3.1 | C13: Gel de 250 ml | D13: 15 | E13: PZ | F13: PRONAMAC | H13: ALT 040 | I13: PRONAMAC | J13: MPC | K13: 60.87 | L13: MXN | M13: MPC | N13: MPC04832 | O13: FALSE | Q13: PENDIENTE | R13: N/A | S13: TRUE | T13: N/A | U13: TRUE
B14: 3.2 | C14: DVD'S | D14: 15 | E14: C/100 | F14: AMAZON | H14: B00O0IDJT2 | I14: AMAZON | J14: MPC | K14: 604.49 | L14: MXN | M14: MPC | N14: MPC04908 | O14: FALSE | Q14: EN ALMACEN 11 | R14: N/A | S14: TRUE | T14: N/A | U14: TRUE
B15: 3.2 | C15: CD'S | D15: 15 | E15: C/100 | F15: AMAZON | H15: CD-R 100 | I15: AMAZON | J15: MPC | K15: 491.86 | L15: MXN | M15: MPC | N15: MPC04908 | O15: FALSE | Q15: EN ALMACEN 11 | R15: N/A | S15: TRUE | T15: N/A | U15: TRUE
B16: 3.3 | C16: Papel para impresora | D16: 75 | E16: PZ | F16: AKUASUL | H16: USP-110HG | I16: AKUAZUL | J16: MPC | K16: =3200/10 -> 320 | L16: MXN | M16: Manprec | N16: MAN01081 | O16: FALSE | Q16: EN ALMACEN 11 | R16: MAN13553 | S16: TRUE | T16: MPC04875 | U16: FALSE
B17: 3.4 | C17: Fundas desechables para trasductor | D17: =200*15 -> 3000 | E17: PZ | F17: PRONAMAC | H17: DEN054 | I17: PRONAMAC | J17: MPC | K17: 2.236111 | L17: MXN | M17: MPC | N17: MPC04832 | O17: FALSE | Q17: PENDIENTE | R17: N/A | S17: TRUE | T17: N/A | U17: TRUE
F29: STOCK
F30: 20 | G30: =E30-F30 -> 55
F32: HP Impresora Smart Tank 210, Tinta Continua, Color, Wi-Fi,USB, Bluetooth, Dúplex (Doble Cara) Manual, Impresión Smart App, hasta 2 años de Garantía* (3D4L3A) | G32: https://www.amazon.com.mx/HP-Impresora-Continua-Impresi%C3%B3n-3D4L3A/dp/B0BXBGM21F/ref=sr_1_1_sspa?__mk_es_MX=%C3%85M%C3%85%C5%BD%C3%95%C3%91&crid=1M5FRWWS5QWB6&dib=eyJ2IjoiMSJ9.vs81EFolhLylsB63agz5CwQy6dx4KhpRr0RN82xKkhRqLHIFA1a5CcberafyJesR3odjREJu4nJRopn-T-w1OEihaDv0BHQ3SfktPJ3E66uAy1kZC0qlIjnWUKsgnG1BtLuuT9qOex-z7bIguHkPIMsVzzscpRkSSBFCF7uusQT3jQ2mwcGzw6bwlavZUCAiYXn5QSXq108o-I6sCDOvkT9DfVxATZeyjrk6Y6bw8zRGca3E82IUxDdMa3hV7wZWwrmt-CwhRAPwJDnIvGYcjbnKdjWg7NmYzGFWVptDhy4.EGLu0hu6rOG5ybQoEfXjTkRbusPBA1jgHw0ImTxGHkA&dib_tag=se&keywords=impresora+EPSON&qid=1783014808&sprefix=impresora+epson%2Caps%2C165&sr=8-1-spons&ufe=app_do%3Aamzn1.fos.e9c905c0-296e-4852-9ea7-c9f4c88300d3&sp_csd=d2lkZ2V0TmFtZT1zcF9hdGY&psc=1&qty=15&sbo=RZvfv%2F%2FHxDF%2BO5021pAnSA%3D%3D
F33: Funda cubierta protectora de equipo | G33: https://www.amazon.com.mx/gp/aw/d/B07TJY1S9K/?_encoding=UTF8&pd_rd_plhdr=t&hsa_cr_id=0&qid=1783015153&sr=1-2-9e67e56a-6f64-441f-a281-df67fc737124&i=aps&aref=1C6kPl15cp&ref_=sbx__sbtcd_asin_1_img&pd_rd_w=TKeFd&content-id=amzn1.sym.cc71ba64-01af-4d4f-bd2b-d826d6fb8aa3%3Aamzn1.sym.cc71ba64-01af-4d4f-bd2b-d826d6fb8aa3&pf_rd_p=cc71ba64-01af-4d4f-bd2b-d826d6fb8aa3&pf_rd_r=0DM5V7AHRNDV2P9WKGW2&pd_rd_wg=ymQ8U&pd_rd_r=54ab2633-731b-44ad-8b31-9c232699035d&th=1
F35: Acondicionador de lina a 120V monofasico de por lo menos 5 KVA | G35: https://articulo.mercadolibre.com.mx/MLM-5161175630-regulador-electronico-de-voltaje-vogar-lan-15-5-kva-120v-1f-_JM?searchVariation=199957060941#polycard_client=search-desktop&be_origin=backend&searchVariation=199957060941&search_layout=grid&position=4&type=item&tracking_id=8909f169-1004-4604-bf84-b508564722c9&sid=search
F39: DVD´S | G39: https://www.pcel.com/Verbatim-97493-Paquete-de-50-DVD-R-Verbatim-de-4-7-GB-16x-188028
F40: CD´S | G40: https://www.pcel.com/almacenamiento/blu-rays-dvds-y-cds/Verbatim-94691-Paquete-de-50-CD-R-Verbatim-de-700-MB-52x-59256
F45: 124 | G45: =E45-F45 -> 2876 | H45: 144 | I45: =G45/H45 -> 19.972222
H46: =H45*20 -> 2880
H48: =322/144 -> 2.2361111

Sheet SEDENA T-395
A1: PEDIDO | B1: PARTIDA | C1: DESCRIPCIÓN | D1: CANTIDAD | E1: UDM | F1: MARCA | G1: MODELO | H1: CÓDIGO | I1: PROVEEDOR | J1: Empresa que vende | K1: COSTO | L1: MONEDA COSTO | M1: EMPRESA QUE COMPRA | N1: OC | O1: B2B | P1: OBSERVACIONES | Q1: ESTATUS | R1: OV-INT | S1: Status de Interempresa | T1: OC-INT | U1: Status de Interempresa
A2: MPC27011 | B2: 25 | C2: EQUIPO DE BIOIMPEDANCIA CON ESTADÍMETRO. | D2: 2 | F2: SECA | G2: mpc | H2: Seca 554 | I2: SECA | J2: MPC | K2: 226653 | L2: MXN | M2: Manprec | N2: MAN01079 | O2: FALSE | Q2: EN ALMACEN 11 | R2: MAN13597 | S2: TRUE | T2: MPC04913 | U2: TRUE
C3: TOALLAS ELECTROCONDUCTIVAS | D3: 2 | H3: B0056BZ99U | I3: AMAZON | J3: MPC | K3: 89.465 | L3: MXN | M3: MPC | N3: MPC05134 | O3: FALSE | Q3: EN ALMACEN 11 | R3: N/A | S3: TRUE | T3: N/A | U3: TRUE
C4: MALETA DE TRANSPORTE | D4: 2 | H4: B0GSVS8XC3 | I4: AMAZON | J4: MPC | K4: 646.54 | L4: MXN | M4: MPC | N4: MPC05122 | O4: FALSE | Q4: EN ALMACEN 11 | R4: N/A | S4: TRUE | T4: N/A | U4: TRUE
C5: LAPTOP | D5: 2 | H5: B0CWH4YRY3 | I5: AMAZON | J5: MPC | K5: 6464.66 | L5: MXN | M5: MPC | N5: MPC04908 | O5: FALSE | Q5: EN ALMACEN 11 | R5: N/A | S5: TRUE | T5: N/A | U5: TRUE
A6: MPC27011 | B6: 35 | C6: ESTUFA BACTERIOLÓGICA. | D6: 1 | F6: JP SELECTA | G6: INCUBAT (2000261) | H6: 2000261 | I6: LAB-MED | J6: MPC | K6: 1815 | L6: EURO | M6: CEO | N6: CEO00151 | O6: FALSE | Q6: EN ALMACEN 11 | R6: CEO00289 | S6: TRUE | T6: MPC04912 | U6: TRUE

Sheet SEDENA T-399
A1: PEDIDO | B1: PARTIDA | C1: DESCRIPCIÓN | D1: CANTIDAD | E1: UDM | F1: MARCA | G1: MODELO | H1: CÓDIGO | I1: PROVEEDOR | J1: Empresa que vende | K1: COSTO | L1: MONEDA COSTO | M1: EMPRESA QUE COMPRA | N1: OC | O1: B2B | P1: OBSERVACIONES | Q1: ESTATUS | R1: OV-INT | S1: Status de Interempresa | T1: OC-INT | U1: Status de Interempresa | V1: FACTURA | W1: PEDIMENTO
A2: MPC27016 | B2: 31 | C2: PROCESADOR DE TEJIDOS SEMIAUTOMÁTICO DE SOBRE MESA. | D2: 1 | E2: PZ | F2: HISTO-LINE | G2: STP250-DUO | H2: STP250-DUO | I2: HISTO-LINE | J2: MPC | K2: 12216.4 | L2: EURO | M2: CEO | N2: CEO00152 | O2: FALSE | Q2: ENVIADA | R2: CEO00287 | S2: TRUE | T2: MPC04868 | U2: TRUE
C3: UPS DE 1 KVA CON RESPALDO DE 15 MIN | D3: 1 | E3: PZ | F3: Power ALL | H3: PA KR+19 -2000 | I3: ALTERNATIVA | J3: MPC | K3: 576 | L3: USD | M3: Gamit | N3: GAM00053 | O3: FALSE | Q3: EN ALMACEN 11 | R3: GAM00165 | S3: TRUE | T3: MPC04869 | U3: TRUE

Sheet SEDENA T-386
A1: PEDIDO | B1: PARTIDA | C1: DESCRIPCIÓN | D1: CANTIDAD | E1: UDM | F1: MARCA | G1: MODELO | H1: CÓDIGO | I1: PROVEEDOR | J1: Empresa que vende | K1: COSTO | L1: MONEDA COSTO | M1: EMPRESA QUE COMPRA | N1: OC | O1: B2B | P1: OBSERVACIONES | Q1: ESTATUS | R1: OV-INT | S1: Status de Interempresa | T1: OC-INT | U1: Status de Interempresa
A2: CEO00285 | B2: 14 | C2: CENTRIFUGA CLÍNICA DE MESA PARA 16-20 TUBOS. | D2: 2 | E2: PZ | F2: OHAUS | G2: 83042046 | H2: 83042046 | I2: LAB-TECH | J2: CEO | K2: 6728.41 | L2: USD | M2: CEO | N2: CEO00155 | O2: FALSE | Q2: ENVIADA | R2: N/A | S2: TRUE | T2: N/A | U2: TRUE
C3: Rotor Oscilante 4X145ML ID | D3: 2 | E3: PZ | H3: 30314822 | J3: CEO | K3: 1095 | L3: USD | M3: CEO | N3: CEO00155 | O3: FALSE | Q3: ENVIADA | R3: N/A | S3: TRUE | T3: N/A | U3: TRUE
C4: Gradilla, 7 × 15 ml, D17 mm RB/Vac, paquete de 2 | D4: 4 | E4: P/2 | H4: 30314852 | J4: CEO | K4: =499.32/2 -> 249.66 | L4: USD | M4: CEO | N4: CEO00155 | O4: FALSE | Q4: ENVIADA | R4: N/A | S4: TRUE | T4: N/A | U4: TRUE
C5: Gradilla, 5 × 4-10 ml, D16 mm Sar, paquete de 2 | D5: 4 | E5: P/2 | H5: 30314858 | J5: CEO | K5: =499.32/2 -> 249.66 | L5: USD | M5: CEO | N5: CEO00155 | O5: FALSE | Q5: ENVIADA | R5: N/A | S5: TRUE | T5: N/A | U5: TRUE
C6: Gradilla, 7×5-7 ml, D13 mm Vac, paquete de 2 | D6: 4 | E6: P/2 | H6: 30314857 | J6: CEO | K6: =499.32/2 -> 249.66 | L6: USD | M6: CEO | N6: CEO00155 | O6: FALSE | Q6: ENVIADA | R6: N/A | S6: TRUE | T6: N/A | U6: TRUE
C7: Gradilla, 10 × 1.5/2.0 ml D11 mm, paquete de 2 | D7: 4 | E7: P/2 | H7: 30314854 | J7: CEO | K7: =532.102/2 -> 266.051 | L7: USD | M7: CEO | N7: CEO00155 | O7: FALSE | Q7: ENVIADA | R7: N/A | S7: TRUE | T7: N/A | U7: TRUE
A8: CEO00285 | B8: 26 | C8: EQUIPO DE RAYOS X PORTÁTIL. | D8: 1 | E8: PZ | F8: ITALRAY | G8: AMR+IR313-B | H8: AMR+IR313-B | I8: ITALRAY | J8: CEO | K8: 58000 | L8: EURO | M8: CEO | N8: CEO00157 | O8: FALSE | Q8: ENVIADA | R8: N/A | S8: TRUE | T8: N/A | U8: TRUE
C9: Mandil Emplomado Para Rayos X Con Cinta Marca Shielding | D9: 2 | H9: JDS536 | I9: NAFARRATE | J9: CEO | K9: 2931.6 | L9: MXN | M9: ITH | N9: ITH00211 | O9: FALSE | Q9: EN ALMACEN 11 | R9: ITH00976 | S9: FALSE | U9: FALSE
C10: Lente Para Proteccion De Rx | D10: 2 | H10: JD53 | I10: NAFARRATE | J10: CEO | K10: 2981 | L10: MXN | M10: ITH | N10: ITH00211 | O10: FALSE | Q10: EN ALMACEN 11 | R10: ITH00976 | S10: FALSE | U10: FALSE
C11: Protector De Tiroides Marca Shielding | D11: 2 | H11: JD611NSL | I11: NAFARRATE | J11: CEO | K11: 720.2 | L11: MXN | M11: ITH | N11: ITH00211 | O11: FALSE | Q11: EN ALMACEN 11 | R11: ITH00976 | S11: FALSE | U11: FALSE
A12: CEO00285 | B12: 35 | C12: LAVADORA ULTRASÓNICA PARA ODONTOLOGÍA. | D12: 1 | E12: PZ | F12: JP SELECTA | G12: 3000868 | H12: 3000868 | I12: LAB_MED | J12: CEO | K12: 2665 | L12: EURO | M12: CEO | N12: CEO00156 | O12: FALSE | Q12: ENVIADA | R12: N/A | S12: TRUE | T12: N/A | U12: TRUE
O13: FALSE | Q13: - | S13: FALSE | U13: FALSE
O14: FALSE | Q14: - | S14: FALSE | U14: FALSE
O15: FALSE | Q15: - | S15: FALSE | U15: FALSE
O16: FALSE | Q16: - | S16: FALSE | U16: FALSE
O17: FALSE | Q17: - | S17: FALSE | U17: FALSE
O18: FALSE | Q18: - | S18: FALSE | U18: FALSE
O19: FALSE | Q19: - | S19: FALSE | U19: FALSE
O20: FALSE | Q20: - | S20: FALSE | U20: FALSE
O21: FALSE | Q21: - | S21: FALSE | U21: FALSE
O22: FALSE | Q22: - | S22: FALSE | U22: FALSE
O23: FALSE | Q23: - | S23: FALSE | U23: FALSE
O24: FALSE | Q24: - | S24: FALSE | U24: FALSE
... O31: FALSE | Q31: - | S31: FALSE | U31: FALSE

Sheet TAPACHULA ARRENDAMIENTO
A1: PEDIDO | B1: PARTIDA | C1: DESCRIPCIÓN | D1: CANTIDAD | E1: UDM | F1: MARCA | G1: MODELO | H1: CÓDIGO | I1: CÓDIGO- ARRENDAMIENTO | J1: NS/LOTE | K1: PROVEEDOR | L1: Empresa que vende | M1: COSTO | N1: MONEDA COSTO | O1: EMPRESA QUE COMPRA | P1: COSTO INTEREMPRESA | Q1: OC | R1: B2B | S1: OBSERVACIONES | T1: ESTATUS | U1: OV-INT | V1: Status de Interempresa | W1: OC-INT | X1: OV - INT -ARREN | Y1: OC-INT-ARREN | Z1: Status de Interempresa
A2: MAN13588 | B2: 1 | C2: ULTRASONIDO PORTATIL 5500 | D2: 1 | E2: PZ | F2: PHILIPS | G2: 5500 | H2: NUSE401 | I2: NUSE401-R | K2: PHILIPS | L2: Manprec | M2: 50000 | N2: USD | O2: Manprec | P2: 957447 | Q2: MAN01090 | R2: FALSE | S2: DEMO, SE ENCUENTRA EN ALMACEN 11 CÓDIGO NUSE401-D | T2: EN ALMACEN 11 | U2: MAN13730 | V2: FALSE | Z2: FALSE
C3: ULTRASONIDO PORTATIL 5500 "EQUIPO DEMO DE MANPREC" | D3: 1 | E3: PZ | F3: PHILIPS | G3: 5500 | H3: NUSE401-D | I3: NUSE401-D | K3: PHILIPS | L3: Manprec | M3: 27900.4 | N3: USD | O3: Manprec | P3: 534263 | Q3: MAN00510 | R3: FALSE | U3: MAN13730 | V3: FALSE | Z3: FALSE
B4: 2 | C4: ULTRASONIDO AVANZADO EPIQ | D4: 1 | E4: PZ | F4: PHILIPS | G4: EPIQ ELITE G | H4: NUSY003 | I4: NUSY003-R | J4: USD25B0348 | K4: PHILIPS | L4: Manprec | M4: 78000 | N4: USD | O4: Manprec | P4: 1493617 | Q4: MAN01090 | R4: FALSE | S4: EN COTIZACIÓN CON PHILIPS | T4: PENDIENTE | U4: MAN13730 | V4: FALSE | Z4: FALSE
C5: UPS DE 5 MIN | D5: 1 | E5: PZ | F5: POWER ALL | H5: KR+19-3000-01UN | I5: KR+19-3000-01UN-R | J5: UI012642505906 | K5: ALTERNATIVA | L5: Manprec | M5: 749 | N5: USD | O5: Gamit | P5: 15408 | Q5: GAM00053 | R5: FALSE | S5: EN ALMACEN 11 | T5: EN ALMACEN 11 | U5: GAM00171 | V5: FALSE | Z5: FALSE
C6: IMPRESORA B/N Y COLOR | D6: 1 | E6: PZ | F6: HP | H6: 3D4L3A | I6: 3D4L3A-R | J6: TH6107W1PT | K6: AMAZON | L6: Manprec | M6: 2154.31 | N6: MXN | O6: MPC | P6: =M6 -> 2154.31 | R6: FALSE | S6: EN ESPERA DE COTIZACIÓN DE PHILIPS | T6: PENDIENTE | U6: MPC29508 | V6: FALSE | Z6: FALSE
B7: 3 | C7: BANDA DE ESFUERZO CARDIOVIT CS-200 EXCELLENCE | D7: 1 | E7: PZ | F7: SCHILLER | G7: CS-200 | H7: 0.035000 EE. UU. | I7: 0.035000 EE. UU.-R | J7: 35.01535 | K7: SCHILLER | L7: Manprec | M7: 18380 | N7: USD | O7: ITH | P7: 350000 | Q7: ITH00212 | R7: FALSE | S7: LLEGA EL VIERNES | T7: PENDIENTE | U7: ITH00985 | V7: FALSE | Z7: FALSE
C8: Mounting kit BP-200, BP-200 plus | D8: 1 | E8: PZ | F8: SCHILLER | H8: 2.210016 | I8: 2.210016-R | J8: S/L | K8: SCHILLER | L8: Manprec | M8: 444 | N8: USD | O8: ITH | P8: 843 | Q8: ITH00212 | R8: FALSE | S8: LLEGA EL VIERNES | T8: PENDIENTE | U8: ITH00985 | V8: FALSE | Z8: FALSE
C9: BP-200 Plus Presión arterial Lun | D9: 1 | E9: PZ | F9: SCHILLER | H9: 0.310000 | I9: 0.310000-R | J9: 310.04104 | K9: SCHILLER | L9: Manprec | M9: 3985 | N9: USD | O9: ITH | P9: 76309 | Q9: ITH00212 | R9: FALSE | S9: LLEGA EL VIERNES | T9: PENDIENTE | U9: ITH00985 | V9: FALSE | Z9: FALSE
C10: CAMINADORA | D10: 1 | E10: PZ | H10: TMX428 | I10: TMX428-R | J10: FVDC-11327 | K10: NAFARRATE | L10: Manprec | M10: 133316.2 | N10: MXN | O10: ITH | P10: 137473 | Q10: ITH00213 | R10: FALSE | S10: LLEGA EL VIERNES | T10: PENDIENTE | U10: ITH00985 | V10: FALSE | Z10: FALSE
C11: Digital connecting cable EMV AT-10, AT-60, CS-100, CS-200 | D11: 1 | E11: PZ | F11: SCHILLER | H11: 2.310056 | I11: 2.310056-R | K11: SCHILLER | L11: Manprec | M11: 40 | N11: USD | O11: ITH | P11: 766 | Q11: ITH00216 | R11: FALSE | S11: REALIAZR EL INTERCOM | T11: EN ALMACEN 11 | U11: ITH00985 | V11: FALSE | Z11: FALSE
C12: PAQUETE DE PAPEL | D12: 30 | E12: PZ | F12: SCHILLER | H12: 2.157050 | I12: N/A | K12: SCHILLER | L12: Manprec | M12: 25 | N12: USD | O12: ITH | Q12: ITH00212 | R12: FALSE | S12: LLEGA EL VIERNES | T12: PENDIENTE | U12: ITH00974 | V12: FALSE | Z12: FALSE
C13: ELECTRODOS DE ECG B/100 | D13: 1 | E13: B/100 | F13: CARDINAL | H13: 31050522 | I13: N/A | K13: HOSPIINNOVA | L13: Manprec | M13: =2464/10 -> 246.4 | N13: MXN | O13: Manprec | P13: $ - | R13: FALSE | S13: EN ALMACEN 11 | T13: EN ALMACEN 11 | U13: MAN13730 | V13: FALSE | Z13: FALSE
C14: UPS DE 1 KVA | D14: 1 | E14: PZ | F14: POWER ALL | H14: PA MG+15-2200-UN | I14: PA MG+15-2200-UN-R | J14: 251106030244 | K14: ALTERNATIVA | L14: Manprec | M14: 260.63 | N14: USD | O14: Gamit | P14: 5362 | Q14: Stock | R14: FALSE | S14: EN ALMACEN 11 | T14: EN ALMACEN 11 | U14: GAM00171 | V14: FALSE | Z14: FALSE
B15: 4 | C15: ELECTROCARDIOGRAFO MULTICANAL CON INTERPRETACION CARDIO VIT-102 G2 | D15: 5 | E15: PZ | F15: SCHILLER | G15: CARDIOVIT AT-102 G2 | H15: 0A.108000 | I15: 0A.108000-R | J15: 1080.020153 1080.020155 1080.020156 1080.020157 1080.020154 | K15: SCHILLER | L15: Manprec | M15: 3966 | N15: USD | O15: ITH | P15: 75945 | Q15: ITH00212 | R15: FALSE | S15: LLEGA EL VIERNES | T15: PENDIENTE | U15: ITH00985 | V15: FALSE | Z15: FALSE
C16: CARRO DE TRANSPORTE | D16: 5 | E16: PZ | F16: TPX | H16: RP050-6 | I16: RP050-6-R | J16: S/L | K16: TPX | L16: Manprec | M16: 115 | N16: USD | O16: MPC | P16: 4498.2 | Q16: Stock | R16: FALSE | S16: EN ALMACEN 11 | T16: EN ALMACEN 11 | U16: MPC29444 | V16: FALSE | Z16: FALSE
C17: PAQUETE DE PAPEL | D17: 50 | E17: PZ | F17: SCHILLER | H17: 2.157050 | I17: N/A | K17: SCHILLER | L17: Manprec | M17: 25 | N17: USD | O17: ITH | Q17: ITH00212 | R17: FALSE | S17: LLEGA EL VIERNES | T17: PENDIENTE | U17: ITH00974 | V17: FALSE | Z17: FALSE
B18: 5 | C18: RAYOS X EN ARCO EN C | D18: 1 | E18: PZ | F18: PHILIPS | H18: NMCA424 | I18: NMCA424-R | J18: 5363 | K18: PHILIPS | L18: Manprec | M18: 129000 | N18: USD | O18: Manprec | P18: 2470213 | R18: FALSE | S18: YA SE ENCUENTRA ENTREGADO | T18: DIRECTO A CLIENTE | U18: MAN13730 | V18: FALSE | Z18: FALSE
B19: 6 | C19: ELECTROENCEFALOGRAFO NEUROWORKS V32 | D19: 1 | E19: PZ | F19: NATUS | H19: PK1274 | I19: PK1274-R | J19: PK1274M004864 | L19: Manprec | M19: 39500 | N19: USD | O19: Manprec | P19: 756383 | Q19: MAN01091 | R19: FALSE | S19: EN ALMACEN 11 | T19: EN ALMACEN 11 | U19: MAN13730 | V19: FALSE | Z19: FALSE
B20: 7 | C20: UNIDAD DE ANESTESIA BASICA (RESONANCIA MAGNETICA) | D20: 1 | E20: PZ | F20: LÖWENSTEIN | H20: 0200025.2 | I20: 10651MRI-00 | J20: DK43202020 | K20: LÖWENSTEIN | L20: Manprec | M20: 19821 | N20: EURO | O20: MPC | P20: =M20*18*1.14*1.17 -> 475870.5 | R20: FALSE | S20: SE ENTREGARÁ DAMECA MRI | T20: EN ALMACEN 11 | U20: MPC29444 | V20: FALSE | Z20: FALSE
C21: vaporizador de sevoflurane | D21: 1 | E21: PZ | H21: 36980 | I21: 36980-R | J21: D1120-0218 | K21: LÖWENSTEIN | L21: Manprec | M21: 1100 | N21: EURO | O21: Manprec | P21: 28095 | Q21: Stock | R21: FALSE | S21: EN ALMACEN 11 | T21: EN ALMACEN 11 | U21: MAN13730 | V21: FALSE | Z21: FALSE
C22: Circuito de anestesi adulto de 3 mts | D22: 50 | E22: PZ | H22: MP00301-3M | I22: N/A | K22: HOSPIINNOVA | L22: Manprec | M22: =6500/10 -> 650 | N22: MXN | O22: Manprec | P22: $ - | Q22: MAN01095 | R22: FALSE | S22: EN ALMACEN 11 | T22: EN ALMACEN 11 | U22: MAN13730 | V22: FALSE | Z22: FALSE
C23: Manguera de oxigeno de 3 mtrs | D23: 1 | E23: PZ | H23: MAN-VERDE | I23: MAN-VERDE-R | J23: S/L | L23: Manprec | M23: 740 | N23: MXN | O23: MPC | P23: =M23 -> 740 | R23: FALSE | S23: EN ALMACEN 11 | T23: EN ALMACEN 11 | U23: MPC29444 | V23: FALSE | Z23: FALSE
C24: Manguera de Aire de 3 mts | D24: 1 | E24: PZ | H24: MAN-AMARILLA | I24: MAN-AMARILLA-R | J24: S/L | L24: Manprec | M24: 795 | N24: MXN | O24: MPC | P24: =M24 -> 795 | R24: FALSE | S24: EN ALMACEN 11 | T24: EN ALMACEN 11 | U24: MPC29444 | V24: FALSE | Z24: FALSE
B25: 8 | C25: BASCULA SECA 700 | D25: 15 | E25: PZ | F25: SECA | H25: SECA 700 | I25: SECA 700-R | J25: 10000002038617 10000002039318 10000002038641 10000001994888 10000002038615 10000002039302 10000002038616 10000002038619 10000002038611 10000002038612 10000002038640 10000002038610 10000002038613 10000002038614 10000002039300 | L25: Manprec | M25: 9230 | N25: MXN | O25: Manprec | P25: 9819 | Q25: MAN01093 | R25: FALSE | S25: EN ALMACEN 11 | T25: EN ALMACEN 11 | U25: MAN13730 | V25: FALSE | Z25: FALSE
I32: por punto 9
I33: INSTALACIÓN | K33: 2 MESES

Sheet FEDERICO GOMEZ
A1: PEDIDO | B1: PARTIDA | C1: DESCRIPCIÓN | D1: CANTIDAD | E1: UDM | F1: MARCA | G1: MODELO | H1: CÓDIGO | I1: PROVEEDOR | J1: Empresa que vende | K1: COSTO | L1: MONEDA COSTO | M1: EMPRESA QUE COMPRA | N1: OC | O1: B2B | P1: OBSERVACIONES | Q1: ESTATUS | R1: OV-INT | S1: Status de Interempresa | T1: OC-INT | U1: Status de Interempresa
A2: MAN13593 | B2: 1 | C2: MONITOR DESFIBRILADOR / CARRO ROJO | D2: 1 | E2: PZ | F2: PHILIPS | G2: DMF100 | H2: 866199.2 | I2: PHILIPS | J2: Manprec | K2: 2520.65 | L2: USD | M2: MPC | N2: Stock | O2: FALSE | Q2: EN ALMACEN 11 | R2: MPC29476 | S2: TRUE | T2: MAN01118 | U2: TRUE
C3: CARRO ROJO O DE REANIMACIÓN CON 5 CAJONES GRANDES | D3: 1 | E3: PZ | F3: GIVAS | G3: COPERNICO | H3: CP0011 | I3: GIVAS | J3: Manprec | K3: 1298.25 | L3: EURO | M3: ITH | N3: Stock | O3: FALSE | Q3: EN ALMACEN 11 | R3: ITH00975 | S3: TRUE | T3: MAN01119 | U3: TRUE
C4: Mango laringoscopio recargable 2.5v | D4: 1 | E4: PZ | F4: WELCH ALLYN | H4: WA60713 | I4: NAFARRATE | J4: Manprec | K4: 3628.8 | L4: MXN | M4: ITH | N4: ITH00214 | O4: FALSE | Q4: EN ALMACEN 11 | R4: ITH00975 | S4: TRUE | T4: MAN01119 | U4: TRUE
C5: Laringo recto miller FO1 | D5: 1 | E5: PZ | F5: WELCH ALLYN | H5: WA68061 | I5: NAFARRATE | J5: Manprec | K5: 1093.2 | L5: MXN | M5: ITH | N5: ITH00214 | O5: FALSE | Q5: EN ALMACEN 11 | R5: ITH00975 | S5: TRUE | T5: MAN01119 | U5: TRUE
C6: Laringo recto miller FO2 | D6: 1 | E6: PZ | F6: WELCH ALLYN | H6: WA68062 | I6: NAFARRATE | J6: Manprec | K6: 1093.2 | L6: MXN | M6: ITH | N6: ITH00214 | O6: FALSE | Q6: EN ALMACEN 11 | R6: ITH00975 | S6: TRUE | T6: MAN01119 | U6: TRUE
C7: Laringo curvo macintosh FO1 | D7: 1 | E7: PZ | F7: WELCH ALLYN | H7: WA69061 | I7: NAFARRATE | J7: Manprec | K7: 1093.2 | L7: MXN | M7: ITH | N7: ITH00214 | O7: FALSE | Q7: EN ALMACEN 11 | R7: ITH00975 | S7: TRUE | T7: MAN01119 | U7: TRUE
C8: Laringo curvo macintosh FO2 | D8: 1 | E8: PZ | F8: WELCH ALLYN | H8: WA69062 | I8: NAFARRATE | J8: Manprec | K8: 1093.2 | L8: MXN | M8: ITH | N8: ITH00214 | O8: FALSE | Q8: EN ALMACEN 11 | R8: ITH00975 | S8: TRUE | T8: MAN01119 | U8: TRUE
C9: Resucitador manual aduto | D9: 1 | E9: PZ | H9: AT70-555-01 | I9: NAFARRATE | J9: Manprec | K9: 878.8 | L9: MXN | M9: ITH | N9: ITH00214 | O9: FALSE | Q9: EN ALMACEN 11 | R9: ITH00975 | S9: TRUE | T9: MAN01119 | U9: TRUE
C10: Resucitador manual pediatrico | D10: 1 | E10: PZ | H10: AT70-555-02 | I10: NAFARRATE | J10: Manprec | K10: 851.4 | L10: MXN | M10: ITH | N10: ITH00214 | O10: FALSE | Q10: EN ALMACEN 11 | R10: ITH00975 | S10: TRUE | T10: MAN01119 | U10: TRUE
C11: Tanque de oxigeno | D11: 1 | E11: PZ | H11: OXI1630A | I11: FAREI | J11: Manprec | K11: 91.21 | L11: USD | M11: MPC | N11: MPC05041 | O11: FALSE | Q11: EN ALMACEN 11 | R11: MPC29476 | S11: TRUE | T11: MAN01118 | U11: TRUE
C12: Cargador universal escritorio | D12: 1 | E12: PZ | H12: WA71140 | I12: NAFARRATE | J12: Manprec | K12: 2697.8 | L12: MXN | M12: ITH | N12: ITH00214 | O12: FALSE | Q12: EN ALMACEN 11 | R12: ITH00975 | S12: TRUE | T12: MAN01119 | U12: TRUE
C13: Canula nasal adulto | D13: 1 | E13: PZ | H13: HUD1103 | I13: MEDLINE | J13: Manprec | K13: =1487/50 -> 29.74 | L13: MXN | M13: MPC | N13: Stock | O13: FALSE | Q13: EN ALMACEN 11 | R13: MPC29476 | S13: TRUE | T13: MAN01118 | U13: TRUE
C14: Regulador tipo clik largo 0-15 LPM | D14: 1 | E14: PZ | H14: Y8715-E | I14: FAREI | J14: Manprec | K14: 28.13 | L14: USD | M14: MPC | N14: Stock | O14: FALSE | Q14: EN ALMACEN 11 | R14: MPC29476 | S14: TRUE | T14: MAN01118 | U14: TRUE
C15: Conector Plastico cola de raton | D15: 1 | E15: PZ | H15: AC1201 | I15: FAREI | J15: Manprec | K15: 0.51 | L15: USD | M15: MPC | N15: Stock | O15: FALSE | Q15: EN ALMACEN 11 | R15: MPC29476 | S15: TRUE | T15: MAN01118 | U15: TRUE
O16: FALSE | Q16: - | S16: FALSE | U16: FALSE
O17: FALSE | Q17: - | S17: FALSE | U17: FALSE
O18: FALSE | Q18: - | S18: FALSE | U18: FALSE
O19: FALSE | Q19: - | S19: FALSE | U19: FALSE

Sheet Cart centro -radioterapia MAN13
A1: PEDIDO | B1: PARTIDA | C1: DESCRIPCIÓN | D1: CANTIDAD | E1: UDM | F1: MARCA | G1: MODELO | H1: CÓDIGO | I1: PROVEEDOR | J1: Empresa que vende | K1: COSTO | L1: MONEDA COSTO | M1: EMPRESA QUE COMPRA | N1: OC | O1: B2B | P1: OBSERVACIONES | Q1: ESTATUS | R1: OV-INT | S1: Status de Interempresa | T1: OC-INT | U1: Status de Interempresa
A2: MAN13621 | B2: 1 | C2: Efficia CM12, ECG | SpO2 | Resp | Temp | PNI789 | D2: 2 | E2: PZ | F2: PHILIPS | G2: CM12 | H2: 863303.1 | I2: PHILIPS | J2: Manprec | L2: USD | M2: N/A | O2: FALSE | Q2: - | S2: FALSE | U2: FALSE
C3: Carro de transporte TPX para monitor de S.V. Philips Efficia/Goldway | D3: 2 | E3: PZ | H3: RP050 | I3: TPX | J3: Manprec | L3: USD | M3: MPC | N3: Stock | O3: FALSE | Q3: - | S3: FALSE | U3: FALSE
C4: Reusable Adult SpO2 Sensor | D4: 2 | E4: PZ | H4: M1191BL | I4: PHILIPS | J4: Manprec | L4: USD | M4: N/A | N4: Stock | O4: FALSE | Q4: - | S4: FALSE | U4: FALSE
C5: SENSOR DE TEMPERATURA | D5: 2 | E5: PZ | H5: 21078ST | I5: HOSPIINNOVA | J5: Manprec | L5: MXN | M5: N/A | N5: Stock | O5: FALSE | Q5: - | S5: FALSE | U5: FALSE
C6: CBL 5 Leadset Snap AAMI ICU | D6: 2 | E6: PZ | H6: M1644A | I6: PHILIPS | J6: Manprec | L6: USD | M6: N/A | N6: Stock | O6: FALSE | Q6: - | S6: FALSE | U6: FALSE
C7: CBL 5 Lead ECG Trunk AAMI/IEC 2.7m (M1668A) | D7: 2 | E7: PZ | H7: 989803145061 | I7: PHILIPS | J7: Manprec | L7: USD | M7: N/A | N7: Stock | O7: FALSE | Q7: - | S7: FALSE | U7: FALSE
C8: Easy Care Cuff 1 Hose Adult (1) | D8: 2 | E8: PZ | H8: M4555B | I8: PHILIPS | J8: Manprec | L8: USD | M8: N/A | N8: Stock | O8: FALSE | Q8: - | S8: FALSE | U8: FALSE
C9: Adult NIBP Air Hose 3.0m | D9: 2 | E9: PZ | H9: 989803209771 | I9: PHILIPS | J9: Manprec | L9: USD | M9: N/A | N9: Stock | O9: FALSE | Q9: - | S9: FALSE | U9: FALSE
O10: FALSE | Q10: - | S10: FALSE | U10: FALSE
O11: FALSE | Q11: - | S11: FALSE | U11: FALSE
O12: FALSE | Q12: - | S12: FALSE | U12: FALSE
O13: FALSE | Q13: - | S13: FALSE | U13: FALSE
O14: FALSE | Q14: - | S14: FALSE | U14: FALSE
O15: FALSE | Q15: - | S15: FALSE | U15: FALSE
O16: FALSE | Q16: - | S16: FALSE | U16: FALSE
O17: FALSE | Q17: - | S17: FALSE | U17: FALSE
O18: FALSE | Q18: - | S18: FALSE | U18: FALSE
O19: FALSE | Q19: - | S19: FALSE | U19: FALSE

Sheet INC
A1: PEDIDO | B1: PARTIDA | C1: DESCRIPCIÓN | D1: CANTIDAD | E1: UDM | F1: MARCA | G1: MODELO | H1: CÓDIGO | I1: PROVEEDOR | J1: Empresa que vende | K1: COSTO | L1: MONEDA COSTO | M1: EMPRESA QUE COMPRA | N1: OC | O1: B2B | P1: OBSERVACIONES | Q1: ESTATUS | R1: OV-INT | S1: Status de Interempresa | T1: OC-INT | U1: Status de Interempresa
A2: MAN13687 | B2: 1 | C2: EarlyVue VS30 Vitals monitor | E2: 2 | G2: 863380.1 | H2: 866360.1 | I2: Philips | J2: Manprec | K2: 2921.1 | L2: USD | M2: MPC | N2: MPC04792 | O2: FALSE | Q2: ENVIADA | R2: MPC29656 | S2: FALSE | U2: FALSE
C3: Easy Care Cuff, 1 Hose, Infant (1) | E3: 2 | H3: M4552B | I3: Philips | J3: Manprec | K3: 11.11 | L3: USD | M3: MPC | N3: MPC04792 | O3: FALSE | Q3: ENVIADA | R3: MPC29656 | S3: FALSE | U3: FALSE
C4: Easy Care Cuff, 1 Hose, Pediatric (1) | E4: 2 | H4: M4553B | I4: Philips | J4: Manprec | K4: 26.71 | L4: USD | M4: MPC | N4: MPC04792 | O4: FALSE | Q4: ENVIADA | R4: MPC29656 | S4: FALSE | U4: FALSE
C5: Easy Care Cuff, 1 Hose, Adult (1) | E5: 2 | H5: M4555B | I5: Philips | J5: Manprec | L5: USD | M5: N/A | N5: Stock | O5: TRUE | Q5: EN ALMACEN 11 | S5: FALSE | U5: FALSE
C6: Adult NIBP Air Hose 3.0m | E6: 2 | H6: 989803209771 | I6: Philips | J6: Manprec | L6: USD | M6: N/A | N6: Stock | O6: TRUE | Q6: EN ALMACEN 11 | S6: FALSE | U6: FALSE
C7: SPO2 Reus Ped-Adult Glove Sensor M1192A | E7: 2 | H7: 989803205871 | I7: Philips | J7: Manprec | L7: USD | M7: N/A | N7: Stock | O7: TRUE | Q7: EN ALMACEN 11 | S7: FALSE | U7: FALSE
C8: SPO2 Reus Neo Hnd-Ft Wrap Sensor M1193A | E8: 2 | H8: 989803205881 | I8: Philips | J8: Manprec | K8: 113.1 | L8: USD | M8: MPC | N8: MPC04792 | O8: FALSE | Q8: ENVIADA | R8: MPC29656 | S8: FALSE | U8: FALSE
C9: CBL SpO2 Extension Cable, 2m | E9: 2 | H9: M1941A | I9: Philips | J9: Manprec | L9: USD | M9: N/A | N9: Stock | O9: TRUE | Q9: EN ALMACEN 11 | S9: FALSE | U9: FALSE
C10: Reusable Adult SpO2 Sensor | E10: 2 | H10: M1191B | I10: Philips | J10: Manprec | K10: 107.9 | L10: USD | M10: MPC | N10: MPC04792 | O10: FALSE | Q10: ENVIADA | R10: MPC29656 | S10: FALSE | U10: FALSE
C11: Reusable Oral Temp Probe & Well Kit | E11: 2 | H11: 989803143381 | I11: Philips | J11: Manprec | K11: 146.9 | L11: USD | M11: MPC | N11: MPC04792 | O11: FALSE | Q11: ENVIADA | R11: MPC29656 | S11: FALSE | U11: FALSE
C12: SureSigns Premium Rollstand | E12: 2 | H12: 989803176601 | I12: Philips | J12: Manprec | K12: 453.7 | L12: USD | M12: MPC | N12: MPC04792 | O12: FALSE | Q12: ENVIADA | R12: MPC29656 | S12: FALSE | U12: FALSE
O13: FALSE | Q13: - | S13: FALSE | U13: FALSE
O14: FALSE | Q14: - | S14: FALSE | U14: FALSE

Sheet IMSS Bienestar N-53 ARRENDAMIEN
A1: PEDIDO | B1: PARTIDA | C1: DESCRIPCIÓN | D1: CANTIDAD | E1: UDM | F1: MARCA | G1: MODELO | H1: CÓDIGO | I1: PROVEEDOR | J1: Empresa que vende | K1: COSTO | L1: MONEDA COSTO | M1: EMPRESA QUE COMPRA | N1: OC | O1: B2B | P1: 1era Inter | Q1: 2da Inter MPC a Manprec | R1: NS | S1: OBSERVACIONES | T1: ESTATUS | U1: OV-INT | V1: Status de Interempresa | W1: OC-INT | X1: Status de Interempresa
A2: MAN13655 | B2: 1 | C2: Ultrasonografos | D2: 2 | E2: PZ | F2: PHILIPS | G2: AFFINITI 30 | H2: NUSM368-R | I2: PHILIPS | J2: Manprec | K2: =21559.06+4900 -> 26459.06 | L2: USD | M2: MPC | N2: MPC04367 | O2: FALSE | P2: - | Q2: 20 | S2: 1 EQUIPO POR MPC | T2: EN ALMACEN 11 | V2: FALSE | X2: FALSE
C3: UPS | D3: 2 | E3: PZ | F3: POWER ALL | H3: KR+19-3000-01UN-R | I3: ALTERNATIVA | J3: Manprec | K3: 749 | L3: USD | M3: Gamit | O3: FALSE | P3: 10 | R3: UI012642505902 UI012642505904 | U3: GAM00169 | V3: TRUE | X3: FALSE
C4: TRASDUCER S4-2 | D4: 1 | E4: PZ | F4: PHILIPS | H4: 989605414692-R | I4: PHILIPS | J4: Manprec | L4: USD | M4: Manprec | O4: FALSE | P4: 6 | U4: MAN13713 | V4: FALSE | X4: FALSE
A5: MAN13655 | B5: 2 | C5: Mastografos Digitales Con Estrerotaxia Y Tomosintesis | D5: 1 | E5: PZ | F5: ITALRAY | H5: DMA+MT300-B-R | I5: ITALRAY | J5: Manprec | K5: 124100 | L5: EURO | M5: CEO | N5: CEO00160 | O5: FALSE | P5: 0.1 | S5: RE VA A RENTAR UN EQUIPO | T5: ENVIADA | V5: FALSE | X5: FALSE
A6: MAN13655 | B6: 3 | C6: Ecocardiografos | D6: 2 | E6: PZ | F6: PHILIPS | G6: EPIQ CVX | H6: 795231-R | I6: PHILIPS | J6: Manprec | K6: =109962.2 -> 109962.2 | L6: USD | M6: Manprec | N6: MAN00477 | O6: FALSE | P6: 0.06 | S6: SE TOMAN LOS EQUIPOS DE FUNDACION DERECHOS DE LA INFANCIA | T6: EN ALMACEN 11 | V6: FALSE | X6: FALSE
C7: UPS | D7: 2 | E7: PZ | F7: POWER ALL | H7: KR+19-3000-01UN-R | I7: ALTERNATIVA | J7: Manprec | K7: 749 | L7: USD | M7: Gamit | O7: FALSE | P7: 10 | R7: UI012642505905 UI012642505907 | U7: GAM00169 | V7: TRUE | X7: FALSE
C8: Upgrade | O8: FALSE | V8: FALSE | X8: FALSE
C9: TRASDUCER S5-1 | D9: 2 | E9: PZ | F9: PHILIPS | H9: FUS9390-R | I9: PHILIPS | J9: Manprec | L9: USD | M9: Manprec | O9: FALSE | P9: 6 | V9: FALSE | X9: FALSE
C10: TRASDUCER S12-4 | D10: 2 | E10: PZ | F10: PHILIPS | H10: 989605361892-R | I10: PHILIPS | J10: Manprec | L10: USD | M10: Manprec | O10: FALSE | P10: 6 | V10: FALSE | X10: FALSE
C11: TRASDUCER X8-2t | D11: 2 | E11: PZ | F11: PHILIPS | H11: FUS9354-R | I11: PHILIPS | J11: Manprec | L11: USD | M11: Manprec | O11: FALSE | P11: 6 | V11: FALSE | X11: FALSE
C12: TRASDUCER S8-3 | D12: 2 | E12: PZ | F12: PHILIPS | H12: 989605361882-R | I12: PHILIPS | J12: Manprec | L12: USD | M12: Manprec | O12: FALSE | P12: 6 | V12: FALSE | X12: FALSE
A13: MAN13655 | B13: 4 | C13: Electrocardiografos Multicanal Con Interpretacion | D13: 2 | E13: PZ | F13: SCHILLER | H13: 0A.108000-R | I13: SCHILLER | J13: Manprec | K13: 3345 | L13: USD | M13: ITH | N13: ITH00215 | O13: FALSE | P13: 10 | T13: EN ALMACEN 11 | U13: ITH00980 | V13: TRUE | X13: FALSE
C14: CARRO DE TRASNPORTE | D14: 2 | E14: PZ | F14: TPX | H14: RP050-6-R | I14: TPX | J14: Manprec | K14: 127.5 | L14: USD | M14: MPC | O14: FALSE | P14: - | T14: PENDIENTE | V14: FALSE | X14: FALSE
A15: MAN13655 | B15: 5 | C15: Unidad Radiológica Y Fluoroscopica, Transportable, Tipo Arco En "C" | D15: 1 | E15: PZ | F15: PHILIPS | G15: ZENITION 70 | H15: NMCA425-R | I15: PHILIPS | J15: Manprec | K15: 129000 | L15: USD | M15: Manprec | N15: MAN00941 | O15: FALSE | P15: 6 | S15: SE SOLCITA DEMO | T15: ENVIADA | V15: FALSE | X15: FALSE
O16: FALSE | T16: - | V16: FALSE | X16: FALSE
O17: FALSE | T17: - | V17: FALSE | X17: FALSE
O18: FALSE | T18: - | V18: FALSE | X18: FALSE
O19: FALSE | T19: - | V19: FALSE | X19: FALSE
O20: FALSE | T20: - | V20: FALSE | X20: FALSE
O21: FALSE | T21: - | V21: FALSE | X21: FALSE
O22: FALSE | T22: - | V22: FALSE | X22: FALSE
O23: FALSE | T23: - | V23: FALSE | X23: FALSE
O24: FALSE | T24: - | V24: FALSE | X24: FALSE
O25: FALSE | T25: - | V25: FALSE | X25: FALSE
O26: FALSE | T26: - | V26: FALSE | X26: FALSE
O27: FALSE | T27: - | V27: FALSE | X27: FALSE
O28: FALSE | T28: - | V28: FALSE | X28: FALSE

Sheet Romare | Siniestros  ISSSTE Coa
A1: PEDIDO | B1: PARTIDA | C1: DESCRIPCIÓN | D1: CANTIDAD | E1: UDM | F1: MARCA | G1: MODELO | H1: CÓDIGO | I1: PROVEEDOR | J1: Empresa que vende | K1: COSTO | L1: MONEDA COSTO | M1: EMPRESA QUE COMPRA | N1: OC | O1: B2B | P1: OBSERVACIONES | Q1: ESTATUS | R1: OV-INT | S1: Status de Interempresa | T1: OC-INT | U1: Status de Interempresa
A2: MPC29406 | B2: 1 | C2: Ecocardiografo | D2: 1 | E2: PZ | F2: Philips | G2: Epic CVX | H2: NUSX001 | I2: PHILIPS | J2: MPC | K2: 67682.94 | L2: USD | M2: MPC | N2: MAN13470 | O2: FALSE | P2: S/N:US626B1109 | Q2: EN ALMACEN 11 | R2: N/A | S2: TRUE | T2: N/A | U2: TRUE
C3: Sistema de respaldo UPS | D3: 1 | E3: PZ | F3: Power All | H3: KR+19-3000-01UN | I3: ALTERNATIVA | J3: MPC | K3: 749 | L3: USD | M3: Gamit | N3: GAM00059 | O3: FALSE | P3: RECUPERAR ESTE UPS | Q3: EN ALMACEN 11 | R3: GAM00170 | S3: TRUE | T3: MPC05156 | U3: TRUE
C4: Tranducer S5-1 | D4: 1 | E4: PZ | F4: Philips | H4: FUS9390 | I4: PHILIPS | J4: MPC | L4: USD | M4: MPC | N4: MPC05033 | O4: FALSE | R4: N/A | S4: TRUE | T4: N/A | U4: TRUE
C5: Tranducer X5-1 | D5: 1 | E5: PZ | F5: Philips | H5: 989605400802 | I5: PHILIPS | J5: MPC | K5: 8000 | L5: USD | M5: MPC | N5: MPC04367 | O5: FALSE | R5: N/A | S5: TRUE | T5: N/A | U5: TRUE
C6: Tranducer X8-2t | D6: 1 | E6: PZ | F6: Philips | H6: FUS9354 | I6: PHILIPS | J6: MPC | K6: 18000 | L6: USD | M6: MPC | N6: MPC04367 | O6: FALSE | R6: N/A | S6: TRUE | T6: N/A | U6: TRUE
C7: Tranducer S8-3 | D7: 1 | E7: PZ | F7: Philips | H7: 989605361882 | I7: PHILIPS | J7: MPC | L7: USD | M7: MPC | N7: MPC05033 | O7: FALSE | R7: N/A | S7: TRUE | T7: N/A | U7: TRUE
A8: MPC29408 | B8: 1 | C8: Unidad de tomografia | D8: 1 | E8: PZ | F8: Philips | G8: Incisive | H8: NCTE306 | I8: PHILIPS | J8: MPC | K8: 400000 | L8: USD | M8: MPC | N8: MPC05084 | O8: FALSE | Q8: ENVIADA | R8: N/A | S8: TRUE | T8: N/A | U8: TRUE
C9: Sistema de energia ininterrumpida | D9: 1 | E9: PZ | F9: Power All | H9: MPP5S-02125HV | I9: ALTERNATIVA | J9: MPC | K9: 25632 | L9: USD | M9: Gamit | N9: GAM00057 | O9: FALSE | Q9: EN ALMACEN 11 | R9: GAM00168 | S9: TRUE | T9: MPC05108 | U9: TRUE
C10: Banco de baterias | D10: 1 | E10: PZ | F10: Power All | H10: PA BB MULTIPOWER | I10: ALTERNATIVA | J10: MPC | K10: 16129 | L10: USD | M10: Gamit | N10: GAM00057 | O10: FALSE | Q10: EN ALMACEN 11 | R10: GAM00168 | S10: TRUE | T10: MPC05108 | U10: TRUE
C11: Obra de adecuaciones | D11: 1 | E11: servicio | F11: TEKTON | H11: servicio | I11: TEKTON | J11: MPC | L11: USD | M11: MPC | O11: FALSE | Q11: - | R11: N/A | S11: TRUE | T11: N/A | U11: TRUE

Sheet Tridex Medical
A1: PEDIDO | B1: PARTIDA | C1: DESCRIPCIÓN | D1: CANTIDAD | E1: UDM | F1: MARCA | G1: MODELO | H1: CÓDIGO | I1: PROVEEDOR | J1: Empresa que vende | K1: COSTO | L1: MONEDA COSTO | M1: EMPRESA QUE COMPRA | N1: OC | O1: B2B | P1: OBSERVACIONES | Q1: ESTATUS | R1: OV-INT | S1: Status de Interempresa | T1: OC-INT | U1: Status de Interempresa
A2: MAN13445 | B2: 1 | C2: Leon MRI | Unidad de anestesia Leon MRI con medición insp de O2 | D2: 1 | E2: PZ | F2: Löwestein | G2: Leon MRI | H2: 0200025.2 | I2: Löwestein | J2: Manprec | L2: EURO | M2: N/A | O2: FALSE | Q2: - | S2: FALSE | U2: FALSE
C3: Vaporizador Sevoflorane | D3: 2 | E3: PZ | F3: Löwestein | H3: 36980 | I3: Löwestein | J3: Manprec | L3: EURO | O3: FALSE | Q3: - | S3: FALSE | U3: FALSE
C4: llenador para vaportizador sevoflorane | D4: 2 | E4: PZ | I4: Löwestein | J4: Manprec | L4: EURO | O4: FALSE | P4: REVISAR SI LO TIENEN DENTRO DEL EQUIPO | Q4: - | S4: FALSE | U4: FALSE
C5: Circuito de paciente desechable 3 mts adulto | D5: 2 | E5: PZ | H5: MP00301-3M | I5: HOSPIINNOVA | J5: Manprec | K5: =6500/10 -> 650 | L5: MXN | M5: N/A | N5: MAN01149 | O5: FALSE | Q5: - | S5: FALSE | U5: FALSE
C6: Circuito tipo bain reusable adulto | D6: 2 | E6: PZ | H6: MP03373 | I6: HOSPIINNOVA | J6: Manprec | K6: =7000/10 -> 700 | L6: MXN | M6: N/A | O6: FALSE | Q6: - | S6: FALSE | U6: FALSE
C7: Mascarilla transparente adulto #5 | D7: 5 | E7: PZ | H7: MP01915 | I7: HOSPIINNOVA | J7: Manprec | K7: 485 | L7: MXN | M7: N/A | N7: MAN01149 | O7: FALSE | Q7: - | S7: FALSE | U7: FALSE
C8: Mascarilla transparente adulto pequeño #4 | D8: 5 | E8: PZ | H8: MP01914 | I8: HOSPIINNOVA | J8: Manprec | K8: 485 | L8: MXN | M8: N/A | N8: MAN01149 | O8: FALSE | Q8: - | S8: FALSE | U8: FALSE
C9: Bolsa para ventilacion reusable 1L | D9: 1 | E9: PZ | H9: 2166127 | I9: HOSPIINNOVA | J9: Manprec | K9: 1311.5 | L9: MXN | M9: N/A | O9: FALSE | Q9: - | S9: FALSE | U9: FALSE
C10: Bolsa para ventilacion reusable 2L | D10: 1 | E10: PZ | H10: 2166062 | I10: HOSPIINNOVA | J10: Manprec | K10: 1311.5 | L10: MXN | M10: N/A | O10: FALSE | Q10: - | S10: FALSE | U10: FALSE
C11: Bolsa para ventilacion reusable 3L | D11: 1 | E11: PZ | H11: 2166070 | I11: HOSPIINNOVA | J11: Manprec | K11: 1311.5 | L11: MXN | M11: N/A | O11: FALSE | Q11: - | S11: FALSE | U11: FALSE
C12: Circuito de paciente audlto desechable | D12: 10 | E12: PZ | H12: MP00301-3M | I12: HOSPIINNOVA | J12: Manprec | K12: =6500/10 -> 650 | L12: MXN | M12: N/A | O12: FALSE | Q12: - | S12: FALSE | U12: FALSE
O13: FALSE | Q13: - | S13: FALSE | U13: FALSE
O14: FALSE | Q14: - | S14: FALSE | U14: FALSE
O15: FALSE | Q15: - | S15: FALSE | U15: FALSE
O16: FALSE | Q16: - | S16: FALSE | U16: FALSE
O17: FALSE | Q17: - | S17: FALSE | U17: FALSE
O18: FALSE | Q18: - | S18: FALSE | U18: FALSE
O19: FALSE | Q19: - | S19: FALSE | U19: FALSE

Sheet IMSS BIENESTAR TABASCO IM168-20
A1: PEDIDO | B1: PARTIDA | C1: DESCRIPCIÓN | D1: CANTIDAD | E1: UDM | F1: MARCA | G1: MODELO | H1: CÓDIGO | I1: PROVEEDOR | J1: Empresa que vende | K1: COSTO | L1: MONEDA COSTO | M1: EMPRESA QUE COMPRA | N1: OC | O1: B2B | P1: OBSERVACIONES | Q1: ESTATUS | R1: OV-INT | S1: Status de Interempresa | T1: OC-INT | U1: Status de Interempresa
A2: MAN13825 | B2: 87 | C2: CARDIOTOCÓGRAFO | D2: 5 | E2: PZ | F2: PHILIPS | G2: AVALON FM20 | H2: M2702A.1 | I2: PHILIPS | J2: Manprec | L2: USD | M2: N/A | N2: Stock | O2: FALSE | P2: DE79570438 DE79570442 DE79570458 DE79570866 DE79570867 | Q2: EN ALMACEN 11 | S2: FALSE | U2: FALSE
C3: Avalon US Transducer | D3: 10 | E3: PZ | H3: 867246 | I3: PHILIPS | J3: Manprec | L3: USD | M3: N/A | N3: Stock | O3: FALSE | Q3: EN ALMACEN 11 | S3: FALSE | U3: FALSE
C4: Avalon TOCO MP Transducer | D4: 10 | E4: PZ | H4: 867248 | I4: PHILIPS | J4: Manprec | L4: USD | M4: N/A | N4: Stock | O4: FALSE | Q4: EN ALMACEN 11 | S4: FALSE | U4: FALSE
C5: Remote Event Marker | D5: 5 | E5: PZ | H5: 989803143411 | I5: PHILIPS | J5: Manprec | L5: USD | M5: N/A | N5: Stock | O5: FALSE | Q5: EN ALMACEN 11 | S5: FALSE | U5: FALSE
C6: Reusable Abdominal Belt- 60mm Wd 1.3M Lg | D6: 10 | E6: C/40 | H6: CINFM | I6: HOSPIINNOVA | J6: Manprec | L6: MXN | M6: N/A | N6: Stock | O6: FALSE | Q6: EN ALMACEN 11 | S6: FALSE | U6: FALSE
C7: Fetal monitoring recording paper | D7: 5 | E7: PZ | H7: M1910A | I7: PHILIPS | J7: Manprec | L7: MXN | M7: N/A | N7: Stock | O7: FALSE | Q7: EN ALMACEN 11 | S7: FALSE | U7: FALSE
C8: GEL PARA ULTRASONIDO | D8: 5 | E8: PZ | H8: ALT 040 | I8: PRONAMAC | J8: Manprec | K8: 55.86 | L8: MXN | M8: MPC | N8: MPC05446 | O8: FALSE | Q8: PENDIENTE | S8: FALSE | U8: FALSE
C9: CARRO DE TRASPORTE | D9: 5 | E9: PZ | H9: RP050-6 | I9: TPX | J9: Manprec | L9: USD | M9: MPC | N9: Stock | O9: FALSE | Q9: EN ALMACEN 11 | S9: FALSE | U9: FALSE
C10: ACTUALIZACION PARA COLOCAR BATERIA | D10: 5 | E10: PZ | H10: M2702AU | I10: PHILIPS | J10: Manprec | L10: USD | M10: N/A | N10: MAN01174 | O10: FALSE | P10: falta cotizacion philips | S10: FALSE | U10: FALSE
C11: ESTIMULADOR ACUSTICO | D11: 5 | E11: PZ | H11: 83.62.17692 | I11: EDAN | J11: Manprec | L11: USD | M11: CEO | O11: FALSE | P11: en espera de cotizacion | S11: FALSE | U11: FALSE
A12: MAN13825 | B12: 150 | C12: ECOCARDIÓGRAFO DIGITAL | D12: 1 | E12: PZ | F12: PHILIPS | G12: AFFINITI CVx | H12: 795190 | I12: PHILIPS | J12: Manprec | K12: 56263.43 | L12: USD | M12: MPC | N12: MPC05324 | O12: FALSE | Q12: ENVIADA | S12: FALSE | U12: FALSE
C13: IMPRESORA | D13: 1 | E13: PZ | H13: B0BVX5SFPN | I13: AMAZON | J13: Manprec | L13: MXN | M13: MPC | O13: FALSE | S13: FALSE | U13: FALSE
C14: UPS | D14: 1 | E14: PZ | H14: KR+19-3000-01UN | I14: ALTERNATIVA | J14: Manprec | L14: USD | M14: Gamit | O14: FALSE | S14: FALSE | U14: FALSE
C15: PAPEL BOND PAQUETE DE 500 HOJAS | D15: 1 | E15: PZ | H15: 6369 | I15: OFFICE DEPOT | J15: Manprec | L15: MXN | M15: MPC | N15: Stock | O15: FALSE | P15: consumible de oficina | S15: FALSE | U15: FALSE
C16: DVD | D16: 5 | E16: C/100 | H16: B00O0IDJT2 | I16: AMAZON | J16: Manprec | L16: MXN | M16: MPC | O16: FALSE | S16: FALSE | U16: FALSE
A17: MAN13825 | B17: 151 | C17: ELECTROCARDIÓGRAFO MULTICANAL (3 CANALES 12 DERIVACIONES) | D17: 1 | E17: PZ | F17: SCHILLER | G17: CARDIOVIT AT-102 G2 | H17: 0A.108000 | I17: SCHILLER | J17: Manprec | L17: USD | M17: ITH | N17: ITH00221 | O17: FALSE | Q17: ENVIADA | S17: FALSE | U17: FALSE
C18: Set of children ECG electrodes incl. 6 suction | D18: 1 | E18: PZ | F18: SCHILLER | H18: 2.000052 | I18: SCHILLER | J18: Manprec | L18: USD | M18: ITH | O18: FALSE | Q18: ENVIADA | S18: FALSE | U18: FALSE
C19: SNAP-CLIP Adapter for banana-plug cables pouch of 10 pcs | D19: 1 | E19: PZ | F19: SCHILLER | H19: 2.155032 | I19: SCHILLER | J19: Manprec | L19: USD | M19: ITH | O19: FALSE | Q19: ENVIADA | S19: FALSE | U19: FALSE
C20: Thermal chart paper AT-102, AT-102 plus, AT-102 G2, | D20: 3 | E20: PZ | F20: SCHILLER | H20: 2.15705 | I20: SCHILLER | J20: Manprec | L20: USD | M20: ITH | O20: FALSE | Q20: ENVIADA | S20: FALSE | U20: FALSE
C21: TUBO DE GEL DE 250 ML | D21: 2 | E21: PZ | F21: ULTRASONIC | H21: ALT 040 | I21: PRONAMAC | J21: Manprec | K21: 55.86 | L21: MXN | M21: MPC | N21: MPC05446 | O21: FALSE | Q21: PENDIENTE | S21: FALSE | U21: FALSE
C22: ELECTRODOS DE ECG | D22: 5 | E22: B/100 | F22: CARDINAL | H22: 31050522 | I22: HOSPIINNOVA | J22: Manprec | L22: MXN | M22: N/A | O22: FALSE | Q22: EN ALMACEN 11 | S22: FALSE | U22: FALSE
A23: MAN13825 | B23: 246 | C23: MICROTOMO PARA CORTES EN PARAFINA | D23: 1 | E23: Equipo | F23: HISTO-LINE | G23: MRS3500-S | H23: MRS3500-S | I23: HISTO-LINE | J23: Manprec | K23: 7859 | L23: EURO | M23: CEO | N23: CEO00169 | O23: FALSE | Q23: ENVIADA | S23: FALSE | U23: FALSE
C24: Cepillo mediano | D24: 1 | E24: C/10 | H24: HL3206 | I24: HISTO-LINE | J24: Manprec | L24: EURO | M24: CEO | N24: CEO00169 | O24: FALSE | P24: EN CONJUTO EN EL EQUIPO | Q24: ENVIADA | S24: FALSE | U24: FALSE
C25: Cepillo redondo | D25: 1 | E25: C/2 | H25: HL3209 | I25: HISTO-LINE | J25: Manprec | L25: EURO | M25: CEO | N25: CEO00169 | O25: FALSE | P25: EN CONJUTO EN EL EQUIPO | Q25: ENVIADA | S25: FALSE | U25: FALSE
C26: Spray desinfectante | D26: 1 | E26: C/10 | H26: 22-135 | I26: HISTO-LINE | J26: Manprec | L26: EURO | M26: CEO | N26: CEO00169 | O26: FALSE | P26: EN CONJUTO EN EL EQUIPO | Q26: ENVIADA | S26: FALSE | U26: FALSE
C27: Aceite para microtomo | D27: 1 | E27: C/10 | H27: 22-124 | I27: HISTO-LINE | J27: Manprec | L27: EURO | M27: CEO | N27: CEO00169 | O27: FALSE | P27: EN CONJUTO EN EL EQUIPO | Q27: ENVIADA | S27: FALSE | U27: FALSE
C28: cuchilla de perfil alto | D28: 4 | E28: C/50 | H28: R43371 | I28: HISTO-LINE | J28: Manprec | L28: EURO | M28: CEO | N28: CEO00169 | O28: FALSE | P28: EN CONJUTO EN EL EQUIPO | Q28: ENVIADA | S28: FALSE | U28: FALSE
C29: cuchilla de perfil bajo | D29: 4 | E29: C/50 | H29: R43351 | I29: HISTO-LINE | J29: Manprec | L29: EURO | M29: CEO | N29: CEO00169 | O29: FALSE | P29: EN CONJUTO EN EL EQUIPO | Q29: ENVIADA | S29: FALSE | U29: FALSE
A30: MAN13244 | B30: 248 | C30: MONITOR DE SIGNOS VITALES | D30: 31 | E30: pz | F30: PHILIPS | G30: INTELLIVUE MX500 | I30: PHILIPS | J30: Manprec | L30: USD | O30: FALSE | Q30: DIRECTO A CLIENTE | S30: FALSE | U30: FALSE
A31: MAN13244 | B31: 248 | C31: MONITOR DE SIGNOS VITALES (RODABLE) | D31: 15 | E31: pz | F31: PHILIPS | G31: INTELLIVUE MX500 | I31: PHILIPS | J31: Manprec | L31: USD | O31: FALSE | Q31: DIRECTO A CLIENTE | S31: FALSE | U31: FALSE
A32: MAN13244 | B32: 249 | C32: MONITOR DE SIGNOS VITALES (PEDIÁTRICO) | D32: 1 | E32: pz | F32: PHILIPS | G32: INTELLIVUE MX550 | I32: PHILIPS | J32: Manprec | L32: USD | O32: FALSE | Q32: DIRECTO A CLIENTE | S32: FALSE | U32: FALSE
A33: MAN13244 | B33: 249 | C33: MONITOR DE SIGNOS VITALES INTERMEDIO | D33: 2 | E33: pz | F33: PHILIPS | G33: INTELLIVUE MX550 | I33: PHILIPS | J33: Manprec | L33: USD | O33: FALSE | Q33: DIRECTO A CLIENTE | S33: FALSE | U33: FALSE
A34: MAN13244 | B34: 250 | C34: MONITOR DE SIGNOS VITALES PARA EL TRASLADO DEL PACIENTE | D34: 8 | E34: pz | F34: PHILIPS | G34: INTELLIVUE MX450 | I34: PHILIPS | J34: Manprec | L34: USD | O34: FALSE | Q34: DIRECTO A CLIENTE | S34: FALSE | U34: FALSE
B35: 292 | C35: PROCESADOR AUTOMÁTICO DE TEJIDOS | D35: 1 | E35: Equipo | F35: HISTO-LINE | G35: STP250-DUO | H35: STP250-DUO | I35: HISTO-LINE | J35: Manprec | K35: 11396.8 | L35: EURO | M35: CEO | N35: CEO00169 | O35: FALSE | Q35: ENVIADA | S35: FALSE | U35: FALSE
C36: Contenedor de reactivos | D36: 4 | E36: PZ | H36: 250-10 | I36: HISTO-LINE | J36: Manprec | L36: EURO | M36: CEO | N36: CEO00169 | O36: FALSE | P36: EN CONJUTO EN EL EQUIPO | Q36: ENVIADA | S36: FALSE | U36: FALSE
C37: Baño de parafina | D37: 1 | E37: PZ | H37: 250-9 | I37: HISTO-LINE | J37: Manprec | L37: EURO | M37: CEO | N37: CEO00169 | O37: FALSE | P37: EN CONJUTO EN EL EQUIPO | Q37: ENVIADA | S37: FALSE | U37: FALSE
C38: Canastilla para casetes | D38: 2 | E38: PZ | H38: 250-24 | I38: HISTO-LINE | J38: Manprec | L38: EURO | M38: CEO | N38: CEO00169 | O38: FALSE | P38: EN CONJUTO EN EL EQUIPO | Q38: ENVIADA | S38: FALSE | U38: FALSE
C39: Casetes | D39: 1 | E39: C/1000 | H39: R4170 | I39: HISTO-LINE | J39: Manprec | L39: EURO | M39: CEO | N39: CEO00169 | O39: FALSE | P39: EN CONJUTO EN EL EQUIPO | Q39: ENVIADA | S39: FALSE | U39: FALSE
C40: Casetes | D40: 1 | E40: C/12 | H40: R4161 | I40: HISTO-LINE | J40: Manprec | L40: EURO | M40: CEO | N40: CEO00169 | O40: FALSE | P40: EN CONJUTO EN EL EQUIPO | Q40: ENVIADA | S40: FALSE | U40: FALSE
A41: MAN13825 | B41: 365 | C41: SISTEMA DE MONITORIZACIÓN FISIOLÓGICA PRUEBA DE ESFUERZO | D41: 1 | E41: PZ | F41: SCHILLER | G41: CS-200 EXCELLENCE | H41: 0.035 | I41: SCHILLER | J41: Manprec | K41: 19385 | L41: USD | M41: ITH | N41: ITH00221 | O41: FALSE | Q41: ENVIADA | S41: FALSE | U41: FALSE
C42: BP-200 plus Blood pressure device Non-invasive blood pressure monitor designed to measure automatically and display a patients systolic and diastolic pressure. | D42: 1 | E42: PZ | H42: 0.31 | I42: SCHILLER | J42: Manprec | K42: 3985 | L42: USD | M42: ITH | N42: ITH00222 | O42: FALSE | Q42: ENVIADA | S42: FALSE | U42: FALSE
C43: TREADMILL TMX-428 110 v | D43: 1 | E43: PZ | H43: 2.210046MT | I43: SCHILLER | J43: Manprec | K43: 8980 | L43: USD | M43: ITH | N43: ITH00221 | O43: FALSE | Q43: ENVIADA | S43: FALSE | U43: FALSE
C44: 10-wire patient cable, clip type, 4.6/4.25, AHA | D44: 1 | E44: PZ | H44: 2.400178 | I44: SCHILLER | J44: Manprec | K44: 244 | L44: USD | M44: ITH | N44: ITH00221 | O44: FALSE | Q44: ENVIADA | S44: FALSE | U44: FALSE
C45: Ergo-belt with pouch, black | D45: 1 | E45: PZ | H45: 2.1561 | I45: SCHILLER | J45: Manprec | K45: 86 | L45: USD | M45: ITH | N45: ITH00221 | O45: FALSE | Q45: ENVIADA | S45: FALSE | U45: FALSE
C46: ELECTRODOS DE ECG | D46: 1 | E46: PZ | H46: 31050522 | I46: SCHILLER | J46: Manprec | K46: 25 | L46: USD | M46: ITH | N46: ITH00221 | O46: FALSE | Q46: ENVIADA | S46: FALSE | U46: FALSE
C47: Thermal chart paper AT-102, AT-102 plus, AT-102 G2, CS-200 Excellence, FT-2, thermosensitive, Z-folded, 210 mm wide, 1 package | D47: 5 | E47: C/100 | H47: 2.15705 | I47: SCHILLER | J47: Manprec | K47: 25 | L47: USD | M47: ITH | N47: ITH00221 | O47: FALSE | Q47: ENVIADA | S47: FALSE | U47: FALSE
C48: UPS DE 30 MIN | D48: 1 | E48: PZ | H48: PA MG+15-2200-UN | I48: POWER ALL | J48: Manprec | L48: USD | M48: Gamit | O48: FALSE | S48: FALSE | U48: FALSE
C49: TUBO DE GEL DE 250 ML | D49: 4 | E49: PZ | H49: ALT 040 | I49: PRONAMAC | J49: Manprec | K49: 55.86 | L49: MXN | M49: MPC | N49: MPC05446 | O49: FALSE | Q49: ENVIADA | S49: FALSE | U49: FALSE
A50: MAN13825 | B50: 390 | C50: VENTILADOR ADULTO – PEDIÁTRICO - NEONATAL | D50: 8 | E50: PZ | F50: LÖWENSTEIN | G50: ELISA 800 | H50: 400810 | I50: LÖWENSTEIN | J50: Manprec | L50: EURO | M50: N/A | N50: MAN01176 | O50: FALSE | S50: FALSE | U50: FALSE
C51: Carro de traslado para ventilador / riel estándar DIN para carro (LM-0691005) | D51: 8 | E51: PZ | H51: LM-0691000 | I51: LÖWENSTEIN | J51: Manprec | L51: EURO | M51: N/A | O51: FALSE | P51: DENTRO DEL EQUIPO | S51: FALSE | U51: FALSE
C52: Brazo soporte de circuito de paciente | D52: 8 | E52: PZ | H52: AZ-389121 | I52: LÖWENSTEIN | J52: Manprec | L52: EURO | M52: N/A | O52: FALSE | P52: DENTRO DEL EQUIPO | S52: FALSE | U52: FALSE
C53: Cabezal nebulizador de malla, pieza en T única para cabezal nebulizador | D53: 8 | E53: PZ | H53: CX-370809 CX-370810 | I53: LÖWENSTEIN | J53: Manprec | L53: EURO | M53: N/A | O53: FALSE | P53: DENTRO DEL EQUIPO | S53: FALSE | U53: FALSE
C54: HUMIDIFIER MR850 115V S/P/E US | D54: 8 | E54: PZ | H54: MR850JSU | I54: FISHER | J54: Manprec | L54: MXN | M54: N/A | O54: FALSE | S54: FALSE | U54: FALSE
C55: ADAPTOR MR850 DUAL HTD RT CCT | D55: 8 | E55: PZ | H55: 900MR805 | I55: FISHER | J55: Manprec | L55: MXN | M55: N/A | O55: FALSE | S55: FALSE | U55: FALSE
C56: PROBE TEMP/FLOW RT ANG 1850mm | D56: 16 | E56: PZ | H56: 900MR869 | I56: FISHER | J56: Manprec | L56: MXN | M56: N/A | O56: FALSE | S56: FALSE | U56: FALSE
C57: MOUNTING BRACKET POLE 15-50mm | D57: 8 | E57: PZ | H57: 900MR030 | I57: FISHER | J57: Manprec | L57: MXN | M57: N/A | O57: FALSE | S57: FALSE | U57: FALSE
C58: CIRCUIT KIT ADULT DUAL-HT | D58: 8 | E58: PZ | H58: RT200 | I58: FISHER | J58: Manprec | L58: MXN | M58: N/A | O58: FALSE | S58: FALSE | U58: FALSE
C59: CIRCUIT KIT NEO BIAS-FLOW | D59: 8 | E59: PZ | H59: RT225 | I59: FISHER | J59: Manprec | L59: MXN | M59: N/A | O59: FALSE | S59: FALSE | U59: FALSE
C60: Manguera 3 mts grado médico para Oxigeno con conexión tipo DISS H , US norm | D60: 8 | E60: PZ | H60: NC-1330 | I60: MIYSA | J60: Manprec | L60: MXN | M60: N/A | O60: FALSE | S60: FALSE | U60: FALSE
C61: Manguera 3 mts grado médico para Oxigeno con conexión tipo DISS. US norm | D61: 8 | E61: PZ | H61: NC-1331 | I61: MIYSA | J61: Manprec | L61: MXN | M61: N/A | O61: FALSE | S61: FALSE | U61: FALSE
C62: TOMA DE PARED AIRE | D62: 8 | E62: PZ | H62: XX | I62: MIYSA | J62: Manprec | L62: MXN | M62: N/A | O62: FALSE | S62: FALSE | U62: FALSE
C63: TOMA DE PARED OXIGENO | D63: 8 | E63: PZ | H63: XXX | I63: MIYSA | J63: Manprec | L63: MXN | M63: N/A | O63: FALSE | S63: FALSE | U63: FALSE
C64: Regulador miniatura de baja presión con manometro y conexiónes DISS M in/out NIST H para Oxigeno | D64: 8 | E64: PZ | H64: LS-3130-110 | I64: MIYSA | J64: Manprec | L64: MXN | M64: N/A | O64: FALSE | S64: FALSE | U64: FALSE
C65: Regulador miniatura de baja presión con trampa de agua, filtro para particulas, manometro y conexiónes DISS M in/out NIST H para Aire | D65: 8 | E65: PZ | H65: LS-3231-111 | I65: MIYSA | J65: Manprec | L65: MXN | M65: N/A | O65: FALSE | S65: FALSE | U65: FALSE
C66: Barrierbac ´S´ 22M/15F-22F | D66: =10*8 -> 80 | E66: PZ | H66: 350/5879 | I66: KENDALL | J66: Manprec | L66: MXN | M66: MPC | O66: FALSE | S66: FALSE | U66: FALSE
C67: Pulmón de prueba neonatos 50cc | D67: 8 | E67: PZ | H67: MP20050 | I67: HOSPIINNOVA | J67: Manprec | L67: MXN | M67: N/A | O67: FALSE | S67: FALSE | U67: FALSE
C68: Pulmón de prueba | D68: 8 | E68: PZ | H68: 8403201-07 | I68: HOSPIINNOVA | J68: Manprec | L68: MXN | M68: N/A | O68: FALSE | S68: FALSE | U68: FALSE
C69: M Amara Gel Mask W/ Rs Marco And Hgr Int (PZA) | D69: =20*8 -> 160 | E69: PZ | J69: Manprec | O69: FALSE | S69: FALSE | U69: FALSE
C70: L Amara Gel Msk Se W/Rs Marco And Hg Int | D70: =10*8 -> 80 | E70: PZ | J70: Manprec | O70: FALSE | S70: FALSE | U70: FALSE

Sheet SEDENA T-575
A1: PEDIDO | B1: PARTIDA | C1: DESCRIPCIÓN | D1: CANTIDAD | E1: UDM | F1: MARCA | G1: MODELO | H1: CÓDIGO | I1: PROVEEDOR | J1: Empresa que vende | K1: COSTO | L1: MONEDA COSTO | M1: EMPRESA QUE COMPRA | N1: OC | O1: B2B | P1: OBSERVACIONES | Q1: ESTATUS | R1: OV-INT | S1: Status de Interempresa | T1: OC-INT | U1: Status de Interempresa
A2: MPC23134 | B2: 31 | C2: EQUIPO DE RAYOS X FIJO | D2: 1 | F2: ITALRAY | G2: XFRAME | H2: AMR+IR313-B | I2: ITALRAY | J2: MPC | L2: EURO | O2: FALSE | Q2: - | S2: FALSE | U2: FALSE
C3: Mandil Emplomado Para Rayos X Con Cinta Marca Shielding | D3: 1 | H3: JDS536 | I3: NAFARRATE | J3: MPC | L3: MXN | O3: FALSE | S3: FALSE | U3: FALSE
C4: GOGGLES EMPLOMADOS. | D4: 1 | H4: JD53 | I4: NAFARRATE | J4: MPC | L4: MXN | O4: FALSE | S4: FALSE | U4: FALSE
C5: PROTECTOR DE TIROIDES | D5: 1 | H5: JD611NSL | I5: NAFARRATE | J5: MPC | L5: MXN | O5: FALSE | S5: FALSE | U5: FALSE
C6: PROTECTOR DE GONADAS. | D6: 1 | H6: JD806L | I6: NAFARRATE | J6: MPC | L6: MXN | O6: FALSE | S6: FALSE | U6: FALSE
C7: porta chalecos | D7: 2 | H7: 531.695.0061 | I7: VE-GA | J7: MPC | L7: MXN | O7: FALSE | S7: FALSE | U7: FALSE
C8: Un sistema de alimentación ininterrumpida (UPS) para RX | D8: 1 | J8: MPC | L8: USD | O8: FALSE | S8: FALSE | U8: FALSE
C9: Un sistema de alimentación ininterrumpida (UPS) estacion de adquisicion | D9: 1 | J9: MPC | L9: USD | O9: FALSE | S9: FALSE | U9: FALSE
C10: Aire acondicionado media tonelada | D10: 1 | J10: MPC | L10: MXN | O10: FALSE | S10: FALSE | U10: FALSE
A11: MPC23134 | B11: 44 | C11: LÁMPARA QUIRÚRGICA PORTÁTIL PARA EMERGENCIA. | D11: 6 | F11: RIMSA | G11: PENTALED 30EL | H11: PENTA30ELPI | I11: RIMSA | J11: MPC | L11: EURO | O11: FALSE | Q11: - | S11: FALSE | U11: FALSE
C12: Manija para lámpara | D12: 6 | F12: RIMSA | H12: Z200518 | I12: RIMSA | J12: MPC | L12: EURO | O12: FALSE | P12: incluidos en el equipo | Q12: - | S12: FALSE | U12: FALSE
O13: FALSE | Q13: - | S13: FALSE | U13: FALSE
O14: FALSE | Q14: - | S14: FALSE | U14: FALSE
O15: FALSE | Q15: - | S15: FALSE | U15: FALSE
O16: FALSE | Q16: - | S16: FALSE | U16: FALSE
O17: FALSE | Q17: - | S17: FALSE | U17: FALSE
O18: FALSE | Q18: - | S18: FALSE | U18: FALSE
O19: FALSE | Q19: - | S19: FALSE | U19: FALSE
O20: FALSE | Q20: - | S20: FALSE | U20: FALSE
O21: FALSE | Q21: - | S21: FALSE | U21: FALSE
O22: FALSE | Q22: - | S22: FALSE | U22: FALSE
O23: FALSE | Q23: - | S23: FALSE | U23: FALSE
O24: FALSE | Q24: - | S24: FALSE | U24: FALSE
... O27: FALSE | Q27: - | S27: FALSE | U27: FALSE

Sheet IMSS NUEVO LEON T-66
A1: PEDIDO | B1: PARTIDA | C1: DESCRIPCIÓN | D1: CANTIDAD | E1: UDM | F1: MARCA | G1: MODELO | H1: CÓDIGO | I1: PROVEEDOR | J1: Empresa que vende | K1: COSTO | L1: MONEDA COSTO | M1: EMPRESA QUE COMPRA | N1: OC | O1: B2B | P1: OBSERVACIONES | Q1: ESTATUS | R1: OV-INT | S1: Status de Interempresa | T1: OC-INT | U1: Status de Interempresa
B2: PARTIDA 13 RED DE FRÍO | C2: CONGELADOR HORIZONTAL DE REFRIGERANTES PARA VACUNAS | D2: 2 | E2: PZ | F2: REFRIMED | G2: CH-5 | H2: CH-5 | I2: REFRIMED | J2: MPC | K2: 18895 | L2: MXN | M2: MPC | N2: MPC05443 | O2: FALSE | Q2: - | S2: FALSE | U2: FALSE
B3: PARTIDA 13 RED DE FRÍO | C3: REFRIGERADOR CONGELADOR DE 5.4 PIES CÚBICOS | D3: 1 | E3: PZ | F3: REFRIMED | G3: RVASCV-5.4 | H3: RVASCV-5.4 | I3: REFRIMED | J3: MPC | K3: 48059.79 | L3: MXN | M3: MPC | N3: MPC05443 | O3: FALSE | Q3: - | S3: FALSE | U3: FALSE
B4: PARTIDA 13 RED DE FRÍO | C4: REFRIGERADOR PARA VACUNAS | D4: 3 | E4: PZ | F4: REFRIMED | G4: RVASCV-17.6 | H4: RVASCV-17.6 | I4: REFRIMED | J4: MPC | K4: 78853.3 | L4: MXN | M4: MPC | N4: MPC05443 | O4: FALSE | Q4: - | S4: FALSE | U4: FALSE
B5: PARTIDA 13 RED DE FRÍO | C5: REFRIGERADOR PARA REACTIVOS Y PRODUCTOS BIOLÓGICOS | D5: 1 | E5: PZ | F5: REFRIMED | G5: RVCCDV-14 | H5: RVCCDV-14 | I5: REFRIMED | J5: MPC | K5: 72836.6 | L5: MXN | M5: MPC | N5: MPC05443 | O5: FALSE | Q5: - | S5: FALSE | U5: FALSE
O6: FALSE | Q6: - | S6: FALSE | U6: FALSE
O7: FALSE | Q7: - | S7: FALSE | U7: FALSE
O8: FALSE | Q8: - | S8: FALSE | U8: FALSE
O9: FALSE | Q9: - | S9: FALSE | U9: FALSE
O10: FALSE | Q10: - | S10: FALSE | U10: FALSE
O11: FALSE | Q11: - | S11: FALSE | U11: FALSE
O12: FALSE | Q12: - | S12: FALSE | U12: FALSE
O13: FALSE | Q13: - | S13: FALSE | U13: FALSE
O14: FALSE | Q14: - | S14: FALSE | U14: FALSE
O15: FALSE | Q15: - | S15: FALSE | U15: FALSE
O16: FALSE | Q16: - | S16: FALSE | U16: FALSE
O17: FALSE | Q17: - | S17: FALSE | U17: FALSE
... O19: FALSE | Q19: - | S19: FALSE | U19: FALSE

Sheet Hoja 30
A1: PEDIDO | B1: PARTIDA | C1: DESCRIPCIÓN | D1: CANTIDAD | E1: UDM | F1: MARCA | G1: MODELO | H1: CÓDIGO | I1: PROVEEDOR | J1: Empresa que vende | K1: COSTO | L1: MONEDA COSTO | M1: EMPRESA QUE COMPRA | N1: OC | O1: B2B | P1: OBSERVACIONES | Q1: ESTATUS | R1: OV-INT | S1: Status de Interempresa | T1: OC-INT | U1: Status de Interempresa
O2: FALSE | Q2: - | S2: FALSE | U2: FALSE
O3: FALSE | Q3: - | S3: FALSE | U3: FALSE
O4: FALSE | Q4: - | S4: FALSE | U4: FALSE
O5: FALSE | Q5: - | S5: FALSE | U5: FALSE
O6: FALSE | Q6: - | S6: FALSE | U6: FALSE
O7: FALSE | Q7: - | S7: FALSE | U7: FALSE
O8: FALSE | Q8: - | S8: FALSE | U8: FALSE
O9: FALSE | Q9: - | S9: FALSE | U9: FALSE
O10: FALSE | Q10: - | S10: FALSE | U10: FALSE
O11: FALSE | Q11: - | S11: FALSE | U11: FALSE
O12: FALSE | Q12: - | S12: FALSE | U12: FALSE
O13: FALSE | Q13: - | S13: FALSE | U13: FALSE
... O19: FALSE | Q19: - | S19: FALSE | U19: FALSE

Sheet Hoja 31
